Workbook

Sheet 2022 Charity (2)
A1: Group | D1: Company | E1: Corporate Key | F1: User Name | G1: Password | H1: What City was i born in? | I1: Answer | J1: Email | K1: ACN | L1: abn | M1: TFN | N1: Established Date | O1: Director | P1: Review Date | Q1: Amount Owing | R1: Amount of Shares | S1: Shareholder | T1: Registered | U1: Principle Place of Business
A2: Charity | B2: XERO | D2: Homes of Hope Limited | E2: 99406654 | F2: homesofhopeltd | G2: Bl3ss3d. | H2: What City was I Born In? | I2: Adelaide | J2: hello@joii.org.au | K2: 643 194 156 | L2: 22 643 194 156 | M2: 639 296 766 | N2: 44047 | O2: David , David and Aaron | P2: 44294 | Q2: 0 | R2: Public | T2: OFFICE 6 / 2404 LOGAN ROAD EIGHT MILE PLAINS QLD 4113 | U2: 46 Aspire Street Rochedale Qld 4123
A3: Charity | B3: nothing | D3: Impact Homes Pty Ltd (formerly Whoa2Go) | E3: ordered | K3: 093 693 415 | L3: 25 093 693 415 | M3: 773 195 351 | N3: 44025 | O3: Aaron Glowka | P3: 13/07/2022 | Q3: 0 | R3: 100 | S3: Homes Of Hope | T3: OFFICE 6 / 2404 LOGAN ROAD EIGHT MILE PLAINS QLD 4113 | U3: 46 Aspire Street Rochedale Qld 4123
A4: Charity | B4: XERO | D4: Livin The Dream | E4: 72943215 | F4: livinthedream | G4: Bl3ss3d. | H4: What City was I Born In? | I4: Adelaide | J4: hello@joii.org.au | K4: 142 372 245 | L4: 95 142 372 245 | M4: 913 810 842 | N4: 40240 | O4: James Jonathan Harder | P4: 44988 | Q4: 688 | R4: 100 | S4: Homes Of Hope | T4: OFFICE 6 / 2404 LOGAN ROAD EIGHT MILE PLAINS QLD 4113 | U4: 46 Aspire Street Rochedale Qld 4123
A5: Charity | B5: XERO | D5: Love Your World | E5: ordered | K5: 158 841 180 | L5: 91 158 841 180 | M5: 942 944 937 | N5: 41066 | O5: David , David and Aaron | P5: 42892 | Q5: 0 | R5: Public | T5: OFFICE 6 / 2404 LOGAN ROAD EIGHT MILE PLAINS QLD 4114 | U5: 46 Aspire Street Rochedale Qld 4123
A6: Charity | B6: XERO | C6: Strike Off | D6: Next Steps Global | E6: 40617621 | F6: nextstepsglobalptyltd | G6: Bl3ss3d. | H6: What City was I Born In? | I6: Adelaide | J6: hello@joii.org.au | K6: 629 932 887 | L6: 13 629 932 887 | M6: 570 952 809 | N6: 43414 | O6: Robert harder | P6: 44845 | Q6: -82 | R6: 100 | S6: Homes Of Hope | T6: OFFICE 6 / 2404 LOGAN ROAD EIGHT MILE PLAINS QLD 4114 | U6: 46 Aspire Street Rochedale Qld 4123
A7: Charity | B7: XERO | C7: Strike Off | D7: The Promise Qld | E7: ordered | K7: 158 275 640 | L7: 53 158 275 640 | M7: 935 906 938 | N7: 41187 | O7: Rachel Harder | P7: 45204 | Q7: 276 | R7: 100 | S7: Love Your World | T7: OFFICE 6 / 2404 LOGAN ROAD EIGHT MILE PLAINS QLD 4114 | U7: 46 Aspire Street Rochedale Qld 4123
A9: Charity | B9: R and D | C9: Strike Off | D9: Money Maid (formerly Harder Money) | K9: 159 631 240 | L9: 77 159 631 240 | M9: 938 235 185 | N9: 25/07/2012 | O9: James Jonathan Harder | P9: 44767 | R9: 100 | S9: Money Matters 20, OPen Gold 16, Joii 25 adn Duncan Miller 39 | T9: OFFICE 6 / 2404 LOGAN ROAD EIGHT MILE PLAINS QLD 4114 | U9: OFFICE 6 / 2404 LOGAN ROAD EIGHT MILE PLAINS QLD 4114
A10: Charity | B10: R and D | C10: Want to close | D10: Money Matters | K10: 605 103 615 | L10: 63 605 103 615 | M10: 635 209 293 | N10: 42095 | O10: Aaron Glowka | P10: 45017 | R10: 100 | S10: Love Your World | T10: OFFICE 6 / 2404 LOGAN ROAD EIGHT MILE PLAINS QLD 4114 | U10: OFFICE 6 / 2404 LOGAN ROAD EIGHT MILE PLAINS QLD 4114

Sheet 2022 Team Harder (2)
A1: Group | C1: Company | D1: Corporate Key | E1: User Name | F1: Password | G1: What City was i born in? | H1: Answer | I1: Carry Forward losses | J1: Franking Balance | K1: Bank Name | L1: BSB | M1: Account | N1: ACN | O1: abn | P1: TFN | Q1: Established Date | R1: Director | S1: Review Date | T1: Amount Owing | U1: Amount of Shares | V1: Shareholder | W1: Registered | X1: Principle Place of Business | Y1: Activity | Z1: what to Do
A2: 485 | B2: MYOB | C2: A Clement Developments Qld | N2: 138 613 046 | O2: 95 138 613 046 | P2: 938 926 367 | Q2: 31/07/2009 | R2: Robert Harder | U2: 2 | V2: Andrew and Ruth | W2: OFFICE 6 / 2404 LOGAN ROAD EIGHT MILE PLAINS QLD 4113 | X2: 46 Aspire Street Rochedale Qld 4123 | Y2: this is for Andrews Family Trust | Z2: Close If Possible
A3: 485 | B3: nothing | C3: Harder Developments Pty Ltd | N3: 073 411 275 | O3: not registered | Q3: 26/03/1996 | R3: Robert Harder | S3: Not Keeping | U3: 2 | V3: Rachel Harder | W3: OFFICE 6 / 2404 LOGAN ROAD EIGHT MILE PLAINS QLD 4113 | X3: 46 Aspire Street Rochedale Qld 4123 | Y3: old trustee th eharder family trust and did some share trading | Z3: Close If Possible
A4: Deregister | C4: JRKA Pty Ltd | I4: Deregister this company | N4: 635 352 671
A5: Team Harder | B5: XERO | C5: Gen2612 | K5: Gen2612 | L5: 84435 | M5: 767243550 | N5: 658 463 659 | O5: 47 658 463 659 | P5: 605 934 566 | Q5: 31/03/2022 | R5: Rachel harder | S5: 31/03/2023 | T5: 0 | U5: 100 | V5: ATF Team Harder Family Trust | W5: OFFICE 6 / 2404 LOGAN ROAD EIGHT MILE PLAINS QLD 4113 | X5: 160 ALPERTON ROAD , BURBANK QLD 4156 , Australia | Y5: Bucket Company
A6: Team Harder | B6: nothing | C6: Harder Family | D6: 13631732 | E6: harderfamilyrach | F6: Bl3ss3d. | G6: What City was i born in? | H6: Adelaide | N6: 159 632 087 | O6: 71 159 632 087 | P6: 939 058 021 | Q6: 25/07/2012 | R6: Rachel harder | S6: 45132 | T6: 0 | U6: 100 | V6: Rachel Harder | W6: OFFICE 6 / 2404 LOGAN ROAD EIGHT MILE PLAINS QLD 4113 | X6: 160 ALPERTON ROAD , BURBANK QLD 4156 , Australia | Y6: Trustee for The Harder Family Trust
A7: Team Harder | B7: XERO | C7: Harder Family ATF The Harder Family Trust | K7: The Harder Family Trust | L7: 084 435 | M7: 239941312 | O7: 20 459 034 329 | P7: 77 583 528 | Y7: Family Trust
A8: Team Harder | C8: Prov1322 Global | N8: 658 602 478 | O8: 34 658 602 478 | P8: 606 189 260 | Q8: 44716 | R8: Rachel Harder | S8: 45081 | T8: 0 | U8: 100 | V8: Rachel Harder | W8: OFFICE 6 / 2404 LOGAN ROAD EIGHT MILE PLAINS QLD 4113 | X8: 160 ALPERTON ROAD , BURBANK QLD 4156 , Australia
A9: Team Harder | B9: XERO | C9: Prov1322 Global ATF Team Harder Family Trust | K9: Team Harder Family Trust | L9: 084 435 | M9: 959276787 | O9: 94 633 472 433 | P9: 605 725 602 | Y9: Family Trust
A10: Team Harder | B10: XERO | C10: LATL | D10: 82704061 | E10: hello@lyw.org.au | F10: Bl3ss3d. | G10: What City was i born in? | H10: Adelaide | K10: LATL | L10: 084 435 | M10: 711090276 | N10: 145 576 138 | O10: 68 145 576 138 | P10: 918 281 149 | Q10: 40245 | R10: Rachel harder | S10: 44993 | T10: 0 | U10: 100 | V10: ATF The Harder Family Trust | W10: OFFICE 6 / 2404 LOGAN ROAD EIGHT MILE PLAINS QLD 4113 | X10: 160 ALPERTON ROAD , BURBANK QLD 4156 , Australia | Y10: Bucket Company
A11: Team Harder | C11: Robert Harder | O11: 93 373 928 858 | P11: 173 955 316
A12: Team Harder | C12: Rachel Harder | P12: 171 927 425
A13: Team Harder | C13: Jared Harder
A14: Team Harder | C14: Grace Harder
A15: Team Harder | C15: Sophie Harder
A16: Team Harder Super Fund GROUP | C16: Team Harder | N16: 645 359 495 | Q16: 23/10/2020 | R16: Rob and Rach | S16: 45222 | T16: 620 | U16: 100 | V16: Robert and Rachel | W16: OFFICE 6 / 2404 LOGAN ROAD EIGHT MILE PLAINS QLD 4113 | X16: OFFICE 6 / 2404 LOGAN ROAD EIGHT MILE PLAINS QLD 4113
A17: Team Harder Super Fund GROUP | B17: Dave | C17: Team Harder ATF Team Harder Super Fund | K17: Team Harder Super Fund | L17: 083 052 | M17: 304656703 | O17: 17 209 120 631 | P17: 534 254 470
A18: Team Harder Super Fund GROUP | B18: nothing | C18: Team Harder Super Investments | K18: Team Harder Super Investments | L18: 084 435 | M18: 259449309 | N18: 658 706 597 | O18: 32 658 706 597 | P18: 608 117 219 | Q18: 44662 | R18: Rachel Harder | S18: 45027 | T18: 0 | U18: 100 | V18: ATF Team Harder Super Fund | W18: OFFICE 6 / 2404 LOGAN ROAD EIGHT MILE PLAINS QLD 4113 | X18: 160 ALPERTON ROAD , BURBANK QLD 4156 , Australia | Y18: Investment for Super Fund
A19: Team Harder Super Fund GROUP | B19: MYOB | C19: AR Clement Investments | D19: ordered | K19: Team Harder Super Investments | L19: 084 435 | M19: 259449309 | N19: 145 575 659 | O19: 42 145 575 659 | P19: 918 280 369 | Q19: 40393 | R19: Rachel harder | S19: 45141 | T19: 0 | W19: OFFICE 6 / 2404 LOGAN ROAD EIGHT MILE PLAINS QLD 4113 | X19: 160 ALPERTON ROAD , BURBANK QLD 4156 , Australia | Y19: this is to do developments in going forward
A20: Team Harder Super Fund GROUP | B20: MYOB | C20: JRANDL Pty Ltd | D20: ordered | K20: JRANDL | L20: 084 435 | M20: 239209244 | N20: 610 667 555 | O20: 55 610 667 555 | P20: 977 018 668 | Q20: 42410 | R20: Rachel Harder | S20: 44967 | T20: 620 | U20: 4300000 | V20: Team Harder Super Investments | W20: OFFICE 6 / 2404 LOGAN ROAD EIGHT MILE PLAINS QLD 4113 | X20: 160 ALPERTON ROAD , BURBANK QLD 4156 , Australia | Y20: grouping THSI
A21: Team Harder Super Fund GROUP | B21: XERO | C21: W2G Assets | D21: 87081049 | E21: w2gasset | F21: Bl3ss3d. | G21: What City was I Born In? | H21: Adelaide | I21: hello@joii.org.au | J21: 092 659 688 | K21: 59 092 659 688 | L21: 726 881 624 | M21: 36655 | N21: 092 659 688 | O21: 59 092 659 688 | P21: 726 881 624 | Q21: 36655 | R21: Rachel Harder | S21: 45055 | T21: 276 | U21: 1000 | V21: Love Your World | W21: OFFICE 6 / 2404 LOGAN ROAD EIGHT MILE PLAINS QLD 4114 | X21: 160 ALPERTON ROAD , BURBANK QLD 4156 , Australia
C22: Property Alternative (AUS) Pty Ltd | N22: 610 974 019 | O22: 34 610 974 019 | P22: 986 555 939 | Q22: 25/02/2016 | R22: Robert Harder
P26: Harder Family
C32: 1432010
C33: 142406
C34: =C32+C33 -> 1574416

Sheet StatementImportTemplate.en-US
A1: *Date | B1: *Amount | C1: Payee | D1: Description | E1: Reference | F1: Check Number

Sheet Co Invest Homes
B1: All Companies
J2: Loan Agreement | K2: Things that must be filed | L2: 2024
B3: Co Invest Homes Pty Ltd | J3: Security Deed | K3: If is a discresionary trust , need to make the trust distribution every year before 30th June
B4: ACN: | C4: 691 269 333 | D4: ABN: | E4: 31691269333 | G4: TFN: | H4: 241641326 | J4: Company Setup | K4: All Bank Statement for the year
B5: Date Incorporated | C5: 45924 | F5: Shares on Issue | G5: 100 | J5: Solvency ASIC | K5: all assets purchases receipts
B6: Purpose: | C6: Co Invest into Homes | F6: Is it a Trustee | J6: Constitution | K6: all sales of assets
B7: Trust Name / Trustee | J7: Members | K7: all distribution if company
B8: Registered office | C8: 160 Alperton Road, Burbank QLD 4156 | F8: Principal place of business | J8: Structure | K8: all company minutes
D9: From | J9: ATO Tax Return | K9: ASIC showing company info on 30th june
B10: Current Director | C10: Rachel Anne Harder | D10: Jake Stanley Baird | J10: Asset | K10: All ASIC Documents
B11: Current Secretary | C11: Rachel Anne Harder | J11: Dividends | K11: Company Tax Return
J12: EOY ATO | K12: Company ATO due
B13: Does this Company have Loans | C13: No | F13: Is there loan documents in place | G13: No | J13: Registered Office
E14: Shares | F14: Beneficially Held | J14: Officers
B15: Current Shareholdings | C15: The Promise QLD | D15: Ordinary | E15: 67 | F15: Yes | G15: The Promise Family Trust | J15: Bank Statements
C16: The Promise QLD | D16: Class A | E16: 322 | F16: Yes | G16: The Promise Family Trust
C17: The Promise QLD | D17: Ordinary | E17: 67 | F17: Yes | G17: The Promise Family Trust
C18: The Promise QLD | D18: Class A | E18: 322 | F18: Yes | G18: The Promise Family Trust
J20: Minutes
B21: Current Bank Accounts | C21: Bank | D21: BSB | E21: Account | F21: Date Opened | J21: Distribution
C22: Westpac | D22: 034-093 | E22: 958183 | F22: 13.11.2025 | J22: EOY ASIC
J23: PPSR
J24: Tax Consolidation
J25: Trust Deed
B28: Folder Storage | C28: Co Invest Homes | D28: Abbreviation | E28: CIH
B30: Company Register | C30: Type | D30: Folder | E30: Date | F30: Manual | G30: Electronicaly Stored | H30: By Whom
D31: =VLOOKUP(C31,'Document Type'!$B$6:$C$34,2,FALSE) -> #N/A
D32: =VLOOKUP(C32,'Document Type'!$B$6:$C$34,2,FALSE) -> #N/A
D33: =VLOOKUP(C33,'Document Type'!$B$6:$C$34,2,FALSE) -> #N/A
D34: =VLOOKUP(C34,'Document Type'!$B$6:$C$34,2,FALSE) -> #N/A
D35: =VLOOKUP(C35,'Document Type'!$B$6:$C$34,2,FALSE) -> #N/A
D36: =VLOOKUP(C36,'Document Type'!$B$6:$C$34,2,FALSE) -> #N/A
D37: =VLOOKUP(C37,'Document Type'!$B$6:$C$34,2,FALSE) -> #N/A
D38: =VLOOKUP(C38,'Document Type'!$B$6:$C$34,2,FALSE) -> #N/A
D39: =VLOOKUP(C39,'Document Type'!$B$6:$C$34,2,FALSE) -> #N/A
D40: =VLOOKUP(C40,'Document Type'!$B$6:$C$34,2,FALSE) -> #N/A
D41: =VLOOKUP(C41,'Document Type'!$B$6:$C$34,2,FALSE) -> #N/A
D42: =VLOOKUP(C42,'Document Type'!$B$6:$C$34,2,FALSE) -> #N/A
... D65: =VLOOKUP(C65,'Document Type'!$B$6:$C$34,2,FALSE) -> #N/A
B66: Certifcate of Registration | C66: Company Setup | D66: =VLOOKUP(C66,'Document Type'!$B$6:$C$34,2,FALSE) -> Company Setup | E66: 45924 | F66: no | G66: Certifcate of registration - Co Invest Homes.pdf | H66: Robert
B67: Tax File Number | C67: Company Setup | D67: =VLOOKUP(C67,'Document Type'!$B$6:$C$34,2,FALSE) -> Company Setup | E67: 45899 | G67: Co Invest Homes Tax File Number | H67: Rachel
D68: =VLOOKUP(C68,'Document Type'!$B$6:$C$34,2,FALSE) -> #N/A
B69: Register of Members
B70: Date | C70: Issue, transfer,share split, buy back or Cancelation | D70: Class of Share | E70: Certification Number | F70: Serial Number From | G70: Serial Number To | H70: Number of Shares Aquired | I70: Trf'd to / Trf'd from | J70: Amount Paid Per Share | K70: Amount Unpaid per Share | L70: Fully Paid? (Y/N) | M70: Total Number os Shares Held | N70: Total Amount paid fo the shares | O70: Are the Shares Benedicially Held | P70: Owner / Buyer / Seller | Q70: ASIC Document Number
B97: 45924 | C97: Issue | D97: Ordinary | E97: 1 | F97: 1 | G97: 1 | H97: 100 | J97: 0.01 | K97: 0 | L97: Y | M97: 100 | N97: 1 | O97: Y | P97: The Promise QLD ATF The Promise Family Trust
B99: Register of Loans
B100: From | C100: To | D100: Amount | E100: Date | F100: Security | G100: PPSR
B108: Register of Assets - Non Trading
B109: Item | C109: Purchase Date | D109: Purchase Price | E109: Sale Date | F109: Sale Price | G109: Depreciation | H109: Profit
H110: =Table79136165[[#This Row],[Sale Price]]-Table79136165[[#This Row],[Purchase Price]]+Table79136165[[#This Row],[Depreciation]] -> 0
H111: =Table79136165[[#This Row],[Sale Price]]-Table79136165[[#This Row],[Purchase Price]]+Table79136165[[#This Row],[Depreciation]] -> 0
H112: =Table79136165[[#This Row],[Sale Price]]-Table79136165[[#This Row],[Purchase Price]]+Table79136165[[#This Row],[Depreciation]] -> 0
H113: =Table79136165[[#This Row],[Sale Price]]-Table79136165[[#This Row],[Purchase Price]]+Table79136165[[#This Row],[Depreciation]] -> 0
H114: =Table79136165[[#This Row],[Sale Price]]-Table79136165[[#This Row],[Purchase Price]]+Table79136165[[#This Row],[Depreciation]] -> 0
H115: =Table79136165[[#This Row],[Sale Price]]-Table79136165[[#This Row],[Purchase Price]]+Table79136165[[#This Row],[Depreciation]] -> 0
H116: =Table79136165[[#This Row],[Sale Price]]-Table79136165[[#This Row],[Purchase Price]]+Table79136165[[#This Row],[Depreciation]] -> 0
H117: =Table79136165[[#This Row],[Sale Price]]-Table79136165[[#This Row],[Purchase Price]]+Table79136165[[#This Row],[Depreciation]] -> 0
H118: =Table79136165[[#This Row],[Sale Price]]-Table79136165[[#This Row],[Purchase Price]]+Table79136165[[#This Row],[Depreciation]] -> 0
H119: =Table79136165[[#This Row],[Sale Price]]-Table79136165[[#This Row],[Purchase Price]]+Table79136165[[#This Row],[Depreciation]] -> 0
H120: =Table79136165[[#This Row],[Sale Price]]-Table79136165[[#This Row],[Purchase Price]]+Table79136165[[#This Row],[Depreciation]] -> 0
H121: =Table79136165[[#This Row],[Sale Price]]-Table79136165[[#This Row],[Purchase Price]]+Table79136165[[#This Row],[Depreciation]] -> 0
... H127: =Table79136165[[#This Row],[Sale Price]]-Table79136165[[#This Row],[Purchase Price]]+Table79136165[[#This Row],[Depreciation]] -> 0

Sheet Co Invest Capital
B1: All Companies
J2: Loan Agreement | K2: Things that must be filed | L2: 2024
B3: Co Invest Capital Pty Ltd | J3: Security Deed | K3: If is a discresionary trust , need to make the trust distribution every year before 30th June
B4: ACN: 691 268 452 | D4: ABN: | G4: TFN: | J4: Company Setup | K4: All Bank Statement for the year
B5: Date Incorporated | C5: 45924 | F5: Shares on Issue | G5: 100 | J5: Solvency ASIC | K5: all assets purchases receipts
B6: Purpose: | C6: Get an ACL Licence | F6: Is it a Trustee | J6: Constitution | K6: all sales of assets
B7: Trust Name / Trustee | J7: Members | K7: all distribution if company
B8: Registered office | C8: 160 Alperton Road, Burbank QLD 4156 | F8: Principal place of business | J8: Structure | K8: all company minutes
D9: From | J9: ATO Tax Return | K9: ASIC showing company info on 30th june
B10: Current Director | C10: Rachel Anne Harder | J10: Asset | K10: All ASIC Documents
B11: Current Secretary | C11: Rachel Anne Harder | J11: Dividends | K11: Company Tax Return
J12: EOY ATO | K12: Company ATO due
B13: Does this Company have Loans | C13: No | F13: Is there loan documents in place | G13: No | J13: Registered Office
E14: Shares | F14: Beneficially Held | J14: Officers
B15: Current Shareholdings | C15: The Promise QLD | E15: 100 | F15: Yes | J15: Bank Statements
J16: Minutes
B17: Current Bank Accounts | C17: Bank | D17: BSB | E17: Account | F17: Date Opened | J17: Distribution
J18: EOY ASIC
J19: PPSR
J20: Tax Consolidation
J21: Trust Deed
B24: Folder Storage | C24: Co Invest Capital | D24: Abbreviation | E24: CIC
B26: Company Register | C26: Type | D26: Folder | E26: Date | F26: Manual | G26: Electronicaly Stored | H26: By Whom
D27: =VLOOKUP(C27,'Document Type'!$B$6:$C$34,2,FALSE) -> #N/A
D28: =VLOOKUP(C28,'Document Type'!$B$6:$C$34,2,FALSE) -> #N/A
D29: =VLOOKUP(C29,'Document Type'!$B$6:$C$34,2,FALSE) -> #N/A
D30: =VLOOKUP(C30,'Document Type'!$B$6:$C$34,2,FALSE) -> #N/A
D31: =VLOOKUP(C31,'Document Type'!$B$6:$C$34,2,FALSE) -> #N/A
D32: =VLOOKUP(C32,'Document Type'!$B$6:$C$34,2,FALSE) -> #N/A
D33: =VLOOKUP(C33,'Document Type'!$B$6:$C$34,2,FALSE) -> #N/A
D34: =VLOOKUP(C34,'Document Type'!$B$6:$C$34,2,FALSE) -> #N/A
D35: =VLOOKUP(C35,'Document Type'!$B$6:$C$34,2,FALSE) -> #N/A
D36: =VLOOKUP(C36,'Document Type'!$B$6:$C$34,2,FALSE) -> #N/A
D37: =VLOOKUP(C37,'Document Type'!$B$6:$C$34,2,FALSE) -> #N/A
D38: =VLOOKUP(C38,'Document Type'!$B$6:$C$34,2,FALSE) -> #N/A
... D61: =VLOOKUP(C61,'Document Type'!$B$6:$C$34,2,FALSE) -> #N/A
B62: Certifcate of Registration | C62: Company Setup | D62: =VLOOKUP(C62,'Document Type'!$B$6:$C$34,2,FALSE) -> Company Setup | E62: 45924 | F62: no | G62: Certificate of Registration - Co Invest Capital.pdf | H62: Robert
B64: Register of Members
B65: Date | C65: Issue, transfer,share split, buy back or Cancelation | D65: Class of Share | E65: Certification Number | F65: Serial Number From | G65: Serial Number To | H65: Number of Shares Aquired | I65: Trf'd to / Trf'd from | J65: Amount Paid Per Share | K65: Amount Unpaid per Share | L65: Fully Paid? (Y/N) | M65: Total Number os Shares Held | N65: Total Amount paid fo the shares | O65: Are the Shares Benedicially Held | P65: Owner / Buyer / Seller | Q65: ASIC Document Number
B92: 45924 | C92: Issue | D92: Ordinary | E92: 1 | F92: 1 | G92: 1 | H92: 100 | J92: 0.01 | K92: 0 | L92: Y | M92: 100 | N92: 1 | O92: Y | P92: The Promise QLD ATF The Promise Family Trust
B94: Register of Loans
B95: From | C95: To | D95: Amount | E95: Date | F95: Security | G95: PPSR
B103: Register of Assets - Non Trading
B104: Item | C104: Purchase Date | D104: Purchase Price | E104: Sale Date | F104: Sale Price | G104: Depreciation | H104: Profit
H105: =Table791361[[#This Row],[Sale Price]]-Table791361[[#This Row],[Purchase Price]]+Table791361[[#This Row],[Depreciation]] -> 0
H106: =Table791361[[#This Row],[Sale Price]]-Table791361[[#This Row],[Purchase Price]]+Table791361[[#This Row],[Depreciation]] -> 0
H107: =Table791361[[#This Row],[Sale Price]]-Table791361[[#This Row],[Purchase Price]]+Table791361[[#This Row],[Depreciation]] -> 0
H108: =Table791361[[#This Row],[Sale Price]]-Table791361[[#This Row],[Purchase Price]]+Table791361[[#This Row],[Depreciation]] -> 0
H109: =Table791361[[#This Row],[Sale Price]]-Table791361[[#This Row],[Purchase Price]]+Table791361[[#This Row],[Depreciation]] -> 0
H110: =Table791361[[#This Row],[Sale Price]]-Table791361[[#This Row],[Purchase Price]]+Table791361[[#This Row],[Depreciation]] -> 0
H111: =Table791361[[#This Row],[Sale Price]]-Table791361[[#This Row],[Purchase Price]]+Table791361[[#This Row],[Depreciation]] -> 0
H112: =Table791361[[#This Row],[Sale Price]]-Table791361[[#This Row],[Purchase Price]]+Table791361[[#This Row],[Depreciation]] -> 0
H113: =Table791361[[#This Row],[Sale Price]]-Table791361[[#This Row],[Purchase Price]]+Table791361[[#This Row],[Depreciation]] -> 0
H114: =Table791361[[#This Row],[Sale Price]]-Table791361[[#This Row],[Purchase Price]]+Table791361[[#This Row],[Depreciation]] -> 0
H115: =Table791361[[#This Row],[Sale Price]]-Table791361[[#This Row],[Purchase Price]]+Table791361[[#This Row],[Depreciation]] -> 0
H116: =Table791361[[#This Row],[Sale Price]]-Table791361[[#This Row],[Purchase Price]]+Table791361[[#This Row],[Depreciation]] -> 0
... H122: =Table791361[[#This Row],[Sale Price]]-Table791361[[#This Row],[Purchase Price]]+Table791361[[#This Row],[Depreciation]] -> 0

Sheet W2G
B1: All Companies
J2: Loan Agreement | K2: Things that must be filed | L2: 2024
B3: W2G Assets Pty Ltd | J3: Security Deed | K3: If is a discresionary trust , need to make the trust distribution every year before 30th June
B4: ACN: | C4: 092 659 688 | D4: ABN: | E4: 59 092 659 688 | G4: TFN: | H4: 726 881 624 | J4: Company Setup | K4: All Bank Statement for the year
B5: Date Incorporated | C5: 36655 | F5: Shares on Issue | G5: 1000 | J5: Solvency ASIC | K5: all assets purchases receipts
B6: Purpose: | F6: Is it a Trustee | G6: No | J6: Constitution | K6: all sales of assets
B7: Trust Name / Trustee | J7: Members | K7: all distribution if company
B8: Registered office | C8: MAGNUS BUSINESS ADVISERS AND ACCOUNTANTS, UNIT 10 , 39 OLD CLEVELAND ROAD , CAPALABA QLD 4157 | F8: Principal place of business | G8: 160 Alperton Road, Burbank QLD 4156 | J8: Structure | K8: all company minutes
D9: From | J9: ATO Tax Return | K9: ASIC showing company info on 30th june
B10: Current Director | C10: Rachel Anne Harder | D10: 36655 | J10: Asset | K10: All ASIC Documents
B11: Current Secretary | C11: Rachel Anne Harder | D11: 40875 | J11: Dividends | K11: Company Tax Return
J12: EOY ATO | K12: Company ATO due
B13: Does this Company have Loans | C13: Yes | F13: Is there loan documents in place | G13: Yes | J13: Registered Office
E14: Shares | F14: Beneficially Held | J14: Officers
B15: Current Shareholdings | C15: Team Harder Super Investments Pty Ltd | E15: 1000 | F15: Yes | J15: Bank Statements
J16: Minutes
B17: Current Bank Accounts | C17: Bank | D17: BSB | E17: Account | F17: Date Opened | J17: Distribution
C18: NAB | D18: 084-435 | E18: 513642009 | F18: 44768 | J18: EOY ASIC
C19: NAB Trade | D19: 083-052 | E19: 304658188 | J19: PPSR
J20: Tax Consolidation
J21: Trust Deed
B24: Folder Storage | C24: W2G Assets | D24: Abbreviation | E24: W2G
B26: Company Register | C26: Type | D26: Folder | E26: Date | F26: Manual | G26: Electronicaly Stored | H26: By Whom | J26: Things to Do
B27: EOY ASIC FY24 | C27: EOY ASIC | D27: =VLOOKUP(C27,'Document Type'!$B$6:$C$34,2,FALSE) -> General | E27: 45471 | G27: EOY ASIC FY24 W2G
B28: EOY ATO FY24 | C28: EOY ATO | D28: =VLOOKUP(C28,'Document Type'!$B$6:$C$34,2,FALSE) -> General | E28: 45471 | G28: EOY ATO FY24 W2G
B29: BOQ Acc 21446327 CLOSED | C29: Bank Statements | D29: =VLOOKUP(C29,'Document Type'!$B$6:$C$34,2,FALSE) -> General | G29: W2G BOQ 21446327 FY24 CLOSED 28.12.23
B30: BOQ Loan Acc 23084038 CLOSED | C30: Bank Statements | D30: =VLOOKUP(C30,'Document Type'!$B$6:$C$34,2,FALSE) -> General | G30: W2G BOQ Loan 23084038 FY24 CLOSED 08.12.23
B31: Certificate of Registration | C31: Company Setup | D31: =VLOOKUP(C31,'Document Type'!$B$6:$C$34,2,FALSE) -> Company Setup | E31: 36655 | G31: Certificate of Registration W2G
B32: Constituition | C32: Constitution | D32: =VLOOKUP(C32,'Document Type'!$B$6:$C$34,2,FALSE) -> Constitution | E32: 36655 | G32: Constituition W2G
B33: Share Certificate | C33: Members | D33: =VLOOKUP(C33,'Document Type'!$B$6:$C$34,2,FALSE) -> Register of Members | E33: 36655 | G33: Share Certificate W2G
B34: Resignation of Director | C34: Officers | D34: =VLOOKUP(C34,'Document Type'!$B$6:$C$34,2,FALSE) -> General | E34: 44497 | G34: Resignation of Director RH W2G
B35: Change of Address | C35: ASIC Docs | D35: =VLOOKUP(C35,'Document Type'!$B$6:$C$34,2,FALSE) -> General | E35: 44159 | G35: Change of Address W2G
D36: =VLOOKUP(C36,'Document Type'!$B$6:$C$34,2,FALSE) -> #N/A
D37: =VLOOKUP(C37,'Document Type'!$B$6:$C$34,2,FALSE) -> #N/A
D38: =VLOOKUP(C38,'Document Type'!$B$6:$C$34,2,FALSE) -> #N/A
D39: =VLOOKUP(C39,'Document Type'!$B$6:$C$34,2,FALSE) -> #N/A
D40: =VLOOKUP(C40,'Document Type'!$B$6:$C$34,2,FALSE) -> #N/A
D41: =VLOOKUP(C41,'Document Type'!$B$6:$C$34,2,FALSE) -> #N/A
D42: =VLOOKUP(C42,'Document Type'!$B$6:$C$34,2,FALSE) -> #N/A
D43: =VLOOKUP(C43,'Document Type'!$B$6:$C$34,2,FALSE) -> #N/A
D44: =VLOOKUP(C44,'Document Type'!$B$6:$C$34,2,FALSE) -> #N/A
D45: =VLOOKUP(C45,'Document Type'!$B$6:$C$34,2,FALSE) -> #N/A
D46: =VLOOKUP(C46,'Document Type'!$B$6:$C$34,2,FALSE) -> #N/A
D47: =VLOOKUP(C47,'Document Type'!$B$6:$C$34,2,FALSE) -> #N/A
... D61: =VLOOKUP(C61,'Document Type'!$B$6:$C$34,2,FALSE) -> #N/A
B63: Register of Members
B64: Date | C64: Issue, transfer,share split, buy back or Cancelation | D64: Class of Share | E64: Certification Number | F64: Serial Number From | G64: Serial Number To | H64: Number of Shares Aquired | I64: Trf'd to / Trf'd from | J64: Amount Paid Per Share | K64: Amount Unpaid per Share | L64: Fully Paid? (Y/N) | M64: Total Number os Shares Held | N64: Total Amount paid fo the shares | O64: Are the Shares Benedicially Held | P64: Owner / Buyer / Seller | Q64: ASIC Document Number
B92: Register of Loans
B93: From | C93: To | D93: Amount | E93: Date | F93: Security | G93: PPSR
B101: Register of Assets - Non Trading
B102: Item | C102: Purchase Date | D102: Purchase Price | E102: Sale Date | F102: Sale Price | G102: Profit
G103: =Table791358[[#This Row],[Purchase Price]]-Table791358[[#This Row],[Sale Price]] -> 0
G104: =Table791358[[#This Row],[Purchase Price]]-Table791358[[#This Row],[Sale Price]] -> 0
G105: =Table791358[[#This Row],[Purchase Price]]-Table791358[[#This Row],[Sale Price]] -> 0
G106: =Table791358[[#This Row],[Purchase Price]]-Table791358[[#This Row],[Sale Price]] -> 0
G107: =Table791358[[#This Row],[Purchase Price]]-Table791358[[#This Row],[Sale Price]] -> 0
G108: =Table791358[[#This Row],[Purchase Price]]-Table791358[[#This Row],[Sale Price]] -> 0
G109: =Table791358[[#This Row],[Purchase Price]]-Table791358[[#This Row],[Sale Price]] -> 0
G110: =Table791358[[#This Row],[Purchase Price]]-Table791358[[#This Row],[Sale Price]] -> 0
G111: =Table791358[[#This Row],[Purchase Price]]-Table791358[[#This Row],[Sale Price]] -> 0
G112: =Table791358[[#This Row],[Purchase Price]]-Table791358[[#This Row],[Sale Price]] -> 0
G113: =Table791358[[#This Row],[Purchase Price]]-Table791358[[#This Row],[Sale Price]] -> 0
G114: =Table791358[[#This Row],[Purchase Price]]-Table791358[[#This Row],[Sale Price]] -> 0
... G120: =Table791358[[#This Row],[Purchase Price]]-Table791358[[#This Row],[Sale Price]] -> 0

Sheet THSI
B1: All Companies
J2: Loan Agreement | K2: Things that must be filed | L2: 2024
B3: Team Harder Super Investments | J3: Security Deed | K3: If is a discresionary trust , need to make the trust distribution every year before 30th June
B4: ACN: | C4: 658 706 597 | D4: ABN: | E4: 32 658 706 597 | G4: TFN: | H4: 608 117 219 | J4: Company Setup | K4: All Bank Statement for the year
B5: Date Incorporated | C5: 44662 | F5: Shares on Issue | G5: 100 | J5: Solvency ASIC | K5: all assets purchases receipts
B6: Purpose: | F6: Is it a Trustee | G6: No | J6: Constitution | K6: all sales of assets
B7: Trust Name / Trustee | J7: Members | K7: all distribution if company
B8: Registered office | C8: MAGNUS BUSINESS ADVISERS AND ACCOUNTANTS, UNIT 10 , 39 OLD CLEVELAND ROAD , CAPALABA QLD 4157 | F8: Principal place of business | G8: 160 Alperton Road, Burbank QLD 4156 | J8: Structure | K8: all company minutes
D9: From | J9: ATO Tax Return | K9: ASIC showing company info on 30th june
B10: Current Director | C10: Rachel Anne Harder | D10: 44662 | J10: Asset | K10: All ASIC Documents
B11: Current Secretary | C11: Rachel Anne Harder | D11: 44662 | J11: Dividends | K11: Company Tax Return
J12: EOY ATO | K12: Company ATO due
B13: Does this Company have Loans | C13: No | F13: Is there loan documents in place | G13: No | J13: Registered Office
E14: Shares | F14: Beneficially Held | J14: Officers
B15: Current Shareholdings | C15: Prov1322 Global Pty Ltd | E15: 100 | F15: No | J15: Bank Statements
J16: Minutes
B17: Current Bank Accounts | C17: Bank | D17: BSB | E17: Account | F17: Date Opened | J17: Distribution
C18: NAB | D18: 084-435 | E18: 259449309 | F18: 44671 | J18: EOY ASIC
C19: NAB Trade | D19: 083-052 | E19: 305422840 | J19: PPSR
C20: Westpac | J20: Tax Consolidation
J21: Trust Deed
B24: Folder Storage | C24: Team Harder Super Investments | D24: Abbreviation | E24: THSI
B26: Company Register | C26: Type | D26: Folder | E26: Date | F26: Manual | G26: Electronicaly Stored | H26: By Whom | J26: Things to Do
B27: EOY ASIC FY24 | C27: EOY ASIC | D27: =VLOOKUP(C27,'Document Type'!$B$6:$C$34,2,FALSE) -> General | E27: 45471 | G27: EOY ASIC FY24 THSI
B28: EOY ATO FY24 | C28: EOY ATO | D28: =VLOOKUP(C28,'Document Type'!$B$6:$C$34,2,FALSE) -> General | E28: 45471 | G28: EOY ATO FY24 THIS
B29: Corporate Key | C29: Corporate Key | D29: General | E29: 45100 | G29: Corporate Key THIS
B30: EOY ASIC FY23 | C30: EOY ASIC | D30: =VLOOKUP(C30,'Document Type'!$B$6:$C$34,2,FALSE) -> General | E30: 45107 | G30: EOY ASIC FY23 THIS
B31: EOY ATO FY23 | C31: EOY ATO | D31: =VLOOKUP(C31,'Document Type'!$B$6:$C$34,2,FALSE) -> General | E31: 45107 | G31: EOY ATO FY23 THIS
B32: Change to Register of Members | C32: Members | D32: =VLOOKUP(C32,'Document Type'!$B$6:$C$34,2,FALSE) -> Register of Members | E32: 44698 | G32: Change to Register of Members THIS
B33: Registered Address | C33: ASIC Docs | D33: =VLOOKUP(C33,'Document Type'!$B$6:$C$34,2,FALSE) -> General | E33: 44698 | G33: Registered Office Multiplace THIS
B34: Resolution of Expenditure | C34: Minutes | D34: =VLOOKUP(C34,'Document Type'!$B$6:$C$34,2,FALSE) -> Minutes | E34: 45283 | G34: Resolution of Expenditure THIS
B35: EOFY 24 Dividend Resolution | D35: General | E35: 45842 | G35: [SIGNED] 2024 Dividend Resolution - W2G ASSETS PTY LTD | H35: Rachel
B36: EOFY 24 Financials | D36: General | E36: 45842 | G36: [SIGNED] Team Harder Super Investments Pty Ltd - Consolidated Financials 2024 | H36: rachel
B37: EOFY24 Tax Return | D37: General | E37: 45842 | G37: [SIGNED] Team Harder Super Investments Pty Ltd - Consolidated Tax Return 2024 | H37: Rachel
B38: Annual Company Statement | D38: General | E38: 45813
B39: PAYG - June 2025 | D39: General | E39: 45862 | G39: [SIGNED] Team Harder Super Investments Pty Ltd - PAYGIN June 2025 | H39: Rachel
D40: =VLOOKUP(C40,'Document Type'!$B$6:$C$34,2,FALSE) -> #N/A
D41: =VLOOKUP(C41,'Document Type'!$B$6:$C$34,2,FALSE) -> #N/A
D42: =VLOOKUP(C42,'Document Type'!$B$6:$C$34,2,FALSE) -> #N/A
D43: =VLOOKUP(C43,'Document Type'!$B$6:$C$34,2,FALSE) -> #N/A
D44: =VLOOKUP(C44,'Document Type'!$B$6:$C$34,2,FALSE) -> #N/A
D45: =VLOOKUP(C45,'Document Type'!$B$6:$C$34,2,FALSE) -> #N/A
D46: =VLOOKUP(C46,'Document Type'!$B$6:$C$34,2,FALSE) -> #N/A
D47: =VLOOKUP(C47,'Document Type'!$B$6:$C$34,2,FALSE) -> #N/A
D48: =VLOOKUP(C48,'Document Type'!$B$6:$C$34,2,FALSE) -> #N/A
D49: =VLOOKUP(C49,'Document Type'!$B$6:$C$34,2,FALSE) -> #N/A
D50: =VLOOKUP(C50,'Document Type'!$B$6:$C$34,2,FALSE) -> #N/A
D51: =VLOOKUP(C51,'Document Type'!$B$6:$C$34,2,FALSE) -> #N/A
... D63: =VLOOKUP(C63,'Document Type'!$B$6:$C$34,2,FALSE) -> #N/A
B67: Register of Members
B68: Date | C68: Issue, transfer,share split, buy back or Cancelation | D68: Class of Share | E68: Certification Number | F68: Serial Number From | G68: Serial Number To | H68: Number of Shares Aquired | I68: Trf'd to / Trf'd from | J68: Amount Paid Per Share | K68: Amount Unpaid per Share | L68: Fully Paid? (Y/N) | M68: Total Number os Shares Held | N68: Total Amount paid fo the shares | O68: Are the Shares Benedicially Held | P68: Owner / Buyer / Seller | Q68: ASIC Document Number
B96: Register of Loans
B97: From | C97: To | D97: Amount | E97: Date | F97: Security | G97: PPSR
B105: Register of Assets - Non Trading
B106: Item | C106: Purchase Date | D106: Purchase Price | E106: Sale Date | F106: Sale Price | G106: Profit
G107: =Table791354[[#This Row],[Purchase Price]]-Table791354[[#This Row],[Sale Price]] -> 0
G108: =Table791354[[#This Row],[Purchase Price]]-Table791354[[#This Row],[Sale Price]] -> 0
G109: =Table791354[[#This Row],[Purchase Price]]-Table791354[[#This Row],[Sale Price]] -> 0
G110: =Table791354[[#This Row],[Purchase Price]]-Table791354[[#This Row],[Sale Price]] -> 0
G111: =Table791354[[#This Row],[Purchase Price]]-Table791354[[#This Row],[Sale Price]] -> 0
G112: =Table791354[[#This Row],[Purchase Price]]-Table791354[[#This Row],[Sale Price]] -> 0
G113: =Table791354[[#This Row],[Purchase Price]]-Table791354[[#This Row],[Sale Price]] -> 0
G114: =Table791354[[#This Row],[Purchase Price]]-Table791354[[#This Row],[Sale Price]] -> 0
G115: =Table791354[[#This Row],[Purchase Price]]-Table791354[[#This Row],[Sale Price]] -> 0
G116: =Table791354[[#This Row],[Purchase Price]]-Table791354[[#This Row],[Sale Price]] -> 0
G117: =Table791354[[#This Row],[Purchase Price]]-Table791354[[#This Row],[Sale Price]] -> 0
G118: =Table791354[[#This Row],[Purchase Price]]-Table791354[[#This Row],[Sale Price]] -> 0
... G124: =Table791354[[#This Row],[Purchase Price]]-Table791354[[#This Row],[Sale Price]] -> 0

Sheet Team Harder Family Trust
B1: All Companies
B3: Prov1322 Global ATF Team Harder Family Trust | J3: Things to Do:
B4: ACN: | D4: ABN: | E4: 94 633 472 433 | G4: TFN: | H4: 605 725 602 | J4: Need Structure Group
B5: Date Incorporated | C5: 44383 | F5: Shares on Issue | J5: Share Purchase
B6: Purpose: | C6: To Act as a Trust for Prov1322 | F6: Is it a Trustee | G6: No | J6: Gold Purchase
B7: Trust Name / Trustee | C7: Team Harder Family Trust | J7: Limeco Purchase
B8: Registered office | C8: MAGNUS BUSINESS ADVISERS AND ACCOUNTANTS, UNIT 10 , 39 OLD CLEVELAND ROAD , CAPALABA QLD 4157 | F8: Principal place of business | G8: 160 Alperton Road, Burbank QLD 4156 | J8: Tekna Purchase
D9: From | J9: Silver Purchase
B10: Current Director
B11: Current Secretary
B13: Does this Company have Loans | C13: No | F13: Is there loan documents in place | G13: No
E14: Shares | F14: Beneficially Held
B15: Current Shareholdings
B17: Current Bank Accounts | C17: Bank | D17: BSB | E17: Account | F17: Date Opened
C18: Westpac | D18: 034-076 | E18: 699669 | F18: 45282
C19: Westpac Trade | E19: 6864378 | F19: 45483
C20: NAB | D20: 084-436 | E20: 959276787 | F20: 44399
C21: NAB Trade | D21: 083-052 | E21: 305383521
B24: Folder Storage | C24: Team Harder Family Trust | D24: Abbreviation | E24: THFT
B26: Company Register | C26: Type | D26: Folder | E26: Date | F26: Manual | G26: Electronicaly Stored | H26: By Whom
B27: Harder Bloodline Trust Deed | C27: Trust Deed | D27: =VLOOKUP(C27,'Document Type'!$B$6:$C$34,2,FALSE) -> Trust Deed | E27: 44270 | G27: Harder Bloodline Trust Deed THFT | H27: Sophie Harder
B28: Harder Bloodline Trust Certified | C28: Trust Deed | D28: =VLOOKUP(C28,'Document Type'!$B$6:$C$34,2,FALSE) -> Trust Deed | E28: 44270 | G28: Harder Bloodline Trust Certified THFT | H28: Sophie Harder
B29: Bloodline Trust Name Change THFT | C29: Trust Deed | D29: =VLOOKUP(C29,'Document Type'!$B$6:$C$34,2,FALSE) -> Trust Deed | E29: 44641 | G29: Bloodline Name Change to THFT | H29: Sophie Harder
B30: Deed of Appointment and Removal | C30: Trust Deed | D30: =VLOOKUP(C30,'Document Type'!$B$6:$C$34,2,FALSE) -> Trust Deed | E30: 44642 | G30: Trustee Changed Rachel to Harder Dev THFT | H30: Sophie Harder
B31: Deed of Appointment and Removal | C31: Trust Deed | D31: =VLOOKUP(C31,'Document Type'!$B$6:$C$34,2,FALSE) -> Trust Deed | E31: 44658 | G31: Trustee Change Harder Dev to Prov1322 THFT | H31: Sophie Harder
B32: Loan Prov1322 to Gen2612 THFT | C32: Loan Agreement | D32: =VLOOKUP(C32,'Document Type'!$B$6:$C$34,2,FALSE) -> Loans and Security | E32: 44658 | G32: In folder in Loans and Security | H32: Sophie Harder
B33: Jared to Prov1322 THFT | C33: Loan Agreement | D33: =VLOOKUP(C33,'Document Type'!$B$6:$C$34,2,FALSE) -> Loans and Security | E33: 44658 | G33: In folder in Loans and Security | H33: Sophie Harder
B34: Grace to Prov1322 THFT | C34: Loan Agreement | D34: =VLOOKUP(C34,'Document Type'!$B$6:$C$34,2,FALSE) -> Loans and Security | E34: 44658 | G34: In folder in Loans and Security | H34: Sophie Harder
B35: Sophie to Prov1322 THFT | C35: Loan Agreement | D35: =VLOOKUP(C35,'Document Type'!$B$6:$C$34,2,FALSE) -> Loans and Security | E35: 44658 | G35: In folder in Loans and Security | H35: Sophie Harder
B36: Distribution Minute | C36: Distribution Minutes | D36: =VLOOKUP(C36,'Document Type'!$B$6:$C$34,2,FALSE) -> Minutes | E36: 44741 | G36: Distribution Minute 2022 THFT | H36: Sophie Harder
B37: Distribution Minute FY22 THFT | C37: Distribution Minutes | D37: =VLOOKUP(C37,'Document Type'!$B$6:$C$34,2,FALSE) -> Minutes | E37: 44742 | G37: Distribution Minute FY22 THFT
B38: Change of Company | C38: ASIC Docs | D38: =VLOOKUP(C38,'Document Type'!$B$6:$C$34,2,FALSE) -> General | E38: 44767 | G38: Change of Company Details THFT | H38: Sophie Harder
B39: Distribution Minute | C39: Distribution Minutes | D39: =VLOOKUP(C39,'Document Type'!$B$6:$C$34,2,FALSE) -> Minutes | E39: 45107 | G39: Distribution Minute 2023 THFT | H39: Sophie Harder
B40: 2023 - Team Harder Family Trust - Distribution Minute | C40: Distribution Minutes | D40: =VLOOKUP(C40,'Document Type'!$B$6:$C$34,2,FALSE) -> Minutes | E40: 45107 | G40: Distribution Minute FY23 THFT | H40: Sophie Harder
B41: This was because we couldn’t find orginal deed and sign resigned stating it was done then | C41: Trust Deed | D41: =VLOOKUP(C41,'Document Type'!$B$6:$C$34,2,FALSE) -> Trust Deed | E41: 45282 | G41: Deed of Variation of Discretionary Trust THFT | H41: Sophie Harder
B42: EOY ATO FY24 | C42: EOY ATO | D42: =VLOOKUP(C42,'Document Type'!$B$6:$C$34,2,FALSE) -> General | E42: 45471 | G42: EOY ATO FY24 Prov1322 ATF THFT | H42: Sophie Harder
B43: Distribution Minute FY24 THFT | C43: Distribution Minutes | D43: =VLOOKUP(C43,'Document Type'!$B$6:$C$34,2,FALSE) -> Minutes | E43: 45472 | G43: Distribution Minute FY24 THFT | H43: Sophie Harder
B44: Return of Gift Deed | C44: Return of Gift Deed | D44: =VLOOKUP(C44,'Document Type'!$B$6:$C$34,2,FALSE) -> Loans and Security | E44: 45108 | G44: Return of Gift Deed THFT | H44: Sophie Harder
B45: EOY NAB 959276787 FY22 | C45: Bank Statements | D45: =VLOOKUP(C45,'Document Type'!$B$6:$C$34,2,FALSE) -> General | E45: 45562 | G45: EOY NAB 959276787 FY22 THFT | H45: Rachel
B46: EOY NAB 959276787 FY23 | C46: Bank Statements | D46: =VLOOKUP(C46,'Document Type'!$B$6:$C$34,2,FALSE) -> General | E46: 45562 | G46: EOY NAB 959276787 FY23 THFT | H46: Rachel
B47: EOY NAB 959276787 FY24 | C47: Bank Statements | D47: =VLOOKUP(C47,'Document Type'!$B$6:$C$34,2,FALSE) -> General | E47: 45562 | G47: EOY NAB 959276787 FY24 THFT | H47: Rachel
B48: EOY NAB Trade 305383521 FY22 | C48: Bank Statements | D48: =VLOOKUP(C48,'Document Type'!$B$6:$C$34,2,FALSE) -> General | E48: 45562 | G48: EOY NAB Trade 305383521 FY22 THFT | H48: Rachel
B49: EOY NAB Trade 305383521 FY23 | C49: Bank Statements | D49: =VLOOKUP(C49,'Document Type'!$B$6:$C$34,2,FALSE) -> General | E49: 45562 | G49: EOY NAB Trade 305383521 FY23 THFT | H49: Rachel
... B61: THFT - Tax Return 2024 | C61: EOFY Financials | D61: =VLOOKUP(C61,'Document Type'!$B$6:$C$34,2,FALSE) -> General | E61: 45852 | G61: [SIGNED] Team Harder Family Trust - Tax return 2024 | H61: Rachel
C62: EOFY Financials | D62: =VLOOKUP(C62,'Document Type'!$B$6:$C$34,2,FALSE) -> General
B63: Deed of Novation | C63: Loan Agreement | D63: Loans and Security | E63: 45517 | G63: Deed of Novation Gen2612
B64: Deed of Novation ATO | C64: Loan Agreement | D64: =VLOOKUP(C64,'Document Type'!$B$6:$C$34,2,FALSE) -> Loans and Security | E64: 45474 | G64: Deed of Novation ATO Gen2612
B65: Bank Statement | C65: Bank Statements | D65: =VLOOKUP(C65,'Document Type'!$B$6:$C$34,2,FALSE) -> General | E65: 45884 | G65: 2. WBC 699669 FY25 THFT 20.09.24 - 20.12.24 | H65: Sophie Harder
B66: Bank Statement | C66: Bank Statements | D66: =VLOOKUP(C66,'Document Type'!$B$6:$C$34,2,FALSE) -> General | E66: 45884 | G66: 3. WBC 699669 FY25 THFT 20.12.24 - 21.03.25 | H66: Sophie Harder
B67: Bank Statement | C67: Bank Statements | D67: =VLOOKUP(C67,'Document Type'!$B$6:$C$34,2,FALSE) -> General | E67: 45884 | G67: 4. WBC 699669 FY25 THFT 21.03.25 - 20.06.25 | H67: Sophie Harder
B68: THFT - BAS - 2025-06-30 | C68: BAS | D68: =VLOOKUP(C68,'Document Type'!$B$6:$C$34,2,FALSE) -> BAS | E68: 45891 | G68: [SIGNED] Team Harder Family Trust - BAS - 2025-06-30
B74: Register of Members
B75: Date | C75: Issue, transfer,share split, buy back or Cancelation | D75: Class of Share | E75: Certification Number | F75: Serial Number From | G75: Serial Number To | H75: Number of Shares Aquired | I75: Trf'd to / Trf'd from | J75: Amount Paid Per Share | K75: Amount Unpaid per Share | L75: Fully Paid? (Y/N) | M75: Total Number os Shares Held | N75: Total Amount paid fo the shares | O75: Are the Shares Benedicially Held | P75: Owner / Buyer / Seller | Q75: ASIC Document Number
B103: Register of Loans
B104: From | C104: To | D104: Amount | E104: Date | F104: Security | G104: PPSR
B105: Prov1322 ATF | C105: Gen2612 | D105: 100000000 | E105: 44658 | F105: Yes | G105: Yes
B106: Jared Harder | C106: Prov1322 ATF | D106: 5000000 | E106: 44658 | F106: Yes | G106: Yes
B107: Grace Harder | C107: Prov1322 ATF | D107: 5000000 | E107: 44658 | F107: Yes | G107: Yes
B108: Sophie Harder | C108: Prov1322 ATF | D108: 5000000 | E108: 44658 | F108: Yes | G108: Yes
B112: Register of Assets - Non Trading
B113: Item | C113: Purchase Date | D113: Purchase Price | E113: Sale Date | F113: Sale Price | G113: Profit
B114: Gen2612 Shares | C114: 44651 | D114: 100 | G114: =Table791330[[#This Row],[Purchase Price]]-Table791330[[#This Row],[Sale Price]] -> 100
G115: =Table791330[[#This Row],[Purchase Price]]-Table791330[[#This Row],[Sale Price]] -> 0
G116: =Table791330[[#This Row],[Purchase Price]]-Table791330[[#This Row],[Sale Price]] -> 0
G117: =Table791330[[#This Row],[Purchase Price]]-Table791330[[#This Row],[Sale Price]] -> 0
G118: =Table791330[[#This Row],[Purchase Price]]-Table791330[[#This Row],[Sale Price]] -> 0
G119: =Table791330[[#This Row],[Purchase Price]]-Table791330[[#This Row],[Sale Price]] -> 0
G120: =Table791330[[#This Row],[Purchase Price]]-Table791330[[#This Row],[Sale Price]] -> 0
G121: =Table791330[[#This Row],[Purchase Price]]-Table791330[[#This Row],[Sale Price]] -> 0
G122: =Table791330[[#This Row],[Purchase Price]]-Table791330[[#This Row],[Sale Price]] -> 0
G123: =Table791330[[#This Row],[Purchase Price]]-Table791330[[#This Row],[Sale Price]] -> 0
G124: =Table791330[[#This Row],[Purchase Price]]-Table791330[[#This Row],[Sale Price]] -> 0
G125: =Table791330[[#This Row],[Purchase Price]]-Table791330[[#This Row],[Sale Price]] -> 0
G126: =Table791330[[#This Row],[Purchase Price]]-Table791330[[#This Row],[Sale Price]] -> 0
... G131: =Table791330[[#This Row],[Purchase Price]]-Table791330[[#This Row],[Sale Price]] -> 0

Sheet Prov1322
A1: All Companies
I2: Loan Agreement | J2: Things that must be filed | K2: 2024
A3: Prov1322 Global Pty Ltd | I3: Security Deed | J3: If is a discresionary trust , need to make the trust distribution every year before 30th June
A4: ACN: | B4: 658 602 478 | C4: ABN: | D4: 34 658 602 478 | F4: TFN: | G4: 606 189 260 | I4: Company Setup | J4: All Bank Statement for the year
A5: Date Incorporated | B5: 44657 | E5: Shares on Issue | F5: 100 | I5: Solvency ASIC | J5: all assets purchases receipts
A6: Purpose: | B6: To act as Trustee for Team Harder Family Trust | E6: Is it a Trustee | F6: Yes | I6: Constitution | J6: all sales of assets
A7: Trust Name / Trustee | B7: Team Harder Family Trust | I7: Members | J7: all distribution if company
A8: Registered office | B8: MAGNUS BUSINESS ADVISERS AND ACCOUNTANTS, UNIT 10 , 39 OLD CLEVELAND ROAD , CAPALABA QLD 4157 | E8: Principal place of business | F8: 160 Alperton Road, Burbank QLD 4156 | I8: Structure | J8: all company minutes
C9: From | I9: ATO Tax Return | J9: ASIC showing company info on 30th june
A10: Current Director | B10: Rachel Anne Harder | C10: 44657 | I10: Asset | J10: All ASIC Documents
A11: Current Secretary | B11: Rachel Anne Harder | C11: 44657 | I11: Dividends | J11: Company Tax Return
I12: EOY ATO | J12: Company ATO due
A13: Does this Company have Loans | B13: No | E13: Is there loan documents in place | F13: No | I13: Registered Office
D14: Shares | E14: Beneficially Held | I14: Officers
A15: Current Shareholdings | B15: Rachel Harder | D15: 100 | E15: Yes | I15: Bank Statements
I16: Minutes
A17: Current Bank Accounts | B17: Bank | C17: BSB | D17: Account | E17: Date Opened | I17: Distribution
B18: NAB | I18: EOY ASIC
B19: Westpac | C19: 034-076 | D19: 699669 | E19: 45282 | I19: PPSR
I20: Tax Consolidation
I21: Trust Deed
A24: Folder Storage | B24: Prov1322 | C24: Abbreviation | D24: Prov1322
A26: Company Register | B26: Type | C26: Folder | D26: Date | E26: Manual | F26: Electronicaly Stored | G26: By Whom | I26: Things to Do
A27: EOY ATO FY24 | B27: EOY ATO | C27: =VLOOKUP(B27,'Document Type'!$B$6:$C$34,2,FALSE) -> General | D27: 45471 | F27: EOY ATO FY24 Prov1322
A28: EOY ASIC FY24 | B28: EOY ASIC | C28: =VLOOKUP(B28,'Document Type'!$B$6:$C$34,2,FALSE) -> General | D28: 45471 | F28: EOY ASIC FY24 Prov1322
A29: Certificate of Registration | B29: Company Setup | C29: =VLOOKUP(B29,'Document Type'!$B$6:$C$34,2,FALSE) -> Company Setup | D29: 44657 | F29: Certificate of Registration Prov1322
A30: Constituition | B30: Constitution | C30: =VLOOKUP(B30,'Document Type'!$B$6:$C$34,2,FALSE) -> Constitution | D30: 44657 | F30: Constitution Prov1322.pdf
A31: Corporate Key | B31: Corporate Key | C31: =VLOOKUP(B31,'Document Type'!$B$6:$C$34,2,FALSE) -> General | D31: 45100 | F31: Corporate Key Prov1322
A32: EOY ATO FY23 | B32: EOY ATO | C32: =VLOOKUP(B32,'Document Type'!$B$6:$C$34,2,FALSE) -> General | D32: 45107 | F32: EOY ATO FY23 Prov1322
A33: EOY ASIC FY23 | B33: EOY ASIC | C33: =VLOOKUP(B33,'Document Type'!$B$6:$C$34,2,FALSE) -> General | D33: 45107 | F33: EOY ASIC FY23 Prov1322
A34: Registered Office | B34: ASIC Docs | C34: =VLOOKUP(B34,'Document Type'!$B$6:$C$34,2,FALSE) -> General | D34: 44698 | F34: Registered Office Multiplace Prov1322
A35: Annual Solvency Minutes | B35: Minutes | C35: =VLOOKUP(B36,'Document Type'!$B$6:$C$34,2,FALSE) -> Register of Members | D35: 44657 | F35: Annual Solvency Minutes Prov1322
A36: Share Certificate | B36: Members | C36: Register of Members | D36: 44657 | F36: Share Certificate Rachel Harder Prov1322
A37: Resolution of Members | B37: Members | C37: =VLOOKUP(B37,'Document Type'!$B$6:$C$34,2,FALSE) -> Register of Members | D37: 44657 | F37: Resolution of Members Prov1322
A38: Register of Debentures | B38: Members | C38: =VLOOKUP(B38,'Document Type'!$B$6:$C$34,2,FALSE) -> Register of Members | D38: 44714 | F38: Register of Debentures Prov1322
A39: Register of Charges | B39: Members | C39: =VLOOKUP(B39,'Document Type'!$B$6:$C$34,2,FALSE) -> Register of Members | D39: 44714 | F39: Register of Charges Prov1322
A40: Officeholder Consent | B40: Members | C40: =VLOOKUP(B40,'Document Type'!$B$6:$C$34,2,FALSE) -> Register of Members | D40: 44714 | F40: Officeholder Consent Rachel Harder Prov1322
A41: Application for Shares | B41: Members | C41: =VLOOKUP(B41,'Document Type'!$B$6:$C$34,2,FALSE) -> Register of Members | D41: 44714 | F41: Application for Shares Rachel Harder Prov1322
A42: Register of Members | B42: Members | C42: =VLOOKUP(B42,'Document Type'!$B$6:$C$34,2,FALSE) -> Register of Members | D42: 44657 | F42: Register of Members Prov1322
A43: Change to Register of Members | B43: Members | C43: =VLOOKUP(B43,'Document Type'!$B$6:$C$34,2,FALSE) -> Register of Members | D43: 44698 | F43: Change of Register of Members Prov1322
A44: Change to Register of Members | B44: Members | C44: =VLOOKUP(B44,'Document Type'!$B$6:$C$34,2,FALSE) -> Register of Members | D44: 44698 | F44: Change of Register of Members Rachel Harder Prov1322
C45: =VLOOKUP(B45,'Document Type'!$B$6:$C$34,2,FALSE) -> #N/A
C46: =VLOOKUP(B46,'Document Type'!$B$6:$C$34,2,FALSE) -> #N/A
C47: =VLOOKUP(B47,'Document Type'!$B$6:$C$34,2,FALSE) -> #N/A
C48: =VLOOKUP(B48,'Document Type'!$B$6:$C$34,2,FALSE) -> #N/A
C49: =VLOOKUP(B49,'Document Type'!$B$6:$C$34,2,FALSE) -> #N/A
C50: =VLOOKUP(B50,'Document Type'!$B$6:$C$34,2,FALSE) -> #N/A
C51: =VLOOKUP(B51,'Document Type'!$B$6:$C$34,2,FALSE) -> #N/A
C52: =VLOOKUP(B52,'Document Type'!$B$6:$C$34,2,FALSE) -> #N/A
C53: =VLOOKUP(B53,'Document Type'!$B$6:$C$34,2,FALSE) -> #N/A
C54: =VLOOKUP(B54,'Document Type'!$B$6:$C$34,2,FALSE) -> #N/A
C55: =VLOOKUP(B55,'Document Type'!$B$6:$C$34,2,FALSE) -> #N/A
C56: =VLOOKUP(B56,'Document Type'!$B$6:$C$34,2,FALSE) -> #N/A
... C60: =VLOOKUP(B60,'Document Type'!$B$6:$C$34,2,FALSE) -> #N/A
A62: Register of Members
A63: Date | B63: Issue, transfer,share split, buy back or Cancelation | C63: Class of Share | D63: Certification Number | E63: Serial Number From | F63: Serial Number To | G63: Number of Shares Aquired | H63: Trf'd to / Trf'd from | I63: Amount Paid Per Share | J63: Amount Unpaid per Share | K63: Fully Paid? (Y/N) | L63: Total Number os Shares Held | M63: Total Amount paid fo the shares | N63: Are the Shares Benedicially Held | O63: Owner / Buyer / Seller | P63: ASIC Document Number
A64: 44698 | C64: ORD | G64: 100 | I64: 1 | K64: Y | L64: 100 | M64: 100 | N64: Y
A91: Register of Loans
A92: From | B92: To | C92: Amount | D92: Date | E92: Security | F92: PPSR
A100: Register of Assets - Non Trading
A101: Item | B101: Purchase Date | C101: Purchase Price | D101: Sale Date | E101: Sale Price | F101: Profit
F102: =Table791326[[#This Row],[Purchase Price]]-Table791326[[#This Row],[Sale Price]] -> 0
F103: =Table791326[[#This Row],[Purchase Price]]-Table791326[[#This Row],[Sale Price]] -> 0
F104: =Table791326[[#This Row],[Purchase Price]]-Table791326[[#This Row],[Sale Price]] -> 0
F105: =Table791326[[#This Row],[Purchase Price]]-Table791326[[#This Row],[Sale Price]] -> 0
F106: =Table791326[[#This Row],[Purchase Price]]-Table791326[[#This Row],[Sale Price]] -> 0
F107: =Table791326[[#This Row],[Purchase Price]]-Table791326[[#This Row],[Sale Price]] -> 0
F108: =Table791326[[#This Row],[Purchase Price]]-Table791326[[#This Row],[Sale Price]] -> 0
F109: =Table791326[[#This Row],[Purchase Price]]-Table791326[[#This Row],[Sale Price]] -> 0
F110: =Table791326[[#This Row],[Purchase Price]]-Table791326[[#This Row],[Sale Price]] -> 0
F111: =Table791326[[#This Row],[Purchase Price]]-Table791326[[#This Row],[Sale Price]] -> 0
F112: =Table791326[[#This Row],[Purchase Price]]-Table791326[[#This Row],[Sale Price]] -> 0
F113: =Table791326[[#This Row],[Purchase Price]]-Table791326[[#This Row],[Sale Price]] -> 0
... F119: =Table791326[[#This Row],[Purchase Price]]-Table791326[[#This Row],[Sale Price]] -> 0

Sheet Gen2612
A1: All Companies
A3: Gen2612 Pty Ltd | I3: Things to Do:
A4: ACN: | B4: 658 463 659 | C4: ABN: | D4: 47 658 463 659 | F4: TFN: | G4: 605 934 566 | I4: Need Structure Group
A5: Date Incorporated | B5: 44651 | E5: Shares on Issue | F5: 100
A6: Purpose: | E6: Is it a Trustee
A7: Trust Name / Trustee
A8: Registered office | B8: MAGNUS BUSINESS ADVISERS AND ACCOUNTANTS, UNIT 10 , 39 OLD CLEVELAND ROAD , CAPALABA QLD 4157 | E8: Principal place of business | F8: 160 Alperton Road, Burbank QLD 4156
C9: From
A10: Current Director | B10: Rachel Anne Harder | C10: 44651
A11: Current Secretary | B11: Rachel Anne Harder | C11: 44651
A13: Does this Company have Loans | B13: Yes | E13: Is there loan documents in place | F13: Yes
D14: Shares | E14: Beneficially Held
A15: Current Shareholdings | B15: Prov1322 Global Pty Ltd | D15: 100 | E15: No
A17: Current Bank Accounts | B17: Bank | C17: BSB | D17: Account | E17: Date Opened
B18: Westpac | C18: 034-076 | D18: 709783 | E18: 45356
B19: NAB | C19: 084-435 | D19: 767243550 | E19: 44658
A24: Folder Storage | B24: Gen2612 | C24: Abbreviation | D24: Gen2612
A26: Company Register | B26: Type | C26: Folder | D26: Date | E26: Manual | F26: Electronicaly Stored | G26: By Whom
A27: Application for Incorporation | B27: ASIC Docs | C27: =VLOOKUP(B27,'Document Type'!$B$6:$C$34,2,FALSE) -> General | D27: 44651 | F27: Application for Incorporation Gen2612
A28: Application for Shares | B28: Members | C28: =VLOOKUP(B28,'Document Type'!$B$6:$C$34,2,FALSE) -> Register of Members | D28: 44714 | F28: Applications for Shares Gen2612
A29: Certificate of Registration | B29: Company Setup | C29: =VLOOKUP(B29,'Document Type'!$B$6:$C$34,2,FALSE) -> Company Setup | D29: 44714 | F29: Certificate of Registration Gen212
A30: Commissioner of Tax | B30: Members | C30: =VLOOKUP(B30,'Document Type'!$B$6:$C$34,2,FALSE) -> Register of Members | D30: 44651 | F30: Letter to Commissioner of Tax Gen2612
A31: Constituition | B31: Constitution | C31: =VLOOKUP(B31,'Document Type'!$B$6:$C$34,2,FALSE) -> Constitution | D31: 44850 | F31: Constitution Gen2612.pdf
A32: Corporate Key | B32: Corporate Key | C32: =VLOOKUP(B32,'Document Type'!$B$6:$C$34,2,FALSE) -> General | D32: 45106 | F32: Corporate Key Gen2612
A33: EOY ASIC FY22 | B33: EOY ASIC | C33: =VLOOKUP(B33,'Document Type'!$B$6:$C$34,2,FALSE) -> General | D33: 44651 | F33: EOY ASIC FY22 Gen2612
A34: EOY ASIC FY24 | B34: EOY ASIC | C34: =VLOOKUP(B34,'Document Type'!$B$6:$C$34,2,FALSE) -> General | D34: 45473 | F34: EOY ASIC FY24 Gen2612
A35: EOY ASIC FY243 | B35: EOY ASIC | C35: =VLOOKUP(B35,'Document Type'!$B$6:$C$34,2,FALSE) -> General | D35: 45107 | F35: EOY ASIC FY23 Gen2612
A36: EOY ATO FY23 | B36: EOY ATO | C36: =VLOOKUP(B36,'Document Type'!$B$6:$C$34,2,FALSE) -> General | D36: 45107 | F36: EOY ATO FY23 Gen2612
A37: EOY ATO FY24 | B37: EOY ATO | C37: =VLOOKUP(B37,'Document Type'!$B$6:$C$34,2,FALSE) -> General | D37: 45473 | F37: EOY ATO FY24 Gen2612
A38: EOY NAB 767243550 FY22 | B38: Bank Statements | C38: =VLOOKUP(B38,'Document Type'!$B$6:$C$34,2,FALSE) -> General | D38: 45562 | F38: EOY NAB 767243550 FY22 Gen2612 | G38: Rachel
A39: EOY NAB 767243550 FY23 | B39: Bank Statements | C39: =VLOOKUP(B39,'Document Type'!$B$6:$C$34,2,FALSE) -> General | D39: 45562 | F39: EOY NAB 767243550 FY23 Gen2612 | G39: Rachel
A40: EOY NAB 767243550 FY24 | B40: Bank Statements | C40: =VLOOKUP(B40,'Document Type'!$B$6:$C$34,2,FALSE) -> General | D40: 45562 | F40: EOY NAB 767243550 FY24 Gen2612 | G40: Rachel
A41: EOY WBC 709783 FY24 | B41: Bank Statements | C41: =VLOOKUP(B41,'Document Type'!$B$6:$C$34,2,FALSE) -> General | D41: 45562 | F41: EOY WBC 709783 FY24 Gen2612 | G41: Rachel
A42: Loan Facility Deed Rachel to Gen2612 | B42: Loan Agreement | C42: =VLOOKUP(B42,'Document Type'!$B$6:$C$34,2,FALSE) -> Loans and Security | D42: 45517 | F42: In Folder Called "Rachel to Gen2612"
A43: Loan Gen2612 to Rachel | B43: Loan Agreement | C43: =VLOOKUP(B43,'Document Type'!$B$6:$C$34,2,FALSE) -> Loans and Security | D43: 44658 | F43: In Folder Called "Gen2612 to Rachel"
A44: Loan GEN2612 to Tekna | B44: Loan Agreement | C44: =VLOOKUP(B44,'Document Type'!$B$6:$C$34,2,FALSE) -> Loans and Security | D44: 45219 | F44: In Folder Called "GEN2612 to Tekna"
A45: Loan GEN2612 to THIS | B45: Loan Agreement | C45: =VLOOKUP(B45,'Document Type'!$B$6:$C$34,2,FALSE) -> Loans and Security | D45: 44713 | F45: In Folder Called "GEN2612 to THSI"
A46: Loan THFT to GEN2612 | B46: Loan Agreement | C46: =VLOOKUP(B46,'Document Type'!$B$6:$C$34,2,FALSE) -> Loans and Security | D46: 44658 | F46: In Folder called "THFT to GEN2612"
A47: Officeholder Consent | B47: Members | C47: =VLOOKUP(B47,'Document Type'!$B$6:$C$34,2,FALSE) -> Register of Members | D47: 45035 | F47: Officeholder Consent Rachel Harder Gen2612
A48: Register of Charges | B48: Members | C48: =VLOOKUP(B48,'Document Type'!$B$6:$C$34,2,FALSE) -> Register of Members | D48: 44714 | F48: Register of Charges Gen2612
A49: Register of Debentures | B49: Members | C49: =VLOOKUP(B49,'Document Type'!$B$6:$C$34,2,FALSE) -> Register of Members | D49: 44714 | F49: Register of Debentures Gen2612
A50: Resolution of Members | B50: Members | C50: =VLOOKUP(B50,'Document Type'!$B$6:$C$34,2,FALSE) -> Register of Members | D50: 44714 | F50: Resolution of Members Gen2612
A51: Security Deed Rachel to Gen2612 | B51: Security Deed | C51: =VLOOKUP(B51,'Document Type'!$B$6:$C$34,2,FALSE) -> Loans and Security | D51: 45517 | F51: In Folder Called "Rachel to Gen2612"
A52: Share Certificate | B52: Members | C52: =VLOOKUP(B52,'Document Type'!$B$6:$C$34,2,FALSE) -> Register of Members | D52: 44714 | F52: Share Certificate Gen2612
A53: Financials 2024 | C53: =VLOOKUP(B53,'Document Type'!$B$6:$C$34,2,FALSE) -> #N/A | D53: 45852 | F53: [SIGNED] Gen2612 Pty Ltd - Financials 2024 | G53: Rachel
A54: Tax Return 2024 | C54: =VLOOKUP(B54,'Document Type'!$B$6:$C$34,2,FALSE) -> #N/A | D54: 45852 | F54: [SIGNED] Gen2612 Pty Ltd - Tax return 2024 | G54: Rachel
A55: Bank Statements | B55: Bank Statements | C55: =VLOOKUP(B55,'Document Type'!$B$6:$C$34,2,FALSE) -> General | D55: 45884 | F55: 2. WBC 709783 FY25 Gen2612 - 05.09.24 - 05.12.24 | G55: Sophie
A56: Bank Statements | B56: Bank Statements | C56: =VLOOKUP(B56,'Document Type'!$B$6:$C$34,2,FALSE) -> General | D56: 45884 | F56: 3. WBC 709783 FY25 Gen2612 - 05.12.24 - 05.03.25 | G56: Sophie
A57: Bank Statements | B57: Bank Statements | C57: =VLOOKUP(B57,'Document Type'!$B$6:$C$34,2,FALSE) -> General | D57: 45884 | F57: 4. WBC 709783 FY25 Gen2612 - 05.03.25 - 05.06.25 | G57: Sophie
C58: =VLOOKUP(B58,'Document Type'!$B$6:$C$34,2,FALSE) -> #N/A
C59: =VLOOKUP(B59,'Document Type'!$B$6:$C$34,2,FALSE) -> #N/A
C60: =VLOOKUP(B60,'Document Type'!$B$6:$C$34,2,FALSE) -> #N/A
C61: =VLOOKUP(B61,'Document Type'!$B$6:$C$34,2,FALSE) -> #N/A
A64: Register of Members
A65: Date | B65: Issue, transfer,share split, buy back or Cancelation | C65: Class of Share | D65: Certification Number | E65: Serial Number From | F65: Serial Number To | G65: Number of Shares Aquired | H65: Trf'd to / Trf'd from | I65: Amount Paid Per Share | J65: Amount Unpaid per Share | K65: Fully Paid? (Y/N) | L65: Total Number os Shares Held | M65: Total Amount paid fo the shares | N65: Are the Shares Benedicially Held | O65: Owner / Buyer / Seller | P65: ASIC Document Number
A66: 44651 | B66: Issue | C66: ORD | G66: 100 | I66: 1 | K66: Y | L66: 100 | M66: 100 | N66: N | O66: Prov1322 Global ATF Team Harder Family Trust
A71: Register of Loans
A72: From | B72: To | C72: Amount | D72: Date | E72: Security | F72: PPSR
A73: Gen2612 | B73: Rachel | C73: 3000000 | D73: 44658 | E73: Yes | F73: Yes
A74: Team Harder Family Trust | B74: Gen2612 | C74: 100000000 | D74: 44658 | E74: Yes | F74: Yes
A75: Gen2612 | B75: Team Harder Super Investments | C75: 3000000 | D75: 44713 | E75: Yes | F75: Yes
A76: Gen2612 | B76: Tekna | C76: 2000000 | D76: 45219 | E76: Yes | F76: Yes
A80: Register of Assets - Non Trading
A81: Item | B81: Purchase Date | C81: Purchase Price | D81: Sale Date | E81: Sale Price | F81: Profit
F82: =Table791322[[#This Row],[Purchase Price]]-Table791322[[#This Row],[Sale Price]] -> 0
F83: =Table791322[[#This Row],[Purchase Price]]-Table791322[[#This Row],[Sale Price]] -> 0
F84: =Table791322[[#This Row],[Purchase Price]]-Table791322[[#This Row],[Sale Price]] -> 0
F85: =Table791322[[#This Row],[Purchase Price]]-Table791322[[#This Row],[Sale Price]] -> 0
F86: =Table791322[[#This Row],[Purchase Price]]-Table791322[[#This Row],[Sale Price]] -> 0
F87: =Table791322[[#This Row],[Purchase Price]]-Table791322[[#This Row],[Sale Price]] -> 0
F88: =Table791322[[#This Row],[Purchase Price]]-Table791322[[#This Row],[Sale Price]] -> 0
F89: =Table791322[[#This Row],[Purchase Price]]-Table791322[[#This Row],[Sale Price]] -> 0
F90: =Table791322[[#This Row],[Purchase Price]]-Table791322[[#This Row],[Sale Price]] -> 0
F91: =Table791322[[#This Row],[Purchase Price]]-Table791322[[#This Row],[Sale Price]] -> 0
F92: =Table791322[[#This Row],[Purchase Price]]-Table791322[[#This Row],[Sale Price]] -> 0
F93: =Table791322[[#This Row],[Purchase Price]]-Table791322[[#This Row],[Sale Price]] -> 0
... F99: =Table791322[[#This Row],[Purchase Price]]-Table791322[[#This Row],[Sale Price]] -> 0

Sheet Team Harder Super Fund
A1: All Companies
A3: Team Harder Super Fund | I3: To DO
A4: ACN: | C4: ABN: | D4: 17 209 120 631 | F4: TFN: | G4: 534 254 470
A5: Date Incorporated | E5: Shares on Issue | I5: Need to add all share purchases in assets
A6: Purpose: | E6: Is it a Trustee | F6: Yes
A7: Trust Name / Trustee
A8: Registered office | E8: Principal place of business
C9: From
A10: Current Director
A11: Current Secretary
A13: Does this Company have Loans | B13: No | E13: Is there loan documents in place | F13: No
D14: Shares | E14: Beneficially Held
A15: Current Shareholdings
A17: Current Bank Accounts | B17: Bank | C17: BSB | D17: Account | E17: Date Opened
B18: NAB Trade | C18: 083-052 | D18: 304656703 | E18: 44137
A24: Folder Storage | B24: Team Harder Super Investments | C24: Abbreviation | D24: THSF
A26: Company Register | B26: Type | C26: Folder | D26: Date | E26: Manual | F26: Electronicaly Stored | G26: By Whom
A27: SMSF Deed | B27: Trust Deed | C27: =VLOOKUP(B27,'Document Type'!$B$6:$C$34,2,FALSE) -> Trust Deed | D27: 44130 | E27: No | F27: SMSF Deed THSF | G27: Sophie Harder
A28: EOY ATO FY23 THSF | B28: EOY ATO | C28: =VLOOKUP(B28,'Document Type'!$B$6:$C$34,2,FALSE) -> General | D28: 45107 | E28: No | F28: EOY ATO FY23 THSF | G28: Sophie Harder
A29: EOY ATO FY23 040723 showing debt paid | B29: EOY ATO | C29: =VLOOKUP(B29,'Document Type'!$B$6:$C$34,2,FALSE) -> General | D29: 45111 | E29: No | F29: EOY ATO FY23 040723 THSF | G29: Sophie Harder
A30: Resolution of Members on Setup | B30: Company Setup | C30: =VLOOKUP(B30,'Document Type'!$B$6:$C$34,2,FALSE) -> Company Setup | D30: 44127 | E30: No | F30: Resolution of Members on Setup THSF | G30: Sophie Harder
A31: Formation Documents | B31: Company Setup | C31: =VLOOKUP(B31,'Document Type'!$B$6:$C$34,2,FALSE) -> Company Setup | D31: 44127 | F31: Formation Documents THSF | G31: Sophie Harder
A32: Bank Statements | B32: Bank Statements | C32: =VLOOKUP(B32,'Document Type'!$B$6:$C$34,2,FALSE) -> General | D32: 45884 | E32: No | F32: 1. WBC 727658 FY25 THSF - 11.07.24 - 11.10.24 | G32: Sophie Harder
A33: Bank Statements | B33: Bank Statements | C33: =VLOOKUP(B33,'Document Type'!$B$6:$C$34,2,FALSE) -> General | D33: 45884 | E33: No | F33: 2. WBC 727658 FY25 THSF - 11.10.24 - 10.01.25 | G33: Sophie Harder
A34: Bank Statements | B34: Bank Statements | C34: =VLOOKUP(B34,'Document Type'!$B$6:$C$34,2,FALSE) -> General | D34: 45884 | E34: No | F34: 3. WBC 727658 FY25 THSF - 10.01.25 - 11.04.25 | G34: Sophie Harder
A35: Bank Statements | B35: Bank Statements | C35: =VLOOKUP(B35,'Document Type'!$B$6:$C$34,2,FALSE) -> General | D35: 45884 | E35: No | F35: 4. WBC 727658 FY25 THSF - 11.04.25 - 11.07.25 | G35: Sophie Harder
A36: Bank Statements | B36: Bank Statements | C36: =VLOOKUP(B36,'Document Type'!$B$6:$C$34,2,FALSE) -> General | D36: 45884 | E36: No | F36: 1. WBC 727658 FY26 THSF - 11.04.25 - 11.07.25 | G36: Sophie Harder
C37: =VLOOKUP(B37,'Document Type'!$B$6:$C$34,2,FALSE) -> #N/A | E37: No
C38: =VLOOKUP(B38,'Document Type'!$B$6:$C$34,2,FALSE) -> #N/A | E38: No
C39: =VLOOKUP(B39,'Document Type'!$B$6:$C$34,2,FALSE) -> #N/A | E39: No
C40: =VLOOKUP(B40,'Document Type'!$B$6:$C$34,2,FALSE) -> #N/A | E40: No
C41: =VLOOKUP(B41,'Document Type'!$B$6:$C$34,2,FALSE) -> #N/A | E41: No
C42: =VLOOKUP(B42,'Document Type'!$B$6:$C$34,2,FALSE) -> #N/A | E42: No
C43: =VLOOKUP(B43,'Document Type'!$B$6:$C$34,2,FALSE) -> #N/A | E43: No
C44: =VLOOKUP(B44,'Document Type'!$B$6:$C$34,2,FALSE) -> #N/A | E44: No
C45: =VLOOKUP(B45,'Document Type'!$B$6:$C$34,2,FALSE) -> #N/A | E45: No
C46: =VLOOKUP(B46,'Document Type'!$B$6:$C$34,2,FALSE) -> #N/A | E46: No
C47: =VLOOKUP(B47,'Document Type'!$B$6:$C$34,2,FALSE) -> #N/A | E47: No
C48: =VLOOKUP(B48,'Document Type'!$B$6:$C$34,2,FALSE) -> #N/A | E48: No
... C61: =VLOOKUP(B61,'Document Type'!$B$6:$C$34,2,FALSE) -> #N/A | E61: No
A64: Register of Members
A65: Date | B65: Issue, transfer,share split, buy back or Cancelation | C65: Class of Share | D65: Certification Number | E65: Serial Number From | F65: Serial Number To | G65: Number of Shares Aquired | H65: Trf'd to / Trf'd from | I65: Amount Paid Per Share | J65: Amount Unpaid per Share | K65: Fully Paid? (Y/N) | L65: Total Number os Shares Held | M65: Total Amount paid fo the shares | N65: Are the Shares Benedicially Held | O65: Owner / Buyer / Seller | P65: ASIC Document Number
A93: Register of Loans
A94: From | B94: To | C94: Amount | D94: Date | E94: Security | F94: PPSR
A102: Register of Assets - Non Trading
A103: Item | B103: Purchase Date | C103: Purchase Price | D103: Sale Date | E103: Sale Price | F103: Profit
F104: =Table791318[[#This Row],[Purchase Price]]-Table791318[[#This Row],[Sale Price]] -> 0
F105: =Table791318[[#This Row],[Purchase Price]]-Table791318[[#This Row],[Sale Price]] -> 0
F106: =Table791318[[#This Row],[Purchase Price]]-Table791318[[#This Row],[Sale Price]] -> 0
F107: =Table791318[[#This Row],[Purchase Price]]-Table791318[[#This Row],[Sale Price]] -> 0
F108: =Table791318[[#This Row],[Purchase Price]]-Table791318[[#This Row],[Sale Price]] -> 0
F109: =Table791318[[#This Row],[Purchase Price]]-Table791318[[#This Row],[Sale Price]] -> 0
F110: =Table791318[[#This Row],[Purchase Price]]-Table791318[[#This Row],[Sale Price]] -> 0
F111: =Table791318[[#This Row],[Purchase Price]]-Table791318[[#This Row],[Sale Price]] -> 0
F112: =Table791318[[#This Row],[Purchase Price]]-Table791318[[#This Row],[Sale Price]] -> 0
F113: =Table791318[[#This Row],[Purchase Price]]-Table791318[[#This Row],[Sale Price]] -> 0
F114: =Table791318[[#This Row],[Purchase Price]]-Table791318[[#This Row],[Sale Price]] -> 0
F115: =Table791318[[#This Row],[Purchase Price]]-Table791318[[#This Row],[Sale Price]] -> 0
... F121: =Table791318[[#This Row],[Purchase Price]]-Table791318[[#This Row],[Sale Price]] -> 0

Sheet Team Harder
A1: All Companies
A3: Team Harder Pty Ltd | I3: To DO
A4: ACN: | B4: 645 359 495 | C4: ABN: | F4: TFN:
A5: Date Incorporated | B5: 44127 | E5: Shares on Issue | F5: 100 | I5: Need ot find paper work for robert to transfer shares to rachel
A6: Purpose: | B6: To Act as Trustee for Team Harder Super Fund | E6: Is it a Trustee | F6: Yes
A7: Trust Name / Trustee | B7: Team Harder Super Fund
A8: Registered office | B8: MAGNUS BUSINESS ADVISERS AND ACCOUNTANTS, UNIT 10 , 39 OLD CLEVELAND ROAD , CAPALABA QLD 4157 | E8: Principal place of business | F8: 160 Alperton Road, Burbank QLD 4156
C9: From
A10: Current Director | B10: Rachel Anne Harder | C10: 44127
A11: Current Secretary
A13: Does this Company have Loans | B13: Yes | E13: Is there loan documents in place | F13: Yes
D14: Shares | E14: Beneficially Held
A15: Current Shareholdings | B15: Rachel Anne Harder | D15: 100 | E15: Yes
A17: Current Bank Accounts | B17: Bank | C17: BSB | D17: Account | E17: Date Opened
B18: NAB
B19: Westpac
A24: Folder Storage | B24: Team Harder | C24: Abbreviation | D24: TH
A26: Company Register | B26: Type | C26: Folder | D26: Date | E26: Manual | F26: Electronicaly Stored | G26: By Whom
A27: EOY ASIC FY24 | B27: EOY ASIC | C27: =VLOOKUP(B27,'Document Type'!$B$6:$C$34,2,FALSE) -> General | D27: 45471 | F27: EOY ASIC FY24 | G27: Sophie Harder
A28: EOY ATO FY24 | B28: EOY ATO | C28: =VLOOKUP(B28,'Document Type'!$B$6:$C$34,2,FALSE) -> General | D28: 45471 | F28: EOY ATO FY24 | G28: Sophie Harder
A29: Resolution of Members on Setup | B29: Company Setup | C29: =VLOOKUP(B29,'Document Type'!$B$6:$C$34,2,FALSE) -> Company Setup | D29: 44127 | E29: No | F29: Resolution of Members on Setup TH | G29: Sophie Harder
A30: Certifcate of Registration | B30: Company Setup | C30: =VLOOKUP(B30,'Document Type'!$B$6:$C$34,2,FALSE) -> Company Setup | D30: 44127 | F30: Certifcate of Registration TH | G30: Sophie Harder
A31: Formation Documents | B31: Company Setup | C31: =VLOOKUP(B31,'Document Type'!$B$6:$C$34,2,FALSE) -> Company Setup | D31: 44127 | F31: Formation Documents TH | G31: Sophie Harder
A32: Minutes Company Setup | B32: Minutes | C32: =VLOOKUP(B32,'Document Type'!$B$6:$C$34,2,FALSE) -> Minutes | D32: 44127 | F32: Minutes Company Setup TH | G32: Sophie Harder
A33: Share Certifcate Rachel | B33: Members | C33: =VLOOKUP(B33,'Document Type'!$B$6:$C$34,2,FALSE) -> Register of Members | D33: 44127 | F33: Share Certifcate Rachel TH | G33: Sophie Harder
A34: Share Certifcate Robert | B34: Members | C34: =VLOOKUP(B34,'Document Type'!$B$6:$C$34,2,FALSE) -> Register of Members | D34: 44127 | F34: Share Certifcate Robert TH | G34: Sophie Harder
A35: Signed Application for Shares Robert | B35: Members | C35: =VLOOKUP(B35,'Document Type'!$B$6:$C$34,2,FALSE) -> Register of Members | D35: 44127 | F35: Signed Application for Shares Robert TH | G35: Sophie Harder
A36: Consent Rachel Director | B36: Officers | C36: =VLOOKUP(B36,'Document Type'!$B$6:$C$34,2,FALSE) -> General | D36: 44127 | F36: Consent Rachel Director TH | G36: Sophie Harder
A37: Consent Robert Director | B37: Officers | C37: =VLOOKUP(B37,'Document Type'!$B$6:$C$34,2,FALSE) -> General | D37: 44127 | F37: Consent Robert Director TH | G37: Sophie Harder
A38: Rachel ATO Declaration | B38: Company Setup | C38: =VLOOKUP(B38,'Document Type'!$B$6:$C$34,2,FALSE) -> Company Setup | D38: 44130 | F38: Rachel ATO Declaration TH | G38: Sophie Harder
A39: Robert ATO Declaration | B39: Company Setup | C39: =VLOOKUP(B39,'Document Type'!$B$6:$C$34,2,FALSE) -> Company Setup | D39: 44130 | F39: Robert ATO Declaration TH | G39: Sophie Harder
A40: Signed Application for Shares Rachel | B40: Members | C40: =VLOOKUP(B40,'Document Type'!$B$6:$C$34,2,FALSE) -> Register of Members | D40: 44127 | F40: Signed Application for Shares Rachel TH | G40: Sophie Harder
A41: Consent Company Setup | B41: Company Setup | C41: =VLOOKUP(B41,'Document Type'!$B$6:$C$34,2,FALSE) -> Company Setup | D41: 44130 | F41: Consent Company Setup TH | G41: Sophie Harder
... A50: Constitution | B50: Constitution | C50: =VLOOKUP(B50,'Document Type'!$B$6:$C$34,2,FALSE) -> Constitution | D50: 44127 | F50: Constitution TH | G50: Sophie Harder
C51: =VLOOKUP(B51,'Document Type'!$B$6:$C$34,2,FALSE) -> #N/A
C52: =VLOOKUP(B52,'Document Type'!$B$6:$C$34,2,FALSE) -> #N/A
C53: =VLOOKUP(B53,'Document Type'!$B$6:$C$34,2,FALSE) -> #N/A
C54: =VLOOKUP(B54,'Document Type'!$B$6:$C$34,2,FALSE) -> #N/A
C55: =VLOOKUP(B55,'Document Type'!$B$6:$C$34,2,FALSE) -> #N/A
C56: =VLOOKUP(B56,'Document Type'!$B$6:$C$34,2,FALSE) -> #N/A
C57: =VLOOKUP(B57,'Document Type'!$B$6:$C$34,2,FALSE) -> #N/A
C58: =VLOOKUP(B58,'Document Type'!$B$6:$C$34,2,FALSE) -> #N/A
C59: =VLOOKUP(B59,'Document Type'!$B$6:$C$34,2,FALSE) -> #N/A
C60: =VLOOKUP(B60,'Document Type'!$B$6:$C$34,2,FALSE) -> #N/A
C61: =VLOOKUP(B61,'Document Type'!$B$6:$C$34,2,FALSE) -> #N/A
A63: Register of Members
A64: Date | B64: Issue, transfer,share split, buy back or Cancelation | C64: Class of Share | D64: Certification Number | E64: Serial Number From | F64: Serial Number To | G64: Number of Shares Aquired | H64: Trf'd to / Trf'd from | I64: Amount Paid Per Share | J64: Amount Unpaid per Share | K64: Fully Paid? (Y/N) | L64: Total Number os Shares Held | M64: Total Amount paid fo the shares | N64: Are the Shares Benedicially Held | O64: Owner / Buyer / Seller | P64: ASIC Document Number
A65: 44127 | B65: Issue | C65: ord | G65: 50 | I65: 1 | K65: Y | L65: 50 | M65: 50 | N65: Y | O65: Rachel Anne Harder
A66: 44127 | B66: Issue | C66: ord | G66: 50 | I66: 1 | K66: y | L66: 50 | M66: 50 | N66: y | O66: Robert John Harder
A92: Register of Loans
A93: From | B93: To | C93: Amount | D93: Date | E93: Security | F93: PPSR
A101: Register of Assets - Non Trading
A102: Item | B102: Purchase Date | C102: Purchase Price | D102: Sale Date | E102: Sale Price | F102: Profit

Sheet Tekna Homes
A1: All Companies
A3: Tekna Homes Pty Ltd | I3: Things to Do:
A4: ACN: | B4: 658 462 732 | C4: ABN: | D4: 34 658 462 732 | F4: TFN: | G4: 605 934 180 | I4: Need Structure Group
A5: Date Incorporated | B5: 44651 | E5: Shares on Issue | F5: 400100
A6: Purpose: | E6: Is it a Trustee
A7: Trust Name
A8: Registered office | B8: 160 Alperton Road, Burbank QLD 4156 | E8: Principal place of business | F8: 160 Alperton Road, Burbank QLD 4156
C9: From
A10: Current Director | B10: Andrew Mark Clement | C10: 44875
A11: Current Secretary | B11: Andrew Mark Clement | C11: 45194
A13: Does this Company have Loans | B13: Yes | E13: Is there loan documents in place | F13: Yes
D15: Shares | E15: Beneficially Held
A16: Current Shareholdings | B16: Tekna Pty Ltd | D16: 400100 | E16: Yes
A18: Current Bank Accounts | B18: Bank | C18: BSB | D18: Account | E18: Date Opened
B19: NAB | C19: 084435 | D19: 302971208 | E19: 44697
B20: Westpac | C20: 034-076 | D20: 702733 | E20: 45301
A25: Folder Storage | B25: Tekna Homes | C25: Abbreviation | D25: TH
A27: Company Register | B27: Type | C27: Folder | D27: Date | E27: Manual | F27: Electronicaly Stored | G27: By Whom
A28: EOY ASIC FY24 | B28: EOY ASIC | C28: =VLOOKUP(B28,'Document Type'!$B$6:$C$34,2,FALSE) -> General | D28: 45471 | F28: EOY ASIC FY24 TH | G28: Sophie Harder
A29: EOY ATO FY24 TH | B29: EOY ATO | C29: =VLOOKUP(B29,'Document Type'!$B$6:$C$34,2,FALSE) -> General | D29: 45471 | F29: EOY ATO FY24 TH | G29: Sophie Harder
A30: Constituition | B30: Constitution | C30: =VLOOKUP(B30,'Document Type'!$B$6:$C$34,2,FALSE) -> Constitution | D30: 44714 | F30: Constitution Tekna Licence TH.pdf | G30: Sophie Harder
A31: ASIC Key | B31: ASIC Key | C31: =VLOOKUP(B31,'Document Type'!$B$6:$C$34,2,FALSE) -> General | D31: 45100 | F31: ASIC Key TH | G31: Sophie Harder
A32: Corporate Key | B32: Corporate Key | C32: =VLOOKUP(B32,'Document Type'!$B$6:$C$34,2,FALSE) -> General | D32: 45100 | F32: Corporate Key TH | G32: Sophie Harder
A33: EOY ASIC FY23 | B33: EOY ASIC | C33: =VLOOKUP(B33,'Document Type'!$B$6:$C$34,2,FALSE) -> General | D33: 45107 | F33: EOY ASIC FY23 TH | G33: Sophie Harder
A34: Registered Office | B34: ASIC Docs | C34: General | D34: 44698 | F34: Registered Office Multiplace TH | G34: Sophie Harder
A35: Change of Address | B35: ASIC Docs | C35: =VLOOKUP(B35,'Document Type'!$B$6:$C$34,2,FALSE) -> General | D35: 44698 | F35: Change of Business Address TH | G35: Sophie Harder
A36: ASIC Trading Name | B36: ASIC Docs | C36: =VLOOKUP(B36,'Document Type'!$B$6:$C$34,2,FALSE) -> General | D36: 45204 | F36: ASIC Trading Name TH | G36: Sophie Harder
A37: ASIC Key For Trading Name Tekna Homes | B37: ASIC Key | C37: =VLOOKUP(B37,'Document Type'!$B$6:$C$34,2,FALSE) -> General | D37: 45204 | F37: ASIC Key For Trading Name Tekna Homes TH | G37: Sophie Harder
A38: Summary | B38: Members | C38: =VLOOKUP(B38,'Document Type'!$B$6:$C$34,2,FALSE) -> Register of Members | D38: 45194 | F38: Summary TH | G38: Sophie Harder
A39: Application for Incorporation | B39: ASIC Docs | C39: =VLOOKUP(B39,'Document Type'!$B$6:$C$34,2,FALSE) -> General | D39: 44651 | F39: Application for Incorporation TH | G39: Sophie Harder
A40: Solvency Minutes | B40: Minutes | C40: =VLOOKUP(B40,'Document Type'!$B$6:$C$34,2,FALSE) -> Minutes | D40: 45016 | F40: Annual Solvency Minutes TH | G40: Sophie Harder
A41: Resolution of Members | B41: Members | C41: =VLOOKUP(B41,'Document Type'!$B$6:$C$34,2,FALSE) -> Register of Members | D41: 44714 | F41: Resolution of Members TH | G41: Sophie Harder
A42: Register of Debentures | B42: Members | C42: =VLOOKUP(B42,'Document Type'!$B$6:$C$34,2,FALSE) -> Register of Members | D42: 44714 | F42: Register of Debentures TH | G42: Sophie Harder
A43: Register of Charges | B43: Members | C43: =VLOOKUP(B43,'Document Type'!$B$6:$C$34,2,FALSE) -> Register of Members | D43: 45035 | F43: Register of Chargers TH | G43: Sophie Harder
A44: Officeholder Consent | B44: Members | C44: =VLOOKUP(B44,'Document Type'!$B$6:$C$34,2,FALSE) -> Register of Members | D44: 44714 | F44: Officeholder Consent Samuel James Harder TH | G44: Sophie Harder
A45: Register of Members | B45: Members | C45: =VLOOKUP(B45,'Document Type'!$B$6:$C$34,2,FALSE) -> Register of Members | D45: 44714 | F45: Register of Members TH | G45: Sophie Harder
A46: Application for Shares | B46: Members | C46: =VLOOKUP(B46,'Document Type'!$B$6:$C$34,2,FALSE) -> Register of Members | D46: 45035 | F46: Application for Shares TH | G46: Sophie Harder
... A56: Cabinetry Making Machinery Invoice | B56: Asset | C56: =VLOOKUP(B56,'Document Type'!$B$6:$C$34,2,FALSE) -> Assets | D56: 45600 | F56: Cabinetry Making Machinery TH | G56: Sophie Harder
C57: =VLOOKUP(B57,'Document Type'!$B$6:$C$34,2,FALSE) -> #N/A
C58: =VLOOKUP(B58,'Document Type'!$B$6:$C$34,2,FALSE) -> #N/A
C59: =VLOOKUP(B59,'Document Type'!$B$6:$C$34,2,FALSE) -> #N/A
C60: =VLOOKUP(B60,'Document Type'!$B$6:$C$34,2,FALSE) -> #N/A
C61: =VLOOKUP(B61,'Document Type'!$B$6:$C$34,2,FALSE) -> #N/A
C62: =VLOOKUP(B62,'Document Type'!$B$6:$C$34,2,FALSE) -> #N/A
C63: =VLOOKUP(B63,'Document Type'!$B$6:$C$34,2,FALSE) -> #N/A
A65: Register of Members
A66: Date | B66: Issue, transfer,share split, buy back or Cancelation | C66: Class of Share | D66: Certification Number | E66: Serial Number From | F66: Serial Number To | G66: Number of Shares Aquired | H66: Trf'd to / Trf'd from | I66: Amount Paid Per Share | J66: Amount Unpaid per Share | K66: Fully Paid? (Y/N) | L66: Total Number os Shares Held | M66: Total Amount paid fo the shares | N66: Are the Shares Benedicially Held | O66: Owner / Buyer / Seller | P66: ASIC Document Number
A67: 44651 | B67: Issue | C67: ORD | E67: 1 | F67: 100 | G67: 100 | I67: 1 | K67: Y | L67: 100 | M67: 100 | N67: Y | O67: Tekna
A68: 44875 | B68: Issue | C68: ORD | E68: 101 | F68: 100100 | G68: 100000 | I68: 1 | K68: Y | L68: 100100 | M68: 100000 | N68: Y | O68: Tekna
A69: 45261 | B69: Issue | C69: ORD | E69: 100101 | F69: 400100 | G69: 300000 | I69: 1 | K69: Y | L69: 400100 | M69: 300000 | N69: Y | O69: Tekna
A71: Register of Loans
A72: From | B72: To | C72: Amount | D72: Date | E72: Security | F72: PPSR
A73: Tekna Drafting | B73: Tekna Homes | C73: 3000000 | D73: 45219 | E73: Yes | F73: Yes
A76: Register of Assets - Non Trading
A77: Item | B77: Purchase Date | C77: Purchase Price | D77: Sale Date | E77: Sale Price | F77: Profit
F78: =Table791333[[#This Row],[Purchase Price]]-Table791333[[#This Row],[Sale Price]] -> 0
F79: =Table791333[[#This Row],[Purchase Price]]-Table791333[[#This Row],[Sale Price]] -> 0
F80: =Table791333[[#This Row],[Purchase Price]]-Table791333[[#This Row],[Sale Price]] -> 0

Sheet Tekna Drafting
B1: All Companies
B3: Tekna Drafting Pty Ltd | J3: Things to Do:
B4: ACN: | C4: 159 565 849 | D4: ABN: | E4: 96 159 565 849 | G4: TFN: | H4: 938 078 821 | J4: Need Structure Group
B5: Date Incorporated | C5: 41109 | F5: Shares on Issue | G5: 100 | J5: find scanned in shared equity agreements
B6: Purpose: | C6: Loans to Tekna Group and Others and Investments | F6: Is it a Trustee | G6: No
B7: Trust Name
B8: Registered office | C8: 160 Alperton Road, Burbank QLD 4156 | F8: Principal place of business | G8: 160 Alperton Road, Burbank QLD 4156
D9: From
B10: Current Director | C10: Andrew Mark Clement | D10: 44571
B11: Current Secretary | C11: Andrew Mark Clement | D11: 44286
B13: Does this Company have Loans | C13: Yes | F13: Is there loan documents in place
E14: Shares | F14: Beneficially Held
B15: Current Shareholdings | C15: Tekna Pty Ltd | E15: 100 | F15: Yes
B17: Current Bank Accounts | C17: Bank | D17: BSB | E17: Account | F17: Date Opened
C18: NAB | D18: 084-435 | E18: 922875532 | F18: 44663
C19: Westpac | D19: 034-076 | E19: 699626 | F19: 45282
B24: Folder Storage | C24: Tekna Drafting | D24: Abbreviation | E24: TD
B26: Company Register | C26: Type | D26: Folder | E26: Date | F26: Manual | G26: Electronicaly Stored | H26: By Whom
B27: Constitution (Previous Rock Invest QLD) | C27: Constitution | D27: =VLOOKUP(C27,'Document Type'!$B$6:$C$34,2,FALSE) -> Constitution | E27: 41109 | F27: No | G27: Constitution TD | H27: Sophie Harder
B28: Company Setup | C28: Company Setup | D28: =VLOOKUP(C28,'Document Type'!$B$6:$C$34,2,FALSE) -> Company Setup | E28: 41109 | F28: No | G28: Company Setup TD | H28: Sophie Harder
B29: Register of Members Setup TD | C29: Members | D29: =VLOOKUP(C29,'Document Type'!$B$6:$C$34,2,FALSE) -> Register of Members | E29: 41109 | F29: No | G29: Register of Members Setup TD | H29: Sophie Harder
B30: Company Setup and Members Info TD | C30: Members | D30: =VLOOKUP(C30,'Document Type'!$B$6:$C$34,2,FALSE) -> Register of Members | E30: 41109 | F30: No | G30: Company Setup and Members Info TD | H30: Sophie Harder
B31: Tax File Number TD | C31: ATO Docs | D31: =VLOOKUP(C31,'Document Type'!$B$6:$C$34,2,FALSE) -> General | E31: 41114 | F31: No | G31: Tax File Number TD | H31: Sophie Harder
B32: Solvency ASIC FY13 TD | C32: Solvency ASIC | D32: =VLOOKUP(C32,'Document Type'!$B$6:$C$34,2,FALSE) -> General | E32: 41474 | F32: No | G32: Solvency ASIC FY13 TD | H32: Sophie Harder
B33: Solvency ASIC FY14 TD | C33: Solvency ASIC | D33: =VLOOKUP(C33,'Document Type'!$B$6:$C$34,2,FALSE) -> General | E33: 41839 | F33: No | G33: Solvency ASIC FY14 TD | H33: Sophie Harder
B34: Solvency ASIC FY15 TD | C34: Solvency ASIC | D34: =VLOOKUP(C34,'Document Type'!$B$6:$C$34,2,FALSE) -> General | E34: 42204 | F34: No | G34: Solvency ASIC FY15 TD | H34: Sophie Harder
B35: Solvency ASIC FY16 TD | C35: Solvency ASIC | D35: =VLOOKUP(C35,'Document Type'!$B$6:$C$34,2,FALSE) -> General | E35: 42570 | F35: No | G35: Solvency ASIC FY16 TD | H35: Sophie Harder
B36: Solvency ASIC FY17 TD | C36: Solvency ASIC | D36: =VLOOKUP(C36,'Document Type'!$B$6:$C$34,2,FALSE) -> General | E36: 42935 | F36: No | G36: Solvency ASIC FY17 TD | H36: Sophie Harder
B37: Resignation of Director AC TD | C37: Officers | D37: =VLOOKUP(C37,'Document Type'!$B$6:$C$34,2,FALSE) -> General | E37: 42978 | F37: No | G37: Resignation of Director AC TD | H37: Sophie Harder
B38: Appoint of Director JH TD | C38: Officers | D38: =VLOOKUP(C38,'Document Type'!$B$6:$C$34,2,FALSE) -> General | E38: 42978 | F38: No | G38: Appoint of Director JH TD | H38: Sophie Harder
... B80: EOY WBC 699626 FY24 | C80: Bank Statements | D80: =VLOOKUP(C80,'Document Type'!$B$6:$C$34,2,FALSE) -> General | E80: 45562 | F80: No | G80: EOY WBC 699626 FY24 TD | H80: Rachel
D81: =VLOOKUP(C81,'Document Type'!$B$6:$C$34,2,FALSE) -> #N/A | F81: No
D82: =VLOOKUP(C82,'Document Type'!$B$6:$C$34,2,FALSE) -> #N/A | F82: No
D83: =VLOOKUP(C83,'Document Type'!$B$6:$C$34,2,FALSE) -> #N/A | F83: No
D84: =VLOOKUP(C84,'Document Type'!$B$6:$C$34,2,FALSE) -> #N/A | F84: No
D85: =VLOOKUP(C85,'Document Type'!$B$6:$C$34,2,FALSE) -> #N/A | F85: No
D86: =VLOOKUP(C86,'Document Type'!$B$6:$C$34,2,FALSE) -> #N/A | F86: No
D87: =VLOOKUP(C87,'Document Type'!$B$6:$C$34,2,FALSE) -> #N/A | F87: No
B89: Register of Members
B90: Date | C90: Issue, transfer,share split, buy back or Cancelation | D90: Class of Share | E90: Certification Number | F90: Serial Number From | G90: Serial Number To | H90: Number of Shares Aquired | I90: Trf'd to / Trf'd from | J90: Amount Paid Per Share | K90: Amount Unpaid per Share | L90: Fully Paid? (Y/N) | M90: Total Number os Shares Held | N90: Total Amount paid fo the shares | O90: Are the Shares Benedicially Held | P90: Owner / Buyer / Seller | Q90: ASIC Document Number
B91: 41109 | C91: Issue | D91: ORD | E91: 1 | F91: 1 | G91: 100 | J91: 0.01 | L91: Y | M91: 100 | N91: 100 | O91: Y | P91: Robert John Harder
B92: 41963 | C92: Cancel | D92: ORD | E92: 1 | F92: 1 | G92: 100 | L92: y | M92: -100 | N92: -100 | O92: Y | P92: Robert John Harder
B93: 41963 | C93: Issue | D93: ORD | J93: 1 | L93: y | M93: 27 | N93: 27 | O93: N | P93: Harder Developments ATF The Harder Family Trust
B94: 41963 | C94: Issue | D94: ORD | J94: 1 | L94: y | M94: 27 | N94: 27 | O94: N | P94: A Clement Developmentrs QLD ATF Clement Family Trust
B95: 41963 | C95: Issue | D95: ORD | J95: 1 | L95: y | M95: 27 | N95: 27 | O95: N | P95: Plug Investments ATF Plug Family Trust
B96: 41963 | C96: Issue | D96: ORD | J96: 1 | L96: Y | M96: 19 | N96: 19 | O96: Y | P96: The Promise QLD
B97: 42116 | C97: issue | D97: ORD | J97: 1 | L97: Y | M97: 8 | N97: 8 | O97: Y | P97: The Promise QLD
B98: 44494 | C98: Cancel | D98: ORD | J98: 1 | L98: Y | M98: -8 | N98: -8 | O98: Y | P98: The Promise QLD
B99: 44494 | C99: Sell | D99: ORD | J99: 1 | M99: -27 | N99: -27 | P99: A Clement Developmentrs QLD ATF Clement Family Trust
B100: 44494 | C100: Buy | D100: ORD | J100: 1 | M100: 27 | N100: 27 | P100: Harder Developments ATF The Harder Family Trust
B101: 44494 | C101: Sell | D101: ORD | J101: 1 | M101: -9 | N101: -9 | P101: The Promise QLD
B102: 44494 | C102: Buy | D102: ORD | M102: 9 | N102: 9 | P102: Jonathan Lance Ament
B103: 44494 | C103: Sell | D103: ORD | M103: -1 | N103: -1 | P103: The Promise QLD
B104: 44494 | C104: Buy | D104: ORD | M104: 1 | N104: 1 | P104: Harder Developments ATF The Harder Family Trust
B105: 44494 | C105: Sell | D105: ORD | M105: -8 | N105: -8 | P105: The Promise QLD
B106: 44494 | C106: buy | D106: ORD | M106: 8 | N106: 8 | P106: Plug Investments ATF Plug Family Trust
B107: 44651 | C107: Transfer | D107: ORD | M107: -100 | P107: All ABOVE
B108: 44651 | C108: Transfer | D108: ORD | M108: 100 | N108: 100 | P108: Tekna Pty Ltd | Q108: 7EBR13770
B118: Register of Loans
B119: From | C119: To | D119: Amount | E119: Date | F119: Security | G119: PPSR
B120: Tekna | C120: Tekna Drafting | D120: 4000000 | E120: 45216 | F120: Yes | G120: Yes
B121: Tekna Drafting | C121: Homes of Hope | D121: 1000000 | E121: 45216 | F121: Yes | G121: Yes
B122: Tekna Drafting | C122: Tekna Homes | D122: 3000000 | E122: 45216 | F122: Yes | G122: Yes
B123: Tekna Drafting | C123: Tekna Admin | D123: 2000000 | E123: 45275 | F123: Yes | G123: Yes
B128: Register of Assets - Non Trading
B129: Item | C129: Purchase Date | D129: Purchase Price | E129: Sale Date | F129: Sale Price | G129: Profit
B130: Commercial Building Unit 5/8 Nevilles Street | C130: 45280 | D130: 661825
B131: Shared Equity Loan Khyiroya (Deed Of Novation) | C131: 45253 | D131: 245391.05
B132: Shared Equity Loan Mansfield (Deed Of Novation) | C132: 45253 | D132: 154608.95

Sheet Tekna Admin
B1: All Companies
B3: Tekna Admin | J3: Things to Do
B4: ACN: | C4: 673 388 424 | D4: ABN: | E4: 81 673 388 424 | G4: TFN: | H4: 518 585 770
B5: Date Incorporated | C5: 45264 | F5: Shares on Issue | G5: 100 | J5: Structure
B6: Purpose: | C6: Charges a fee to pay for all Groups expenses per Job | F6: Is it a Trustee | G6: No
B7: Trust Name
B8: Registered office | C8: 160 Alperton Road, Burbank QLD 4156 | F8: Principal place of business | G8: 160 Alperton Road, Burbank QLD 4156
D9: From
B10: Current Director | C10: Andrew Mark Clement | D10: 45264
B11: Current Secretary | C11: Andrew Mark Clement | D11: 45264
B13: Does this Company have Loans | C13: Yes | F13: Is there loan documents in place | G13: Yes
E15: Shares | F15: Beneficially Held | G15: Yes
B16: Current Shareholdings | C16: Tekna Pty Ltd | E16: 100 | F16: Yes
B18: Current Bank Accounts | C18: Bank | D18: BSB | E18: Account | F18: Date Opened
C19: NAB | D19: 083-004 | E19: 268693995 | F19: 15/12/2023
C20: Westpac | D20: 034-076 | E20: 699642 | F20: 45282
B24: Folder Storage | C24: Tekna Admin | D24: Abbreviation | E24: TA
B26: Company Register | C26: Type | D26: Folder | E26: Date | F26: Manual | G26: Electronicaly Stored | H26: By Whom
B27: Certificate Rego TA | C27: Company Setup | D27: =VLOOKUP(C27,'Document Type'!$B$6:$C$34,2,FALSE) -> Company Setup | E27: 45264 | G27: Certificate Rego TA | H27: Sophie Harder
B28: Company Setup TA | C28: Company Setup | D28: =VLOOKUP(C28,'Document Type'!$B$6:$C$34,2,FALSE) -> Company Setup | E28: 45264 | G28: Company Setup TA | H28: Sophie Harder
B29: Computer | C29: Asset | D29: =VLOOKUP(C29,'Document Type'!$B$6:$C$34,2,FALSE) -> Assets | E29: 45468 | G29: Computer TA | H29: Sophie Harder
B30: Constitution TA | C30: Constitution | D30: =VLOOKUP(C30,'Document Type'!$B$6:$C$34,2,FALSE) -> Constitution | E30: 45264 | G30: Constitution TA | H30: Sophie Harder
B31: EOY ASIC FY24 | C31: EOY ASIC | D31: =VLOOKUP(C31,'Document Type'!$B$6:$C$34,2,FALSE) -> General | E31: 45471 | G31: EOY ASIC FY24 TA | H31: Sophie Harder
B32: EOY ATO FY24 | C32: EOY ATO | D32: =VLOOKUP(C32,'Document Type'!$B$6:$C$34,2,FALSE) -> General | E32: 45471 | G32: EOY ATO FY24 TA | H32: Sophie Harder
B33: EOY NAB 268693995 FY24 | C33: Bank Statements | D33: =VLOOKUP(C33,'Document Type'!$B$6:$C$34,2,FALSE) -> General | E33: 45562 | G33: EOY NAB 268693995 FY24 TA | H33: Rachel
B34: EOY WBC 699642 FY24 | C34: Bank Statements | D34: =VLOOKUP(C34,'Document Type'!$B$6:$C$34,2,FALSE) -> General | E34: 45562 | G34: EOY WBC 699642 FY24 TA | H34: Rachel
B35: Excavator TA | C35: Asset | D35: =VLOOKUP(C35,'Document Type'!$B$6:$C$34,2,FALSE) -> Assets | E35: 45468 | G35: Excavator TA | H35: Sophie Harder
B36: General Security Deed TD to TA | C36: Loan Agreement | D36: =VLOOKUP(C36,'Document Type'!$B$6:$C$34,2,FALSE) -> Loans and Security | E36: 45275 | G36: General Security Deed TD to TA | H36: Sophie Harder
B37: Loan TD to TA | C37: Loan Agreement | D37: =VLOOKUP(C37,'Document Type'!$B$6:$C$34,2,FALSE) -> Loans and Security | E37: 45275 | G37: Loan TD to TA | H37: Sophie Harder
B38: PPSR Token TA | C38: Loan Agreement | D38: =VLOOKUP(C38,'Document Type'!$B$6:$C$34,2,FALSE) -> Loans and Security | E38: 45275 | G38: PPSR Token TA | H38: Sophie Harder
... B43: Truck | C43: Asset | D43: =VLOOKUP(C43,'Document Type'!$B$6:$C$34,2,FALSE) -> Assets | E43: 45405 | G43: Truck TA | H43: Sophie Harder
B44: Consolidated Tax Return FY24 Tekna Admin | C44: ATO Tax Return | D44: =VLOOKUP(C44,'Document Type'!$B$6:$C$34,2,FALSE) -> General | E44: 45937 | G44: Consolidated Tax Return FY24 Tekna Admin
C45: EOY ASIC | D45: =VLOOKUP(C45,'Document Type'!$B$6:$C$34,2,FALSE) -> General | G45: EOY ASIC FY24 TA
D46: =VLOOKUP(C46,'Document Type'!$B$6:$C$34,2,FALSE) -> #N/A
D47: =VLOOKUP(C47,'Document Type'!$B$6:$C$34,2,FALSE) -> #N/A
D48: =VLOOKUP(C48,'Document Type'!$B$6:$C$34,2,FALSE) -> #N/A
D49: =VLOOKUP(C49,'Document Type'!$B$6:$C$34,2,FALSE) -> #N/A
D50: =VLOOKUP(C50,'Document Type'!$B$6:$C$34,2,FALSE) -> #N/A
D51: =VLOOKUP(C51,'Document Type'!$B$6:$C$34,2,FALSE) -> #N/A
D52: =VLOOKUP(C52,'Document Type'!$B$6:$C$34,2,FALSE) -> #N/A
D53: =VLOOKUP(C53,'Document Type'!$B$6:$C$34,2,FALSE) -> #N/A
D54: =VLOOKUP(C54,'Document Type'!$B$6:$C$34,2,FALSE) -> #N/A
D55: =VLOOKUP(C55,'Document Type'!$B$6:$C$34,2,FALSE) -> #N/A
D56: =VLOOKUP(C56,'Document Type'!$B$6:$C$34,2,FALSE) -> #N/A
D57: =VLOOKUP(C57,'Document Type'!$B$6:$C$34,2,FALSE) -> #N/A
... D61: =VLOOKUP(C61,'Document Type'!$B$6:$C$34,2,FALSE) -> #N/A
B63: Register of Members
B64: Date | C64: Issue, transfer,share split, buy back or Cancelation | D64: Class of Share | E64: Certification Number | F64: Serial Number From | G64: Serial Number To | H64: Number of Shares Aquired | I64: Trf'd to / Trf'd from | J64: Amount Paid Per Share | K64: Amount Unpaid per Share | L64: Fully Paid? (Y/N) | M64: Total Number os Shares Held | N64: Total Amount paid fo the shares | O64: Are the Shares Benedicially Held | P64: Owner / Buyer / Seller | Q64: ASIC Document Number
B65: 4/12/202 | C65: Issue | D65: ORD | E65: 1 | F65: 1 | G65: 100 | H65: 100 | J65: 0.01 | L65: Y | M65: 100 | N65: 1 | O65: Y | P65: Tekna Pty Ltd
B92: Register of Loans
B93: From | C93: To | D93: Amount | E93: Date | F93: Security | G93: PPSR
B94: Tekna Drafting | C94: Tekna Admin | D94: 2000000 | E94: 45275 | F94: Yes | G94: Yes
B101: Register of Assets - Non Trading
B102: Item | C102: Purchase Date | D102: Purchase Price | E102: Sale Date | F102: Sale Price | G102: Profit
B103: Skid Seer Toyota | C103: 45405 | D103: 45454.55 | G103: =Table791337[[#This Row],[Sale Price]]-Table791337[[#This Row],[Purchase Price]] -> -45454.55
B104: Skid Seer Toyota Bucket | C104: 45449 | D104: 6136.36 | G104: =Table791337[[#This Row],[Sale Price]]-Table791337[[#This Row],[Purchase Price]] -> -6136.36
B105: Truck | C105: 45405 | D105: 19090.91 | G105: =Table791337[[#This Row],[Sale Price]]-Table791337[[#This Row],[Purchase Price]] -> -19090.91
B106: Excavtor | C106: 45468 | D106: 80000 | G106: =Table791337[[#This Row],[Sale Price]]-Table791337[[#This Row],[Purchase Price]] -> -80000
B107: Computer | C107: 45468 | D107: 833.65 | G107: =Table791337[[#This Row],[Sale Price]]-Table791337[[#This Row],[Purchase Price]] -> -833.65
G108: =Table791337[[#This Row],[Sale Price]]-Table791337[[#This Row],[Purchase Price]] -> 0
G109: =Table791337[[#This Row],[Sale Price]]-Table791337[[#This Row],[Purchase Price]] -> 0
G110: =Table791337[[#This Row],[Sale Price]]-Table791337[[#This Row],[Purchase Price]] -> 0
G111: =Table791337[[#This Row],[Sale Price]]-Table791337[[#This Row],[Purchase Price]] -> 0
G112: =Table791337[[#This Row],[Sale Price]]-Table791337[[#This Row],[Purchase Price]] -> 0
G113: =Table791337[[#This Row],[Sale Price]]-Table791337[[#This Row],[Purchase Price]] -> 0
G114: =Table791337[[#This Row],[Sale Price]]-Table791337[[#This Row],[Purchase Price]] -> 0
G115: =Table791337[[#This Row],[Sale Price]]-Table791337[[#This Row],[Purchase Price]] -> 0
G116: =Table791337[[#This Row],[Sale Price]]-Table791337[[#This Row],[Purchase Price]] -> 0
G117: =Table791337[[#This Row],[Sale Price]]-Table791337[[#This Row],[Purchase Price]] -> 0
G118: =Table791337[[#This Row],[Sale Price]]-Table791337[[#This Row],[Purchase Price]] -> 0
G119: =Table791337[[#This Row],[Sale Price]]-Table791337[[#This Row],[Purchase Price]] -> 0
... G121: =Table791337[[#This Row],[Sale Price]]-Table791337[[#This Row],[Purchase Price]] -> 0

Sheet Tekna
B1: All Companies
B3: Tekna Pty Ltd | J3: Things to Do:
B4: ACN: | C4: 658 462 394 | D4: ABN: | E4: 43 658 462 394 | G4: TFN: | H4: 605 934 917 | J4: Need Structure Group
B5: Date Incorporated | C5: 44712 | F5: Shares on Issue | G5: 200
B6: Purpose: | F6: Is it a Trustee
B7: Trust Name
B8: Registered office | C8: 160 Alperton Road, Burbank QLD 4156 | F8: Principal place of business | G8: 160 Alperton Road, Burbank QLD 4156
D9: From
B10: Current Director | C10: Andrew Mark Clement | D10: 45225
B11: Current Secretary | C11: Andrew Mark Clement | D11: 45225
B13: Does this Company have Loans | C13: Yes | F13: Is there loan documents in place | G13: Yes
E15: Shares | F15: Beneficially Held
B16: Current Shareholdings | C16: Plug Developments Pty Ltd | E16: 35 | F16: No
C17: Prov1322 Global Pty Ltd | E17: 30 | F17: No
C18: The Promise QLD Pty Ltd | E18: 115 | F18: No
C19: Jonathan Lance Ament | E19: 10 | F19: Yes
C20: Samuel James Harder | E20: 10 | F20: No
B22: Current Bank Accounts | C22: Bank | D22: BSB | E22: Account | F22: Date Opened | G22: Date Closed
C23: NAB | D23: 084-435 | E23: 199211357 | F23: 44643
C24: Westpac | D24: 034-076 | E24: 699618 | F24: 45282
B29: Folder Storage | C29: Tekna | D29: Abbreviation | E29: Tekna
B31: Company Register | C31: Type | D31: Folder | E31: Date | F31: Manual | G31: Electronicaly Stored | H31: By Whom
B32: Application for Shares | C32: Members | D32: =VLOOKUP(C32,'Document Type'!$B$6:$C$34,2,FALSE) -> Register of Members | E32: 44712 | G32: Application for Shares Tekna
B33: Application for Shares | C33: Members | D33: =VLOOKUP(C33,'Document Type'!$B$6:$C$34,2,FALSE) -> Register of Members | E33: 44712 | G33: Application for Shares Plug Developments Tekna
B34: Application for Shares | C34: Members | D34: =VLOOKUP(C34,'Document Type'!$B$6:$C$34,2,FALSE) -> Register of Members | E34: 44712 | G34: Application for Shares Jonathan Lance Ament Tekna
B35: BAS Report April-June | C35: BAS | D35: =VLOOKUP(C35,'Document Type'!$B$6:$C$34,2,FALSE) -> BAS | E35: 45531 | G35: In BAS 2024FY Folder
B36: BAS Report Jan-March | C36: BAS | D36: =VLOOKUP(C36,'Document Type'!$B$6:$C$34,2,FALSE) -> BAS | E36: 45531 | G36: In BAS 2024FY Folder
B37: Certificate of Registration | C37: Company Setup | D37: =VLOOKUP(C37,'Document Type'!$B$6:$C$34,2,FALSE) -> Company Setup | E37: 44712 | G37: Certificate of Registration Tekna
B38: Change of Address | C38: ASIC Docs | D38: =VLOOKUP(C38,'Document Type'!$B$6:$C$34,2,FALSE) -> General | E38: 44698 | G38: Change of Address Tekna
B39: Change of Register of Members | C39: ASIC Docs | D39: =VLOOKUP(C39,'Document Type'!$B$6:$C$34,2,FALSE) -> General | E39: 44698 | G39: Change of Register of Members Tekna
B40: Company Tax Return | C40: ATO Tax Return | D40: =VLOOKUP(C40,'Document Type'!$B$6:$C$34,2,FALSE) -> General | E40: 45473 | G40: Company Tax Return FY23 Tekna
B41: Consolidated Income Tax Return FY23 Tekna | C41: Tax Consolidation | D41: =VLOOKUP(C41,'Document Type'!$B$6:$C$34,2,FALSE) -> General | E41: 45473 | G41: Consolidated Income Tax Return FY23 Tekna
B42: Constitution Docx | C42: Constitution | D42: Constitution | E42: 44712 | G42: Constituition Tekna
B43: Constitution PDF | C43: Constitution | D43: =VLOOKUP(C43,'Document Type'!$B$6:$C$34,2,FALSE) -> Constitution | E43: 44712 | G43: Constituition Tekna
B44: Corporate Key | C44: Corporate Key | D44: =VLOOKUP(C44,'Document Type'!$B$6:$C$34,2,FALSE) -> General | E44: 45100 | G44: Corporate Key Tekna
B45: EOY ASIC FY22 | C45: EOY ASIC | D45: =VLOOKUP(C45,'Document Type'!$B$6:$C$34,2,FALSE) -> General | E45: 44742 | G45: EOY ASIC FY22 Tekna
B46: EOY ASIC FY23 | C46: EOY ASIC | D46: =VLOOKUP(C46,'Document Type'!$B$6:$C$34,2,FALSE) -> General | E46: 45107 | G46: EOY ASIC FY23 Tekna
B47: EOY ASIC FY24 | C47: EOY ASIC | D47: =VLOOKUP(C47,'Document Type'!$B$6:$C$34,2,FALSE) -> General | E47: 45471 | G47: EOY ASIC FY24 Tekna | H47: Sophie Harder
B48: EOY ATO FY24 | C48: EOY ATO | D48: =VLOOKUP(C48,'Document Type'!$B$6:$C$34,2,FALSE) -> General | E48: 45471 | G48: EOY ATO FY24 Tekna | H48: Sophie Harder
B49: EOY NAB 199211357 FY22 | C49: Bank Statements | D49: =VLOOKUP(C49,'Document Type'!$B$6:$C$34,2,FALSE) -> General | E49: 45562 | G49: EOY NAB 199211357 FY22 Tekna | H49: Rachel
B50: EOY NAB 199211357 FY23 | C50: Bank Statements | D50: =VLOOKUP(C50,'Document Type'!$B$6:$C$34,2,FALSE) -> General | E50: 45562 | G50: EOY NAB 199211357 FY22 Tekna | H50: Rachel
B51: EOY NAB 199211357 FY24 | C51: Bank Statements | D51: =VLOOKUP(C51,'Document Type'!$B$6:$C$34,2,FALSE) -> General | E51: 45562 | G51: EOY NAB 199211357 FY22 Tekna | H51: Rachel
B52: EOY WBC 699618 FY24 | C52: Bank Statements | D52: =VLOOKUP(C52,'Document Type'!$B$6:$C$34,2,FALSE) -> General | E52: 45562 | G52: EOY WBC 699618 FY24 Tekna | H52: Rachel
B53: Issue News Sam and Prov1322 | C53: Members | D53: =VLOOKUP(C53,'Document Type'!$B$6:$C$34,2,FALSE) -> Register of Members | E53: 45273 | G53: In folder called "Share Structure Sam and Prov"
B54: Loan Docs Gen2612 Tekna | C54: Loan Agreement | D54: =VLOOKUP(C54,'Document Type'!$B$6:$C$34,2,FALSE) -> Loans and Security | E54: 45219 | G54: In Folder Called "Gen2612 Tekna" | H54: Sophie Harder
B55: Loan Docs Plug Investments Tekna | C55: Loan Agreement | D55: =VLOOKUP(C55,'Document Type'!$B$6:$C$34,2,FALSE) -> Loans and Security | E55: 45219 | G55: In Folder Called "Plug Investments Tekna" | H55: Sophie Harder
B56: Purchase Shares Tekna Homes | C56: Asset | D56: =VLOOKUP(C56,'Document Type'!$B$6:$C$34,2,FALSE) -> Assets | E56: 45261 | G56: In Folder Called "Issue New Shares Tekna Homes" | H56: Sophie Harder
B57: Registered Office | C57: ASIC Docs | D57: =VLOOKUP(C57,'Document Type'!$B$6:$C$34,2,FALSE) -> General | E57: 44698 | G57: Registered Office Multiplace Tekna
B58: Solvency Minutes | C58: Minutes | D58: =VLOOKUP(C58,'Document Type'!$B$6:$C$34,2,FALSE) -> Minutes | E58: 45016 | G58: Annual Solvency Minutes Tekna
B59: Consolidated Tax Return FY22 Tekna Group | C59: ATO Tax Return | D59: General | E59: 45937 | G59: Consolidated Tax Return FY22 Tekna Group
B60: Consolidated Tax Return FY23 Tekna Group | C60: ATO Tax Return | D60: General | E60: 45937 | G60: Consolidated Tax Return FY23 Tekna Group
B61: Consolidated Tax Return FY24 Tekna Group | C61: ATO Tax Return | D61: =VLOOKUP(C61,'Document Type'!$B$6:$C$34,2,FALSE) -> General | E61: 45937 | G61: Consolidated Tax Return FY24 Tekna Group
B62: Transfer Shares The Promise QLD | C62: Members | D62: =VLOOKUP(C62,'Document Type'!$B$6:$C$34,2,FALSE) -> Register of Members | E62: 45427 | G62: Share Transfer Form PFT and THFT Tekna
D63: =VLOOKUP(C63,'Document Type'!$B$6:$C$34,2,FALSE) -> #N/A
D64: =VLOOKUP(C64,'Document Type'!$B$6:$C$34,2,FALSE) -> #N/A
D65: =VLOOKUP(C65,'Document Type'!$B$6:$C$34,2,FALSE) -> #N/A
D66: =VLOOKUP(C66,'Document Type'!$B$6:$C$34,2,FALSE) -> #N/A
D67: =VLOOKUP(C67,'Document Type'!$B$6:$C$34,2,FALSE) -> #N/A
D68: =VLOOKUP(C68,'Document Type'!$B$6:$C$34,2,FALSE) -> #N/A
D69: =VLOOKUP(C69,'Document Type'!$B$6:$C$34,2,FALSE) -> #N/A
D70: =VLOOKUP(C70,'Document Type'!$B$6:$C$34,2,FALSE) -> #N/A
D71: =VLOOKUP(C71,'Document Type'!$B$6:$C$34,2,FALSE) -> #N/A
D72: =VLOOKUP(C72,'Document Type'!$B$6:$C$34,2,FALSE) -> #N/A
D73: =VLOOKUP(C73,'Document Type'!$B$6:$C$34,2,FALSE) -> #N/A
B79: Register of Members
B80: Date | C80: Issue, transfer,share split, buy back or Cancelation | D80: Class of Share | E80: Certification Number | F80: Serial Number From | G80: Serial Number To | H80: Number of Shares Aquired | I80: Trf'd to / Trf'd from | J80: Amount Paid Per Share | K80: Amount Unpaid per Share | L80: Fully Paid? (Y/N) | M80: Total Number os Shares Held | N80: Total Amount paid fo the shares | O80: Are the Shares Benedicially Held | P80: Owner / Buyer / Seller | Q80: ASIC Document Number
B81: 44712 | C81: Issue | D81: ORD | H81: 55 | J81: 1 | L81: Y | M81: 55 | N81: 55 | O81: N | P81: Harder Developments ATF Team Harder Family Trust
B82: 44712 | C82: Issue | D82: ORD | H82: 35 | J82: 1 | L82: y | M82: 35 | N82: 35 | O82: N | P82: Plug Investments ATF Plug Family Trust
B83: 44712 | C83: Issue | D83: ORD | H83: 10 | J83: 1 | L83: y | M83: 10 | N83: 10 | O83: Y | P83: Jonathan Lance Ament
B84: 45271 | C84: issue | D84: ORD | H84: 10 | J84: 1 | L84: Y | M84: 10 | N84: 10 | O84: N | P84: Sam Harder ATF Harder Family Trust
B85: 45271 | C85: issue | D85: ORD | H85: 90 | J85: 90 | L85: Y | M85: 90 | N85: 90 | O85: N | P85: Prov1322 Global ATF Team Harder Family Trust
B86: 45427 | C86: Transfer | D86: ORD | H86: 115 | I86: Prov1322 Global ATF Team Harder Family Trust | J86: 115 | L86: y | M86: 115 | N86: 115 | O86: N | P86: The Promise QLD ATF The Promise Family Trust
B108: Register of Loans
B109: From | C109: To | D109: Amount | E109: Date | F109: Security | G109: PPSR
B110: Gen2612 | C110: Tekna | D110: 2000000 | E110: 45219 | F110: Yes | G110: Yes
B111: Plug Investments | C111: Tekna | D111: 2000000 | E111: 45219 | F111: Yes | G111: Yes
B117: Register of Assets - Non Trading
B118: Item | C118: Purchase Date | D118: Purchase Price | E118: Sale Date | F118: Sale Price | G118: Profit
B119: Shares in Tekna Homes | C119: 44875 | D119: 100000 | G119: =Table791341[[#This Row],[Purchase Price]]-Table791341[[#This Row],[Sale Price]] -> 100000
B120: Shares in Tekna Homes | C120: 45261 | D120: 300000 | G120: =Table791341[[#This Row],[Purchase Price]]-Table791341[[#This Row],[Sale Price]] -> 300000
G121: =Table791341[[#This Row],[Purchase Price]]-Table791341[[#This Row],[Sale Price]] -> 0
G122: =Table791341[[#This Row],[Purchase Price]]-Table791341[[#This Row],[Sale Price]] -> 0
G123: =Table791341[[#This Row],[Purchase Price]]-Table791341[[#This Row],[Sale Price]] -> 0
G124: =Table791341[[#This Row],[Purchase Price]]-Table791341[[#This Row],[Sale Price]] -> 0
G125: =Table791341[[#This Row],[Purchase Price]]-Table791341[[#This Row],[Sale Price]] -> 0
G126: =Table791341[[#This Row],[Purchase Price]]-Table791341[[#This Row],[Sale Price]] -> 0
G127: =Table791341[[#This Row],[Purchase Price]]-Table791341[[#This Row],[Sale Price]] -> 0
G128: =Table791341[[#This Row],[Purchase Price]]-Table791341[[#This Row],[Sale Price]] -> 0
G129: =Table791341[[#This Row],[Purchase Price]]-Table791341[[#This Row],[Sale Price]] -> 0
G130: =Table791341[[#This Row],[Purchase Price]]-Table791341[[#This Row],[Sale Price]] -> 0
G131: =Table791341[[#This Row],[Purchase Price]]-Table791341[[#This Row],[Sale Price]] -> 0
G132: =Table791341[[#This Row],[Purchase Price]]-Table791341[[#This Row],[Sale Price]] -> 0
... G136: =Table791341[[#This Row],[Purchase Price]]-Table791341[[#This Row],[Sale Price]] -> 0

Sheet The Promise Family Trust
B1: All Companies
J2: Loan Agreement | K2: Things that must be filed | L2: 2024
B3: The Promise Family Trust | J3: Security Deed | K3: If is a discresionary trust , need to make the trust distribution every year before 30th June
B4: ACN: | D4: ABN: | G4: TFN: | J4: Company Setup | K4: All Bank Statement for the year
B5: Date Incorporated | C5: 45415 | F5: Shares on Issue | J5: Solvency ASIC | K5: all assets purchases receipts
B6: Purpose: | C6: To Act as a Trust for The Promise Queensland Pty Ltd | F6: Is it a Trustee | J6: Constitution | K6: all sales of assets
B7: Trust Name | J7: Members | K7: all distribution if company
B8: Registered office | C8: 162 Alperton Road, Burbank QLD 4156 | F8: Principal place of business | G8: 162 Alperton Road, Burbank QLD 4156 | J8: Structure | K8: all company minutes
D9: From | J9: ATO Tax Return | K9: ASIC showing company info on 30th june
B10: Current Director | C10: Sophie Mee-Jeong Harder | D10: 45415 | J10: Asset | K10: All ASIC Documents
B11: Current Secretary | C11: Sophie Mee-Jeong Harder | D11: 45415 | J11: Dividends | K11: Company Tax Return
J12: EOY ATO | K12: Company ATO due
B13: Does this Company have Loans | C13: No | F13: Is there loan documents in place | G13: No | J13: Registered Office
E14: Shares | F14: Beneficially Held | G14: Yes | J14: Officers
B15: Current Shareholdings | J15: Bank Statements
J16: Minutes
B17: Current Bank Accounts | C17: Bank | D17: BSB | E17: Account | F17: Date Opened | J17: Distribution
J18: EOY ASIC
J19: PPSR
J20: Tax Consolidation
J21: Trust Deed
B24: Folder Storage | C24: The Promise Family Trust | D24: Abbreviation | E24: TPFT
B26: Company Register | C26: Type | D26: Folder | E26: Date | F26: Manual | G26: Electronicaly Stored | H26: By Whom | J26: Things to Do
B27: Trust Deed | C27: Trust Deed | D27: =VLOOKUP(C27,'Document Type'!$B$6:$C$34,2,FALSE) -> Trust Deed | E27: 45415 | G27: Trust Deed TPFT | H27: Sophie Harder
B28: Share Tranfer Form Tekna - TPFT | C28: Asset | D28: =VLOOKUP(C28,'Document Type'!$B$6:$C$34,2,FALSE) -> Assets | E28: 45427 | G28: Share Transfer Form TPFT | H28: Sophie Harder
D29: =VLOOKUP(C29,'Document Type'!$B$6:$C$34,2,FALSE) -> #N/A
D30: =VLOOKUP(C30,'Document Type'!$B$6:$C$34,2,FALSE) -> #N/A
D31: =VLOOKUP(C31,'Document Type'!$B$6:$C$34,2,FALSE) -> #N/A
D32: =VLOOKUP(C32,'Document Type'!$B$6:$C$34,2,FALSE) -> #N/A
D33: =VLOOKUP(C33,'Document Type'!$B$6:$C$34,2,FALSE) -> #N/A
D34: =VLOOKUP(C34,'Document Type'!$B$6:$C$34,2,FALSE) -> #N/A
D35: =VLOOKUP(C35,'Document Type'!$B$6:$C$34,2,FALSE) -> #N/A
D36: =VLOOKUP(C36,'Document Type'!$B$6:$C$34,2,FALSE) -> #N/A
D37: =VLOOKUP(C37,'Document Type'!$B$6:$C$34,2,FALSE) -> #N/A
D38: =VLOOKUP(C38,'Document Type'!$B$6:$C$34,2,FALSE) -> #N/A
D39: =VLOOKUP(C39,'Document Type'!$B$6:$C$34,2,FALSE) -> #N/A
D40: =VLOOKUP(C40,'Document Type'!$B$6:$C$34,2,FALSE) -> #N/A
... D61: =VLOOKUP(C61,'Document Type'!$B$6:$C$34,2,FALSE) -> #N/A
B63: Register of Members
B64: Date | C64: Issue, transfer,share split, buy back or Cancelation | D64: Class of Share | E64: Certification Number | F64: Serial Number From | G64: Serial Number To | H64: Number of Shares Aquired | I64: Trf'd to / Trf'd from | J64: Amount Paid Per Share | K64: Amount Unpaid per Share | L64: Fully Paid? (Y/N) | M64: Total Number os Shares Held | N64: Total Amount paid fo the shares | O64: Are the Shares Benedicially Held | P64: Owner / Buyer / Seller | Q64: ASIC Document Number
B92: Register of Loans
B93: From | C93: To | D93: Amount | E93: Date | F93: Security | G93: PPSR
B101: Register of Assets - Non Trading
B102: Item | C102: Purchase Date | D102: Purchase Price | E102: Sale Date | F102: Sale Price | G102: Profit
G103: =Table791345[[#This Row],[Purchase Price]]-Table791345[[#This Row],[Sale Price]] -> 0
G104: =Table791345[[#This Row],[Purchase Price]]-Table791345[[#This Row],[Sale Price]] -> 0
G105: =Table791345[[#This Row],[Purchase Price]]-Table791345[[#This Row],[Sale Price]] -> 0
G106: =Table791345[[#This Row],[Purchase Price]]-Table791345[[#This Row],[Sale Price]] -> 0
G107: =Table791345[[#This Row],[Purchase Price]]-Table791345[[#This Row],[Sale Price]] -> 0
G108: =Table791345[[#This Row],[Purchase Price]]-Table791345[[#This Row],[Sale Price]] -> 0
G109: =Table791345[[#This Row],[Purchase Price]]-Table791345[[#This Row],[Sale Price]] -> 0
G110: =Table791345[[#This Row],[Purchase Price]]-Table791345[[#This Row],[Sale Price]] -> 0
G111: =Table791345[[#This Row],[Purchase Price]]-Table791345[[#This Row],[Sale Price]] -> 0
G112: =Table791345[[#This Row],[Purchase Price]]-Table791345[[#This Row],[Sale Price]] -> 0
G113: =Table791345[[#This Row],[Purchase Price]]-Table791345[[#This Row],[Sale Price]] -> 0
G114: =Table791345[[#This Row],[Purchase Price]]-Table791345[[#This Row],[Sale Price]] -> 0
... G120: =Table791345[[#This Row],[Purchase Price]]-Table791345[[#This Row],[Sale Price]] -> 0

Sheet The Promise QLD PTY LTD
B1: All Companies
J2: Loan Agreement | K2: Things that must be filed | L2: 2024
B3: The Promise QLD Pty Ltd | J3: Security Deed | K3: If is a discresionary trust , need to make the trust distribution every year before 30th June
B4: ACN: | C4: 677065137 | D4: ABN: | G4: TFN: | J4: Company Setup | K4: All Bank Statement for the year
B5: Date Incorporated | C5: 45415 | F5: Shares on Issue | G5: 100 | J5: Solvency ASIC | K5: all assets purchases receipts
B6: Purpose: | C6: To Act as a trustee for the Promise Family Tust | F6: Is it a Trustee | G6: Yes | J6: Constitution | K6: all sales of assets
B7: Trust Name / Trustee | C7: The Promise Family Trust | J7: Members | K7: all distribution if company
B8: Registered office | C8: 162 Alperton Road, Burbank QLD 4156 | F8: Principal place of business | G8: 162 Alperton Road, Burbank QLD 4156 | J8: Structure | K8: all company minutes
D9: From | J9: ATO Tax Return | K9: ASIC showing company info on 30th june
B10: Current Director | C10: Sophie Mee-Jeong Harder | D10: 45415 | J10: Asset | K10: All ASIC Documents
B11: Current Secretary | C11: Sophie Mee-Jeong Harder | D11: 45415 | J11: Dividends | K11: Company Tax Return
J12: EOY ATO | K12: Company ATO due
B13: Does this Company have Loans | C13: No | F13: Is there loan documents in place | G13: No | J13: Registered Office
E14: Shares | F14: Beneficially Held | J14: Officers
B15: Current Shareholdings | C15: Sophie Mee-Jeong Harder | D15: 100 | E15: 100 | F15: Yes | J15: Bank Statements
J16: Minutes
B17: Current Bank Accounts | C17: Bank | D17: BSB | E17: Account | F17: Date Opened | J17: Distribution
D18: 034-069 | E18: 698 668 | J18: EOY ASIC
J19: PPSR
J20: Tax Consolidation
J21: Trust Deed
B24: Folder Storage | C24: The Promise QLD | D24: Abbreviation | E24: TPQ
B26: Company Register | C26: Type | D26: Folder | E26: Date | F26: Manual | G26: Electronicaly Stored | H26: By Whom
B27: Set Up Company Legal Vision | C27: Company Setup | D27: =VLOOKUP(C27,'Document Type'!$B$6:$C$34,2,FALSE) -> Company Setup | E27: 45415 | G27: Company Set Up TPQ | H27: Sophie Harder
B28: Register of Members On Set up | C28: Members | D28: =VLOOKUP(C28,'Document Type'!$B$6:$C$34,2,FALSE) -> Register of Members | E28: 45415 | G28: Members 03052024 TPQ | H28: Sophie Harder
B29: Constitution | C29: Constitution | D29: =VLOOKUP(C29,'Document Type'!$B$6:$C$34,2,FALSE) -> Constitution | E29: 45415 | G29: Constituition TPQ | H29: Sophie Harder
B30: Share Certificate | C30: Members | D30: =VLOOKUP(C30,'Document Type'!$B$6:$C$34,2,FALSE) -> Register of Members | E30: 45415 | G30: Share Certificate TPQ | H30: Sophie Harder
B31: EOY ASIC FY24 | C31: EOY ASIC | D31: =VLOOKUP(C31,'Document Type'!$B$6:$C$34,2,FALSE) -> General | E31: 45471 | G31: EOY ASIC FY24 TPQ | H31: Sophie Harder
B32: Bank Statement | C32: Bank Statements | D32: =VLOOKUP(C32,'Document Type'!$B$6:$C$34,2,FALSE) -> General | E32: 45884 | G32: 1. WBC 698668 FY25 TPQ - 14.01.25 - 14.02.25 | H32: Sophie Harder
B33: Bank Statement | C33: Bank Statements | D33: =VLOOKUP(C33,'Document Type'!$B$6:$C$34,2,FALSE) -> General | E33: 45884 | G33: 2. WBC 698668 FY25 TPQ - 14.02.25 - 14.05.25 | H33: Sophie Harder
B34: Bank Statement | C34: Bank Statements | D34: =VLOOKUP(C34,'Document Type'!$B$6:$C$34,2,FALSE) -> General | E34: 45884 | G34: 3. WBC 698668 FY25 TPQ - 14.05.25 - 13.06.25 | H34: Sophie Harder
B35: Bank Statement | C35: Bank Statements | D35: =VLOOKUP(C35,'Document Type'!$B$6:$C$34,2,FALSE) -> General | E35: 45884 | G35: 4. WBC 698668 FY25 TPQ - 13.06.25 - 14.07.25 | H35: Sophie Harder
B36: Bank Statement | C36: Bank Statements | D36: =VLOOKUP(C36,'Document Type'!$B$6:$C$34,2,FALSE) -> General | E36: 45884 | G36: 1. WBC 698668 FY26 TPQ - 13.06.25 - 14.07.25 | H36: Sophie Harder
D37: =VLOOKUP(C37,'Document Type'!$B$6:$C$34,2,FALSE) -> #N/A
D38: =VLOOKUP(C38,'Document Type'!$B$6:$C$34,2,FALSE) -> #N/A
D39: =VLOOKUP(C39,'Document Type'!$B$6:$C$34,2,FALSE) -> #N/A
D40: =VLOOKUP(C40,'Document Type'!$B$6:$C$34,2,FALSE) -> #N/A
D41: =VLOOKUP(C41,'Document Type'!$B$6:$C$34,2,FALSE) -> #N/A
D42: =VLOOKUP(C42,'Document Type'!$B$6:$C$34,2,FALSE) -> #N/A
D43: =VLOOKUP(C43,'Document Type'!$B$6:$C$34,2,FALSE) -> #N/A
D44: =VLOOKUP(C44,'Document Type'!$B$6:$C$34,2,FALSE) -> #N/A
D45: =VLOOKUP(C45,'Document Type'!$B$6:$C$34,2,FALSE) -> #N/A
D46: =VLOOKUP(C46,'Document Type'!$B$6:$C$34,2,FALSE) -> #N/A
D47: =VLOOKUP(C47,'Document Type'!$B$6:$C$34,2,FALSE) -> #N/A
D48: =VLOOKUP(C48,'Document Type'!$B$6:$C$34,2,FALSE) -> #N/A
... D61: =VLOOKUP(C61,'Document Type'!$B$6:$C$34,2,FALSE) -> #N/A
B64: Register of Members
B65: Date | C65: Issue, transfer,share split, buy back or Cancelation | D65: Class of Share | E65: Certification Number | F65: Serial Number From | G65: Serial Number To | H65: Number of Shares Aquired | I65: Trf'd to / Trf'd from | J65: Amount Paid Per Share | K65: Amount Unpaid per Share | L65: Fully Paid? (Y/N) | M65: Total Number os Shares Held | N65: Total Amount paid fo the shares | O65: Are the Shares Benedicially Held | P65: Owner / Buyer / Seller | Q65: ASIC Document Number
B93: Register of Loans
B94: From | C94: To | D94: Amount | E94: Date | F94: Security | G94: PPSR
B102: Register of Assets - Non Trading
B103: Item | C103: Purchase Date | D103: Purchase Price | E103: Sale Date | F103: Sale Price | G103: Profit
G104: =Table791350[[#This Row],[Purchase Price]]-Table791350[[#This Row],[Sale Price]] -> 0
G105: =Table791350[[#This Row],[Purchase Price]]-Table791350[[#This Row],[Sale Price]] -> 0
G106: =Table791350[[#This Row],[Purchase Price]]-Table791350[[#This Row],[Sale Price]] -> 0
G107: =Table791350[[#This Row],[Purchase Price]]-Table791350[[#This Row],[Sale Price]] -> 0
G108: =Table791350[[#This Row],[Purchase Price]]-Table791350[[#This Row],[Sale Price]] -> 0
G109: =Table791350[[#This Row],[Purchase Price]]-Table791350[[#This Row],[Sale Price]] -> 0
G110: =Table791350[[#This Row],[Purchase Price]]-Table791350[[#This Row],[Sale Price]] -> 0
G111: =Table791350[[#This Row],[Purchase Price]]-Table791350[[#This Row],[Sale Price]] -> 0
G112: =Table791350[[#This Row],[Purchase Price]]-Table791350[[#This Row],[Sale Price]] -> 0
G113: =Table791350[[#This Row],[Purchase Price]]-Table791350[[#This Row],[Sale Price]] -> 0
G114: =Table791350[[#This Row],[Purchase Price]]-Table791350[[#This Row],[Sale Price]] -> 0
G115: =Table791350[[#This Row],[Purchase Price]]-Table791350[[#This Row],[Sale Price]] -> 0
... G121: =Table791350[[#This Row],[Purchase Price]]-Table791350[[#This Row],[Sale Price]] -> 0

Sheet Template
B1: All Companies
J2: Loan Agreement | K2: Things that must be filed | L2: 2024
B3: The Promise QLD Pty Ltd | J3: Security Deed | K3: If is a discresionary trust , need to make the trust distribution every year before 30th June
B4: ACN: | D4: ABN: | G4: TFN: | J4: Company Setup | K4: All Bank Statement for the year
B5: Date Incorporated | F5: Shares on Issue | J5: Solvency ASIC | K5: all assets purchases receipts
B6: Purpose: | F6: Is it a Trustee | J6: Constitution | K6: all sales of assets
B7: Trust Name / Trustee | J7: Members | K7: all distribution if company
B8: Registered office | F8: Principal place of business | J8: Structure | K8: all company minutes
D9: From | J9: ATO Tax Return | K9: ASIC showing company info on 30th june
B10: Current Director | J10: Asset | K10: All ASIC Documents
B11: Current Secretary | J11: Dividends | K11: Company Tax Return
J12: EOY ATO | K12: Company ATO due
B13: Does this Company have Loans | C13: No | F13: Is there loan documents in place | G13: No | J13: Registered Office
E14: Shares | F14: Beneficially Held | J14: Officers
B15: Current Shareholdings | J15: Bank Statements
J16: Minutes
B17: Current Bank Accounts | C17: Bank | D17: BSB | E17: Account | F17: Date Opened | J17: Distribution
J18: EOY ASIC
J19: PPSR
J20: Tax Consolidation
J21: Trust Deed
B24: Folder Storage | C24: The Promise QLD | D24: Abbreviation | E24: TPQ
B26: Company Register | C26: Type | D26: Folder | E26: Date | F26: Manual | G26: Electronicaly Stored | H26: By Whom
D27: =VLOOKUP(C27,'Document Type'!$B$6:$C$34,2,FALSE) -> #N/A
D28: =VLOOKUP(C28,'Document Type'!$B$6:$C$34,2,FALSE) -> #N/A
D29: =VLOOKUP(C29,'Document Type'!$B$6:$C$34,2,FALSE) -> #N/A
D30: =VLOOKUP(C30,'Document Type'!$B$6:$C$34,2,FALSE) -> #N/A
D31: =VLOOKUP(C31,'Document Type'!$B$6:$C$34,2,FALSE) -> #N/A
D32: =VLOOKUP(C32,'Document Type'!$B$6:$C$34,2,FALSE) -> #N/A
D33: =VLOOKUP(C33,'Document Type'!$B$6:$C$34,2,FALSE) -> #N/A
D34: =VLOOKUP(C34,'Document Type'!$B$6:$C$34,2,FALSE) -> #N/A
D35: =VLOOKUP(C35,'Document Type'!$B$6:$C$34,2,FALSE) -> #N/A
D36: =VLOOKUP(C36,'Document Type'!$B$6:$C$34,2,FALSE) -> #N/A
D37: =VLOOKUP(C37,'Document Type'!$B$6:$C$34,2,FALSE) -> #N/A
D38: =VLOOKUP(C38,'Document Type'!$B$6:$C$34,2,FALSE) -> #N/A
... D61: =VLOOKUP(C61,'Document Type'!$B$6:$C$34,2,FALSE) -> #N/A
B63: Register of Members
B64: Date | C64: Issue, transfer,share split, buy back or Cancelation | D64: Class of Share | E64: Certification Number | F64: Serial Number From | G64: Serial Number To | H64: Number of Shares Aquired | I64: Trf'd to / Trf'd from | J64: Amount Paid Per Share | K64: Amount Unpaid per Share | L64: Fully Paid? (Y/N) | M64: Total Number os Shares Held | N64: Total Amount paid fo the shares | O64: Are the Shares Benedicially Held | P64: Owner / Buyer / Seller | Q64: ASIC Document Number
B92: Register of Loans
B93: From | C93: To | D93: Amount | E93: Date | F93: Security | G93: PPSR
B101: Register of Assets - Non Trading
B102: Item | C102: Purchase Date | D102: Purchase Price | E102: Sale Date | F102: Sale Price | G102: Depreciation | H102: Profit
H103: =Table7913[[#This Row],[Sale Price]]-Table7913[[#This Row],[Purchase Price]]+Table7913[[#This Row],[Depreciation]] -> 0
H104: =Table7913[[#This Row],[Sale Price]]-Table7913[[#This Row],[Purchase Price]]+Table7913[[#This Row],[Depreciation]] -> 0
H105: =Table7913[[#This Row],[Sale Price]]-Table7913[[#This Row],[Purchase Price]]+Table7913[[#This Row],[Depreciation]] -> 0
H106: =Table7913[[#This Row],[Sale Price]]-Table7913[[#This Row],[Purchase Price]]+Table7913[[#This Row],[Depreciation]] -> 0
H107: =Table7913[[#This Row],[Sale Price]]-Table7913[[#This Row],[Purchase Price]]+Table7913[[#This Row],[Depreciation]] -> 0
H108: =Table7913[[#This Row],[Sale Price]]-Table7913[[#This Row],[Purchase Price]]+Table7913[[#This Row],[Depreciation]] -> 0
H109: =Table7913[[#This Row],[Sale Price]]-Table7913[[#This Row],[Purchase Price]]+Table7913[[#This Row],[Depreciation]] -> 0
H110: =Table7913[[#This Row],[Sale Price]]-Table7913[[#This Row],[Purchase Price]]+Table7913[[#This Row],[Depreciation]] -> 0
H111: =Table7913[[#This Row],[Sale Price]]-Table7913[[#This Row],[Purchase Price]]+Table7913[[#This Row],[Depreciation]] -> 0
H112: =Table7913[[#This Row],[Sale Price]]-Table7913[[#This Row],[Purchase Price]]+Table7913[[#This Row],[Depreciation]] -> 0
H113: =Table7913[[#This Row],[Sale Price]]-Table7913[[#This Row],[Purchase Price]]+Table7913[[#This Row],[Depreciation]] -> 0
H114: =Table7913[[#This Row],[Sale Price]]-Table7913[[#This Row],[Purchase Price]]+Table7913[[#This Row],[Depreciation]] -> 0
... H120: =Table7913[[#This Row],[Sale Price]]-Table7913[[#This Row],[Purchase Price]]+Table7913[[#This Row],[Depreciation]] -> 0

Sheet All Companies
A1: Group | B1: Company | C1: Review Date | D1: ACN | E1: abn | F1: TFN | G1: Director | H1: Established Date | I1: Corporate Key | J1: User Name | K1: Password | L1: Recovery Question | M1: Answer
A2: Tekna | B2: Tekna | C2: 45382 | D2: =Tekna!C4 -> 658 462 394 | E2: =Tekna!E4 -> 43 658 462 394 | F2: =Tekna!H4 -> 605 934 917 | G2: =Tekna!C10 -> Andrew Mark Clement | H2: =Tekna!C5 -> 44712 | I2: 94512428 | J2: andrew@tekna.com.au | K2: J4sper20!0 | L2: What City was I Born In? | M2: Glenelg
A3: Tekna | B3: Tekna Drafting (formerly Rock Invest Qld) | C3: 45492 | D3: ='Tekna Drafting'!C4 -> 159 565 849 | E3: ='Tekna Drafting'!E4 -> 96 159 565 849 | F3: ='Tekna Drafting'!H4 -> 938 078 821 | G3: ='Tekna Drafting'!C10 -> Andrew Mark Clement | H3: ='Tekna Drafting'!C5 -> 41109 | I3: 10135027 | J3: rach@100xbestlife.com | K3: J4sper20!0 | L3: What City was I Born In? | M3: Glenelg
A4: Tekna | B4: Tekna Homes formerly Tekna Licence | C4: 45382 | D4: ='Tekna Homes'!B4 -> 658 462 732 | E4: ='Tekna Homes'!D4 -> 34 658 462 732 | F4: ='Tekna Homes'!G4 -> 605 934 180 | G4: ='Tekna Homes'!B10 -> Andrew Mark Clement | H4: ='Tekna Homes'!B5 -> 44651 | I4: 56845790 | J4: rachel@tekna.com.au | K4: J4sper20!0 | L4: What City was I Born In? | M4: Glenelg
A5: Tekna | B5: Tekna Admin Pty LTd | C5: 45630 | D5: ='Tekna Admin'!C4 -> 673 388 424 | E5: ='Tekna Admin'!E4 -> 81 673 388 424 | F5: ='Tekna Admin'!H4 -> 518 585 770 | G5: ='Tekna Admin'!C10 -> Andrew Mark Clement | H5: ='Tekna Admin'!C5 -> 45264 | I5: 42468380 | J5: andrew@tekna.com.au | K5: J4sper20!0 | L5: What City was I Born In? | M5: Glenelg
A6: Team Harder Super Fund GROUP | B6: Team Harder | C6: 45222 | D6: ='Team Harder'!B4 -> 645 359 495 | G6: ='Team Harder'!B10 -> Rachel Anne Harder | H6: ='Team Harder'!B5 -> 44127 | I6: 16724280 | J6: rach@100xbestlife.com | K6: J4sper20!0 | L6: What City was I Born In? | M6: Glenelg
A7: Team Harder Super Fund GROUP | B7: Team Harder ATF Team Harder Super Fund | E7: ='Team Harder Super Fund'!D4 -> 17 209 120 631 | F7: ='Team Harder Super Fund'!G4 -> 534 254 470
A8: Team Harder | B8: Gen2612 | C8: 45016 | D8: ='Gen2612'!B4 -> 658 463 659 | E8: ='Gen2612'!D4 -> 47 658 463 659 | F8: ='Gen2612'!G4 -> 605 934 566 | G8: ='Gen2612'!B10 -> Rachel Anne Harder | H8: ='Gen2612'!B5 -> 44651 | I8: 8860820 | J8: rach@100xbestlife.com | K8: J4sper20!0 | L8: What City was I Born In? | M8: Glenelg
A9: Team Harder | B9: Prov1322 Global | C9: 45081 | D9: =Prov1322!B4 -> 658 602 478 | E9: =Prov1322!D4 -> 34 658 602 478 | F9: =Prov1322!G4 -> 606 189 260 | G9: =Prov1322!B10 -> Rachel Anne Harder | H9: =Prov1322!B5 -> 44657 | I9: 32350239 | J9: rach@100xbestlife.com | K9: J4sper20!0 | L9: What City was I Born In? | M9: Glenelg
A10: Team Harder | B10: Prov1322 Global ATF Team Harder Family Trust | E10: ='Team Harder Family Trust'!E4 -> 94 633 472 433 | F10: ='Team Harder Family Trust'!H4 -> 605 725 602
A11: Team Harder | B11: Team Harder Super Investments | C11: 45027 | D11: =THSI!C4 -> 658 706 597 | E11: =THSI!E4 -> 32 658 706 597 | F11: =THSI!H4 -> 608 117 219 | G11: =THSI!C10 -> Rachel Anne Harder | H11: =THSI!C5 -> 44662 | I11: 24400857 | J11: rach@100xbestlife.com | K11: J4sper20!0 | L11: What City was I Born In? | M11: Glenelg
A12: Team Harder | B12: W2G Assets | C12: 45055 | D12: =W2G!C4 -> 092 659 688 | E12: =W2G!E4 -> 59 092 659 688 | F12: =W2G!H4 -> 726 881 624 | G12: =W2G!C10 -> Rachel Anne Harder | H12: =W2G!C5 -> 36655 | I12: 87081049 | J12: w2gasset | K12: J4sper20!0 | L12: What City was I Born In? | M12: Adelaide
A13: Promise | B13: The Promise QLD Pty Ltd | C13: 45780 | D13: ='The Promise QLD PTY LTD'!C4 -> 677065137 | E13: ='The Promise QLD PTY LTD'!E4 -> 0 | F13: ='The Promise QLD PTY LTD'!H4 -> 0 | G13: ='The Promise QLD PTY LTD'!C10 -> Sophie Mee-Jeong Harder | H13: ='The Promise QLD PTY LTD'!C5 -> 45415 | I13: 27845006 | J13: rachel@tekna.com.au | K13: J4sper20!0 | L13: What City was I Born In? | M13: Glenelg
A14: Promise | B14: The Promise Family Trust | C14: 45780
A15: Personal | B15: Robert Harder | E15: 93 373 928 858 | F15: 173 955 316
A16: Personal | B16: Rachel Harder | F16: 171 927 425
A17: Personal | B17: Jared Harder | F17: 965 171 018
A18: Personal | B18: Grace Harder | F18: 633 256 177
A19: Personal | B19: Sophie Mee-Jeong Harder | F19: 633 256 457
A22: Co Invest Group | B22: Co Invest Capital Pty Ltd | C22: 24.09.2026 | D22: 691 268 452 | G22: Rachel Anne Harder | H22: 45924 | J22: rachel@tekna.com.au | K22: co1nvestwithTekna | L22: Who is the director of Tekna | M22: Andrew Clement | N22: application reference for credit licence is 220670993
B23: Co Invest Homes Pty Ltd | D23: 691 269 333
B25: Personal
B27: Co Invest Homes Pty Ltd sign up for ABN - reference 3617043026807 | C27: expiry date for application is 22.11.2025
C28: password for application is co1nvestwithTekna

Sheet Document Type
B2: Document Type | C2: Folder | F2: Description
B6: Loan Agreement | C6: Loans and Security | F6: Loan Docs
B7: Security Deed | C7: Loans and Security | F7: Securty Deed
B8: Company Setup | C8: Company Setup | F8: Set UP Docs
B9: Solvency ASIC | C9: General | F9: Annual ASIC Bill and Solvency Letter
B10: Constitution | C10: Constitution | F10: Constitution
B11: Members | C11: Register of Members | F11: Shareholdings
B12: Structure | C12: Structure | F12: Structure Chart
B13: ATO Tax Return | C13: General | F13: Once it Signed
B14: Asset | C14: Assets | F14: Anything we purchase over $300-00
B15: Dividends | C15: General | F15: Dividend statement
B16: EOY ATO | C16: General | F16: income tax , activity staement
... B18: ATO Docs | C18: General | F18: all ato DOCS OTHER
B19: ASIC Key | C19: General
B20: Officers | C20: General | F20: if change directors or secretary
B21: Bank Statements | C21: General | F21: all statements for the year
B22: BAS | C22: BAS | F22: BAS Reports
B23: Return of Gift Deed | C23: Loans and Security
B24: Minutes | C24: Minutes | F24: All minutes
B25: Distribution Minutes | C25: Minutes | F25: Distribution Minutes FY
B26: Distribution | C26: General | F26: trust document
B27: EOY ASIC | C27: General | F27: company detials and amunt overdue
B28: Corporate Key | C28: General
B29: PPSR | C29: Loans and Security | F29: PPSR
B30: Tax Consolidation | C30: General
B31: SMSF Deed | C31: Trust Deed
B32: EOFY Financials | C32: General | F32: EOFY Financial Documents
B34: Trust Deed | C34: Trust Deed | F34: trust deed
B38: Yes
B39: No
B42: Yes
B45: MAGNUS BUSINESS ADVISERS AND ACCOUNTANTS, UNIT 10 , 39 OLD CLEVELAND ROAD , CAPALABA QLD 4157
B46: 162 Alperton Road, Burbank QLD 4156
B47: 160 Alperton Road, Burbank QLD 4156
B49: Andrew Mark Clement
B50: Sophie Mee-Jeong Harder
B51: Rachel Anne Harder

Sheet Sheet3
B3: Client | C3: ??? | D3: create
B4: Internal | C4: ??? | D4: robert harder
B5: Referall | C5: ???
B6: External | C6: ???
B7: Job Address | C7: ??? | L7: gift return deed | M7: diviidends
B8: Job Type | C8: ??? | L8: ppsr under loans | M8: loan
B9: Job Status | C9: ??? | L9: ASIC Form 484 - Director Changes | M9: ASIC
B10: Job Estimate | C10: ??? | L10: ASIC Form 484 - Registered Office | M10: ASIC
L11: Distribution | M11: only diviidneds
A16: 1 | B16: ASIC
A17: 2 | B17: Assets
A18: 3 | B18: ATO
A19: 4 | B19: bank
A20: 5 | B20: Dividends
A21: 6 | B21: general | C21: trust and structure
A22: 7 | B22: loans | L22: T | M22: T - Tekna
A23: 8 | B23: minutes | L23: TA | M23: TA - Tekna Admin Pty LTd
A24: 9 | B24: financials | C24: thisi snew this is draft and actual financials from accountant ready to lodge the ato returns | L24: TD | M24: TD - Tekna Drafting (formerly Rock Invest
M25: Qld)
L26: TH | M26: TH - Tekna Homes formerly Tekna Licence
L27: GEN | M27: GEN - Gen2612
L28: Prov | M28: PROV - Prov1322 Global
L29: THFT | M29: PROV-THFT - Prov1322 Global ATF Team Harder
M30: Family Trust
L31: rjh | M31: ROB - Robert Harder
L32: rah | M32: RAH - Rachel Harder
L33: CIC | M33: CIC - Co Invest Capital Pty Ltd
L34: CIH | M34: CIH - Co Invest Homes Pty Ltd
L35: THAR | M35: THFT - Team Harder
L36: THSF | M36: THSF - Team Harder ATF Team Harder Super
M37: Fund
L38: THSI | M38: THSI - Team Harder Super Investments
L39: TPFT | M39: PROM - The Promise Family Trust
L40: TPQ | M40: PROM-QLD - The Promise QLD Pty Ltd
L41: w2g | M41: W2G - W2G Assets
L42: JH | M42: JH - Jared Harder
L43: GH | M43: GH - Grace Harder
L44: SH | M44: SH - Sophie Mee-Jeong Harder
M46: 3. Asset Abbreviations Populated (4 assets)
L48: NEV | M48: NEV - Commercial Building Unit 5/8
M49: Nevilles Street
L50: SEL-KHY | M50: SEL-KHY - Shared Equity Loan Khyiroya
L51: SEL-MAN | M51: SEL-MAN - Shared Equity Loan Mansfield
L52: SH-TH | M52: SHARES-TH - Shares in Tekna Homes

Sheet Bank Accounts 
A1: Group | B1: Entity | C1: Institution | D1: BSB | E1: Account Number | F1: Acc Open | G1: Acc Close
A3: Team Harder Group | B3: Gen 2612 | C3: NAB | D3: 084-435 | E3: 767243550 | F3: 07.04.2022
B4: Gen 2612 | C4: WPac | D4: 034-076 | E4: 709783 | F4: 45415
B6: Team Harder Family Trust | C6: NAB | D6: 84435 | E6: 959276787 | F6: 22.07.2021
B7: Team Harder Family Trust | C7: NAB Trade | D7: 83052 | E7: 305383521
B8: Prov 1322 Global Pty Ltd ATF Team Harder Family Trust | C8: WPac | D8: 034-076 | E8: 699669 | F8: 22/12/2023
C9: WPac Trade | E9: 6864378 | F9: 23/05/2024
A11: Team Harder Super Fund Group | B11: Team Harder Super Fund | C11: NAB Trade | D11: 083-052 | E11: 304656703 | F11: 43872
A15: Team Harder Super Investment Group | B15: Team Harder Super Investments | C15: NAB Trade | D15: 083-052 | E15: 305422840
B16: Team Harder Super Investments | C16: NAB | D16: 084-435 | E16: 259449309 | F16: 20.04.2022
B17: W2G Assets | C17: NAB | D17: 084-435 | E17: 513642009 | F17: 26.07.2022
B18: W2G Assets | C18: NAB Trade | D18: 083-052 | E18: 304658188
B19: W2G Assets | C19: BOQ | D19: 124034 | E19: 21446327 | G19: 28/12/2023
B20: W2G Assets Loan | C20: BOQ | D20: 124034 | E20: 23084038 | F20: 22.07.2020 | G20: 45268
A22: Tekna Group | B22: Tekna Pty Ltd | C22: NAB | D22: 84435 | E22: 199211357 | F22: 23.03.2022
C23: WPac | D23: 034-076 | E23: 699618 | F23: 22/12/2023
B24: Tekna Drafting | C24: NAB | D24: 84435 | E24: 922875532 | F24: 12.04.2022
C25: WPac | D25: 034-076 | E25: 699626 | F25: 22/12/2023
B26: Tekna Homes (formerly Tekna Licence) | C26: NAB | D26: 84435 | E26: 302971208 | F26: 16.05.2022
C27: WPac | D27: 034-076 | E27: 702733 | F27: 45566
B28: Tekna Admin | C28: NAB | D28: 083-004 | E28: 268693995 | F28: 15/12/2023
C29: WPac | D29: 034-076 | E29: 699642 | F29: 22/12/2023
A31: Homes of Hope | B31: Homes of Hope | C31: BOQ | D31: 124034 | E31: 23084038
B32: Livin the Dream | C32: BOQ | D32: 124034 | E32: 23078385

Sheet XERO Account Numbers
A1: XERO Company | B1: Account Number | C1: Name | D1: Asset Type
B2: 101 | C2: Bank | D2: Bank
B3: 102 | C3: Bank | D3: Bank
B4: 103 | C4: Bank | D4: Bank
B5: 104 | C5: Bank | D5: Bank
B6: 105 | C6: Bank | D6: Bank
B7: 106 | C7: Bank | D7: Bank
B8: 107 | C8: Bank | D8: Bank
B9: 108 | C9: Bank | D9: Bank
A10: 22892 | B10: 109 | C10: Bank | D10: Bank | J10: 718114 | K10: =J10*0.01 -> 7181.14
A11: 1229 | B11: 110 | C11: Debit Card - 4341 7600 3761 2610 | D11: Bank
A12: =A10+A11 -> 24121 | B12: 111 | C12: Lawyers Trust Account | D12: Current Asset
B13: 112 | C13: Accountant Trust Account | D13: Current Asset
B14: 115 | C14: Suspense - Waiting to be Reconciled | D14: Current Asset
B15: 121 | C15: WIP - Construction | D15: Current Asset
B16: 122 | C16: WIP - Prepayment | D16: Current Asset
B17: 130 | C17: Bobcat | D17: Current Asset
B18: 131 | C18: Truck | D18: Current Asset
B19: 132 | C19: Excavator | D19: Current Asset
B20: 650 | C20: Shares in Tekna | D20: Non Current Assets
B21: 6501 | C21: Shares in Tekna Homes | D21: Non Current Assets
B22: 6502 | C22: Shares in Tekna Drafting | D22: Non Current Assets
B23: 6503 | C23: Shares in Tekna Admin | D23: Non Current Assets
B24: 651 | C24: Private Shares - Limeco | D24: Non Current Assets
B25: 660 | C25: Units in Clausen Street Unit Trust | D25: Non Current Assets | J25: October Closing WIP
B26: 670 | C26: Gold Bullion | D26: Non Current Assets
B27: 671 | C27: Silver Bullion | D27: Non Current Assets
B28: 675 | C28: Crypto | D28: Non Current Assets
B29: 677 | C29: ASX - Share Purchase | D29: Non Current Assets
B30: 678 | C30: Alperton Road Shed | D30: Non Current Assets
B31: 679 | C31: Shared Equity Loans - Khyiroya | D31: Non Current Assets
B32: 680 | C32: Shared Equity Loans - Mansfield | D32: Non Current Assets
B33: 681 | C33: Purchase - Unit 5/8 Nevilles Street | D33: Non Current Assets
B34: 682 | C34: Capital Costs - Unit 5/8 Nevilles Street | D34: Non Current Assets
B35: 683 | C35: Depreciation - Unit 5/8 Nevilles Street | D35: Non Current Assets
B36: 725 | C36: Cabinet Making Machinery | D36: Fixed Asset
B38: 200 | C38: Sales | D38: Revenue
... B102: 404 | C102: Bank Fees | D102: Expense
B103: 4041 | C103: Brokage Fee
B104: 405 | C104: Safety Deposit Box Fees | D104: Expense
B105: 406 | C105: Debt Forgiveness And Uncollectable Investments | D105: Expense
B106: 407 | C106: Crypto Capital Loss | D106: Expense
B107: 408 | C107: Cleaning GST Free | D107: Expense | Q107: 2872978.2
B108: 412 | C108: Consulting & Accounting | D108: Expense | Q108: 1527672.9
B109: 414 | C109: Training Expenses | D109: Expense
B110: 416 | C110: Depreciation | D110: Expense | Q110: =Q107-Q108 -> 1345305.3
B111: 420 | C111: Entertainment | D111: Expense
B112: 425 | C112: Freight & Courier | D112: Expense
B113: 426 | C113: ASIC Filing Fee | D113: Expense
B114: 4261 | C114: ASIC Fees GST Free | D114: Expense
B115: 427 | C115: Other ASIC Fees | D115: Expense
B116: 428 | C116: Tekna Kitchen Materials | D116: Expense
B117: 429 | C117: General Expenses | D117: Expense
B118: 430 | C118: Expense Waiting on Reimbursement | D118: Expense
B119: 433 | C119: Insurance GST Free | D119: Expense
B120: 4331 | C120: Insurance GST Inc | D120: Expense
B121: 434 | C121: Licences & Licence Renewals | D121: Expense
B122: 437 | C122: Interest Expense | D122: Expense
... B124: 441 | C124: Legal Expenses GST Inc | D124: Expense
B125: 4411 | C125: Legal Expenses GST Free
B126: 442 | C126: LYW - Reimbursement Fees | D126: Expense
B127: 445 | C127: Light, Power, Heating | D127: Expense
B128: 449 | C128: M/V - Running Costs | D128: Expense
B129: 450 | C129: M/V - Repairs and Service | D129: Expense
B130: 451 | C130: M/V - Rego and Insurance | D130: Expense
B131: 452 | C131: M/V Fuel | D131: Expense
B132: 453 | C132: Office Expenses | D132: Expense
B133: 461 | C133: Printing & Stationery | D133: Expense
B134: 469 | C134: Rent | D134: Expense
B135: 473 | C135: Repairs and Maintenance | D135: Expense
B136: 475 | C136: Joii Wages | D136: Expense
B137: 4751 | C137: Tekna Trades Wages | D137: Expense
... B165: 835 | C165: Income Tax Payable | D165: Current Liability
A166: Team Harder Family Trust | B166: 900 | C166: Loan - Team Harder Family Trust | D166: Non Current Liability
B167: 901 | C167: Loan - The Harder Family Trust | D167: Non Current Liability
B168: 902 | C168: Loan - Gen2612 | D168: Non Current Liability
B169: 903 | C169: Loan - LATL | D169: Non Current Liability
B170: 904 | C170: Loan - Robert Harder | D170: Non Current Liability
B171: 905 | C171: Loan - Rachel Harder | D171: Non Current Liability
B172: 906 | C172: Loan - Jared Harder | D172: Non Current Liability
B173: 907 | C173: Loan - Grace Harder | D173: Non Current Liability
B174: 908 | C174: Loan - Sophie Harder | D174: Non Current Liability
B175: 909 | C175: Loan - Rachel Harder / Kids | D175: Non Current Liability
B176: 910 | C176: Loan - AR Clement Investments | D176: Non Current Liability
B177: 911 | C177: Loan - Team Harder Super Investments | D177: Non Current Liability
B178: 912 | C178: Loan - Harder Developments | D178: Non Current Liability
... B188: 922 | C188: Loan - Samuel Harder | D188: Non Current Liability
B189: 923 | D189: Non Current Liability
B190: 924 | D190: Non Current Liability
B191: 925 | C191: Loan - Other | D191: Non Current Liability
B192: 926 | C192: Loan - Jonathan Ament | D192: Non Current Liability
B193: 930 | C193: Rent In Advance - Unit 5/8 Nevilles Street | D193: Non Current Liability
B194: 931 | C194: Loan - W2G Assets | D194: Non Current Liability
B195: 932 | C195: Loan - Livin The Dream | D195: Non Current Liability
B196: 935 | C196: Loan - Homes of Hope | D196: Non Current Liability
B197: 951 | C197: Loan - 160 Alperton Road | D197: Non Current Liability
B198: 954 | C198: Promissory Note 1 | D198: Non Current Liability
B199: 955 | C199: Promissory Note 2 | D199: Non Current Liability
B200: 956 | C200: Promissory Note 3 | D200: Non Current Liability
B201: 957 | C201: Promissory Note 4 | D201: Non Current Liability
...

Sheet Sheet2
B3: 484000
B4: 123920
B5: 279980
B6: 3000
B7: =SUM(B3:B6) -> 890900
B9: 69000
B10: 15000
B11: =B9+B10 -> 84000 | D11: 25 | F11: =B11*D11 -> 2100000

Sheet Balance Sheet Reconcile
C1: Loans to or from | E1: Bank Account
A2: Account Number | C2: Account Number | D2: Name of Account | E2: Account Number | F2: Name of Account
A3: 911 | B3: Team Harder Super Investments | C3: 902 | D3: Loan - Gen2612 | E3: 101 | F3: NAB - Team Harder Super Investments
C4: 931 | D4: Loan - W2G Assets | E4: 102 | F4: NAB Share Trade Account - Team Harder Super Investments
A6: 931 | B6: W2G Assets | C6: 911 | D6: Loan - Team Harder Super Investments | E6: 101 | F6: NAB - W2G Assets
C7: 916 | D7: Loan - Tekna Drafting | E7: 102 | F7: NAB Share Trade Account - W2G Assets
E8: 103 | F8: BOQ - W2G Assets
E9: 104 | F9: BOQ LOC - W2G Assets - Unit 5/8 Nevilles Street
A11: 902 | B11: Gen2612 | C11: 900 | D11: Loan - Team Harder Family Trust | E11: 101 | F11: NAB - Gen2612
C12: 905 | D12: Loan - Rachel Harder | E12: 102 | F12: Crypto Credit Card
C13: 911 | D13: Loan - Team Harder Super Investments
B14: Nothing to link to | C14: 914 | D14: Loan - Team Harder Family Reimburse
C15: 915 | D15: Loan - Tekna
B16: Nothing to link to | C16: 918 | D16: Loan - Tekna Licence To Reimburse
B17: Nothing to link to | C17: 920 | D17: Loan Plug Investments
C18: 935 | D18: Loan - Homes of Hope
A20: 900 | B20: Team Harder Family Trust | C20: 902 | D20: Loan - Gen2612 | E20: 101 | F20: NAB - Team Harder Family Trust
C21: 905 | D21: Loan - Rachel Harder | E21: 102 | F21: NAB - Trust Tithe - HFTH
C22: 906 | D22: Loan - Jared Harder
C23: 907 | D23: Loan - Grace Harder
C24: 908 | D24: Loan - Sophie Harder
A26: 915 | B26: Tekna | C26: 902 | D26: Loan - Gen2612 | E26: 101 | F26: NAB - Tekna
C27: 916 | D27: Loan - Tekna Drafting
C28: 917 | D28: Loan - Tekna Licence
B29: Nothing to link to | C29: 920 | D29: Loan - Plug Investments
A31: 917 | B31: Tekna Licence | C31: 915 | D31: Loan - Tekna | E31: 101 | F31: NAB - Tekna Licence
A33: 916 | B33: Tekna Drafting | C33: 905 | D33: Loan - Rachel Harder | E33: 101 | F33: NAB - Tekna Drafting
C34: 915 | D34: Loan - Tekna
C35: 931 | D35: Loan - Tekna Drafting

Sheet Sheet1
B2: Given Names | C2: Family Name | D2: Date Of Birth | E2: Place of Birth | F2: State | G2: Country | H2: Residential Address | I2: TFN | J2: Directors ID
B3: Andrew Mark | C3: Clement | D3: 24491 | E3: Dunstable | G3: England | H3: 2 Winterpeak Close Yarrabilba QLD 4207 | I3: 490 268 825 | J3: 036 535 452 319 643

Sheet Director Details (2)
B1: Given Names | C1: Family Name | D1: Director Number | E1: Date Of Birth | F1: Place of Birth | G1: State | H1: Country | I1: Residential Address | J1: TFN | K1: Directors ID
B2: Aaron Thomas | C2: Glowka | D2: 1 | E2: 31153 | F2: Toowoomba | G2: QLD | H2: Australia | I2: 37 Blackthorn Cresent Shailer Park QLD 4128 | K2: 036 670 980 487 618
B3: David John | C3: Linney | D3: 0 | E3: 24978 | F3: Totternhoe, | H3: England | I3: 4 Muirfield Court Cornubia QLD 4130 | K3: 036 434 217 004 867
B4: David | C4: Palmer | E4: 22091 | F4: Gympie | G4: QLD | H4: Australia | I4: 7 Harlech Court Cornubia QLD 4130 | J4: 486 950 227
B5: Kaab
B7: Andrew Mark | C7: Clement | E7: 24491 | F7: Dunstable | H7: England | I7: 2 Winterpeak Close Yarrabilba QLD 4207 | J7: 490 268 825 | K7: 036 535 452 319 643
B9: Rachel Anne | C9: Harder | E9: 26510 | F9: Glenelg | G9: SA | H9: Australia | I9: 162 Alperton Road Burbank QLD 4156 | J9: 171 927 425 | K9: 036 36387 94301 79
B10: Robert John | C10: Harder | E10: 26507 | F10: Burnie | G10: QLD | H10: Australia | I10: 162 Alperton Road Burbank QLD 4156 | J10: 173 955 316 | K10: 036 00187 50300 93
B12: Jared Sa-Bin | C12: Harder | E12: 36724 | F12: Inchon | H12: South Korea | I12: 162 Alperton Road Burbank QLD 4156 | K12: 036 66785 14102 28
B13: Samuel James | C13: Harder | E13: 36659 | F13: East Fremantle | G13: WA | H13: Australia | I13: 13 English Place Rochedale QLD 4123 | J13: 971 295 981 | K13: 036 723 294 953 150
B17: Christine Leanne | C17: Harder | I17: 13 English Place Rochedale QLD 4123 | K17: 036 20243 44207 73 | L17: Plug Developments | M17: Plug Property Trust and Plug Family trust
B18: James Jonathan | C18: Harder | D18: 0438 765 935 | E18: 25904 | F18: Burnie | G18: Tasmania | H18: Australia | I18: 13 English Place Rochedale QLD 4123 | K18: 036 98079 72594 73 | L18: Plug investments
B21: Kate Harder | E21: 35941
E23: 1967
B24: 1000000 | E24: 2023
B26: 5483.41 | C26: =B26/B24 -> 0.00548341 | E26: =E24-E23 -> 56
B28: Andrew Clement | C28: Licence Number | D28: 48976
C29: Tekna Homes | D29: 15344273 | I29: 0

Sheet Director Details
B1: Given Names | C1: Family Name | D1: Director Mobile | E1: Drivers Licence | F1: Date Of Birth | G1: Place of Birth | H1: State | I1: Country | J1: Residential Address | K1: TFN | L1: Directors ID
B2: Aaron Thomas | C2: Glowka | D2: 1 | F2: 31153 | G2: Toowoomba | H2: QLD | I2: Australia | J2: 37 Blackthorn Cresent Shailer Park QLD 4128 | L2: 036 670 980 487 618
B4: Andrew Mark | C4: Clement | D4: 0407 150 081 | F4: 24491 | G4: Dunstable | I4: England | J4: 2 Winterpeak Close Yarrabilba QLD 4207 | K4: 490 268 825 | L4: 036 535 452 319 643
B6: Rachel Anne | C6: Harder | D6: 0409 397 541 | F6: 26510 | G6: Glenelg | H6: SA | I6: Australia | J6: 160 Alperton Road Burbank QLD 4156 | K6: 171 927 425 | L6: 036 36387 94301 79
B7: Robert John | C7: Harder | D7: 0407 397 541 | F7: 26507 | G7: Burnie | H7: QLD | I7: Australia | J7: 160 Alperton Road Burbank QLD 4156 | K7: 173 955 316 | L7: 036 00187 50300 93
B9: Jared Sa-Bin | C9: Harder | F9: 36724 | G9: Incheon | I9: South Korea | J9: 160 Alperton Road Burbank QLD 4156 | L9: 036 66785 14102 28
B10: Samuel James | C10: Harder | F10: 36659 | G10: East Fremantle | H10: WA | I10: Australia | J10: 13 English Place Rochedale QLD 4123 | K10: 971 295 981 | L10: 036 723 294 953 150
B11: Sophie Mee-jeong | C11: Harder | D11: 0466 316 357 | F11: 38585 | G11: Seoul | I11: South Korea | J11: 160 Alperton Road Burbank QLD 4156 | K11: 633 256 457 | L11: 036 58056 41156 78
B14: Christine Leanne | C14: Harder | J14: 13 English Place Rochedale QLD 4123 | L14: 036 20243 44207 73 | M14: Plug Developments | N14: Plug Property Trust and Plug Family trust
B15: James Jonathan | C15: Harder | D15: 0438 765 935 | F15: 25904 | G15: Burnie | H15: Tasmania | I15: Australia | J15: 13 English Place Rochedale QLD 4123 | L15: 036 98079 72594 73 | M15: Plug investments
B18: Jake | C18: Baird | F18: 32760 | K18: 855 572 024
B27: Andrew Clement | C27: Licence Number | D27: 48976
C28: Tekna Homes | D28: 15344273 | J28: 0

Sheet Rachel Directorship
E1: Start Date | G1: Resigned
D2: Company Incorporated | E2: Director | F2: Secretary | G2: Director | H2: Secretary | I2: Purpose | K2: Part of Group
C3: Gen2612 | D3: 31/03/2022 | E3: 44651 | F3: 44651 | I3: Loans and Family Investments | K3: Team Harder Family Trust
C4: PROV 1322 Global | D4: 44716 | E4: 44657 | F4: 44657 | I4: Corporate Trustee | K4: Team Harder Family Trust
C5: Team Harder Super Investments | D5: 44662 | E5: 44662 | F5: 44662 | I5: Investments and Developments | K5: Team Harder Family Trust ( should be currently part of Super Fund)
C6: W2G Assets | D6: 36655 | E6: 36655 | F6: 40875 | I6: Investments and Developments | K6: Team Harder Family Trust ( should be currently part of Super Fund)
C7: AR Clement Investments | D7: 40393 | E7: 44666 | F7: 44666 | G7: 44937 | H7: 44666 | I7: Investments and Developments | J7: Struck Off | K7: Team Harder Family Trust ( should be currently part of Super Fund)
C8: JRANDL | D8: 42410 | E8: 44666 | F8: 44666 | G8: 44944 | H8: 44944 | I8: Investments and Developments | J8: Struck Off | K8: Team Harder Family Trust ( should be currently part of Super Fund)
C9: Team Harder | D9: 23/10/2020 | E9: 44127 | I9: Corporate Trustee | K9: Team Harder Super Fund
C11: Harder Investments | D11: 34585 | E11: 35431 | F11: 35431 | G11: 44547 | H11: 44547 | I11: Corporate Trustee | K11: Old Super fund with Brother
C12: Harder Developments | D12: 35150 | E12: 35157 | F12: 35157 | G12: 44662 | H12: 44662 | I12: Corporate Trustee | J12: Struck Off | K12: Old Family Trust Group
C13: LATL | D13: 40393 | E13: 44497 | F13: 44497 | G13: 44948 | H13: 44948 | I13: Loans and Family Investments | J13: Struck Off | K13: Old Family Trust Group
C14: Harder Family | D14: 41115 | E14: 44658 | F14: 44658 | G14: 44948 | H14: 44948 | I14: Corporate Trustee | J14: Struck Off | K14: The Harder Family Trust
C15: Love Your WorLd | D15: 41066 | E15: 41249 | F15: 43160 | G15: 44663 | H15: 44663 | I15: Charity | J15: Liquidation
C16: The Promise QLD | D16: 41039 | E16: 44010 | F16: 44010 | G16: 44936 | H16: 44936 | I16: Charity | J16: Struck Off
C17: Joii ACLA | D17: 43595 | E17: 43595 | F17: 43595 | G17: 44609 | H17: 44609 | I17: Charity | J17: Struck Off
C18: Joii ACLP | D18: 43595 | E18: 43595 | F18: 43595 | G18: 44603 | H18: 44603 | I18: Charity | J18: Struck Off
C19: Joii Credit License Management | D19: 43595 | E19: 43595 | F19: 43596 | G19: 44602 | H19: 44602 | I19: Charity | J19: Struck Off
C20: Joii Securities | D20: 43595 | E20: 43595 | F20: 43595 | G20: 44602 | H20: 44602 | I20: Charity | J20: Struck Off
C22: Harder Enterprises | E22: 36627 | F22: 36627 | G22: 40213 | H22: 40213
C23: Omtra | E23: 39773 | G23: 40711
C24: Privium Assets | E24: 40380 | F24: 40380 | G24: 40393 | H24: 40393
C25: Privium Group | E25: 37429 | F25: 37429 | G25: 40443 | H25: 40395
C26: Total Design | E26: 39762 | F26: 39762 | G26: 40233 | H26: 40233
C27: W2G (VIC) | E27: 36705 | F27: 36705 | G27: 39393 | H27: 39393

Sheet Logon
A2: ASIC Agent Number | B2: 38687
A3: User Name | B3: Multiplace
A4: Password | B4: A010Australia$
A6: Email | B6: david@multiplace.com.au
A7: Mobile | B7: 0468 349 295
A9: PO Box | B9: PO Box 7066 Loganholme 4129
A11: Xero manager | B11: admin@multiplace.com.au
B12: X010AustraliaNZ

Sheet  Team Plug
C1: TFN | D1: ACN | E1: ABN
B2: Plug Investments | C2: 918 321 460 | D2: 145 576 030 | E2: 57 145 576 030
B3: Plug Developments | C3: 938 155 618 | D3: 138 616 494 | E3: 38 138 616 494
B4: Harder Investments | D4: Har
B5: Harder Investments ATF The Harder Super Fund | C5: 99 460 226 | E5: 15 429 780 282
B6: Plug Family Trust | C6: 910 104 450 | E6: 98 327 124 629

Sheet  Tekna Group
A1: Group | C1: Company | D1: Corporate Key | E1: User Name | F1: Password | G1: What City was i born in? | H1: Answer | I1: ACN | J1: abn | K1: TFN | L1: Established Date | M1: Director | N1: Drivers Licence | O1: Review Date | P1: Amount Owing | Q1: Amount of Shares | R1: Shareholder | S1: Registered | T1: Principle Place of Business | U1: Activity | V1: what to Do
A2: Tekna | B2: XERO | C2: Tekna | D2: 94512428 | E2: andrew@tekna.com.au | F2: J4sper20!0 | G2: What City was I Born In? | H2: Glenelg | I2: 658 462 394 | J2: 43 658 462 394 | K2: 605 934 917 | L2: 31/03/2022 | M2: Andrew Mark Clement | N2: 013 183 981 | O2: 45382 | P2: 0 | Q2: 55/35/10 | R2: THFT , PFT and Jonno | S2: 160 ALPERTON ROAD , BURBANK QLD 4156 | T2: 160 ALPERTON ROAD , BURBANK QLD 4156 , Australia | U2: head of group
A3: Tekna | B3: XERO | C3: Tekna Drafting (formerly Rock Invest Qld) | D3: 10135027 | E3: rach@100xbestlife.com | F3: J4sper20!0 | G3: What City was I Born In? | H3: Glenelg | I3: 159 565 849 | J3: 96 159 565 849 | K3: 938 078 821 | L3: 19/07/2012 | M3: Andrew Mark Clement | N3: 013 183 981 | O3: 45492 | P3: 0 | Q3: 100 | R3: Tekna | S3: 160 ALPERTON ROAD , BURBANK QLD 4156 | T3: 160 ALPERTON ROAD , BURBANK QLD 4156 , Australia | U3: drafting
A4: Tekna | B4: XERO | C4: Tekna Homes formerly Tekna Licence | D4: 56845790 | E4: rachel@tekna.com.au | F4: J4sper20!0 | G4: What City was I Born In? | H4: Glenelg | I4: 658 462 732 | J4: 34 658 462 732 | K4: 605 934 180 | L4: 31/03/2022 | M4: Andrew Mark Clement | N4: 013 183 981 | O4: 45382 | P4: 0 | Q4: 100 | R4: Tekna | S4: 160 ALPERTON ROAD , BURBANK QLD 4156 | T4: 160 ALPERTON ROAD , BURBANK QLD 4156 , Australia | U4: licence
A5: Tekna | B5: XERO | C5: Tekna Admin Pty LTd | D5: 42468380 | E5: andrew@tekna.com.au | F5: J4sper20!0 | G5: What City was I Born In? | H5: Glenelg | I5: 673 388 424 | J5: 81 673 388 424 | K5: 518 585 770 | L5: 45264 | M5: Andrew Mark Clement | N5: 013 183 981 | O5: 45630 | S5: 160 ALPERTON ROAD , BURBANK QLD 4156 | T5: 160 ALPERTON ROAD , BURBANK QLD 4156 , Australia
C6: The Promise Pty Ltd | D6: 27845006
I9: Tekna QBCC Licence | K9: 15344273
C10: Tekna Holding
C12: Prov1322 Global | D12: 145 | E12: =D12/$D$16 -> 0.725
C13: Plug Developments | D13: 35 | E13: =D13/$D$16 -> 0.175
C14: Jonno | D14: 10 | E14: =D14/$D$16 -> 0.05 | J14: 6500 | K14: 4 | L14: =J14/K14 -> 1625
C15: Sam | D15: 10 | E15: =D15/$D$16 -> 0.05 | J15: 1800
D16: =SUM(D12:D15) -> 200 | J16: =J14/J15 -> 3.6111111
M26: =L26/L25 -> #DIV/0!

Sheet  Team Harder
A1: Group | C1: Company | D1: Corporate Key | E1: User Name | F1: Password | G1: What City was i born in? | H1: Answer | I1: Carry Forward losses | J1: Franking Balance | K1: Bank Name | L1: BSB | M1: Account | N1: ACN | O1: abn | P1: TFN | Q1: Registered GST | R1: Cash/Accural | S1: Established Date | T1: Director | U1: Review Date | V1: Amount Owing | W1: Amount of Shares | X1: Shareholder | Y1: Registered | Z1: Principle Place of Business | AA1: Activity | AB1: what to Do
A2: Team Harder | B2: Xero | C2: Gen2612 | D2: 8860820 | E2: rach@100xbestlife.com | F2: J4sper20!0 | G2: What City was I Born In? | H2: Glenelg | K2: Gen2612 | L2: 084 435 | M2: 767243550 | N2: 658 463 659 | O2: 47 658 463 659 | P2: 605 934 566 | Q2: Registered | S2: 31/03/2022 | T2: Rachel Anne Harder | U2: 31/03/2023 | V2: 0 | W2: 100 | X2: ATF Team Harder Family Trust | Y2: MAGNUS BUSINESS ADVISERS AND ACCOUNTANTS, UNIT 10 , 39 OLD CLEVELAND ROAD , CAPALABA QLD 4157 | Z2: 160 ALPERTON ROAD , BURBANK QLD 4156 , Australia | AA2: Bucket Company
A3: Team Harder | C3: Prov1322 Global | D3: 32350239 | E3: rach@100xbestlife.com | F3: J4sper20!0 | G3: What City was I Born In? | H3: Glenelg | N3: 658 602 478 | O3: 34 658 602 478 | P3: 606 189 260 | S3: 44716 | T3: Rachel Harder | U3: 45081 | V3: 0 | W3: 100 | X3: Rachel Harder | Y3: MAGNUS BUSINESS ADVISERS AND ACCOUNTANTS, UNIT 10 , 39 OLD CLEVELAND ROAD , CAPALABA QLD 4157 | Z3: 160 ALPERTON ROAD , BURBANK QLD 4156 , Australia
A4: Team Harder | B4: MYOB | C4: Prov1322 Global ATF Team Harder Family Trust | F4: J4sper20!0 | G4: What City was I Born In? | H4: Glenelg | K4: Team Harder Family Trust | L4: 084 435 | M4: 959276787 | O4: 94 633 472 433 | P4: 605 725 602 | Q4: Registered | R4: Cash | AA4: Family Trust
A5: Team Harder | C5: Robert Harder | O5: 93 373 928 858 | P5: 173 955 316
A6: Team Harder | C6: Rachel Harder | P6: 171 927 425
A7: Team Harder | C7: Jared Harder | P7: 965 171 018
A8: Team Harder | C8: Grace Harder | P8: 633 256 177
A9: Team Harder | C9: Sophie Harder | P9: 633 256 457
A10: Team Harder Super Fund GROUP | B10: Dave | C10: Team Harder | D10: 16724280 | E10: rach@100xbestlife.com | F10: J4sper20!0 | G10: What City was I Born In? | H10: Glenelg | N10: 645 359 495 | S10: 23/10/2020 | T10: Rachel Anne Harder | U10: 45222 | V10: 620 | W10: 100 | X10: Robert and Rachel | Y10: MAGNUS BUSINESS ADVISERS AND ACCOUNTANTS, UNIT 10 , 39 OLD CLEVELAND ROAD , CAPALABA QLD 4157 | Z10: OFFICE 6 / 2404 LOGAN ROAD EIGHT MILE PLAINS QLD 4113
A11: Team Harder Super Fund GROUP | B11: Dave | C11: Team Harder ATF Team Harder Super Fund | E11: rach@100xbestlife.com | F11: J4sper20!0 | G11: What City was I Born In? | H11: Glenelg | K11: Team Harder Super Fund | L11: 083 052 | M11: 304656703 | O11: 17 209 120 631 | P11: 534 254 470
A12: Team Harder Super Fund GROUP | B12: MYOB | C12: Team Harder Super Investments | D12: 24400857 | E12: rach@100xbestlife.com | F12: J4sper20!0 | G12: What City was I Born In? | H12: Glenelg | K12: Team Harder Super Investments | L12: 084 435 | M12: 259449309 | N12: 658 706 597 | O12: 32 658 706 597 | P12: 608 117 219 | Q12: Not Registered | S12: 44662 | T12: Rachel Harder | U12: 45027 | V12: 0 | W12: 100 | X12: ATF Team Harder Super Fund | Y12: MAGNUS BUSINESS ADVISERS AND ACCOUNTANTS, UNIT 10 , 39 OLD CLEVELAND ROAD , CAPALABA QLD 4157 | Z12: 160 ALPERTON ROAD , BURBANK QLD 4156 , Australia | AA12: Investment for Super Fund
A13: Team Harder Super Fund GROUP | B13: MYOB | C13: W2G Assets | D13: 87081049 | E13: w2gasset | F13: J4sper20!0 | G13: What City was I Born In? | H13: Adelaide | N13: 092 659 688 | O13: 59 092 659 688 | P13: 726 881 624 | S13: 36655 | T13: Rachel Harder | U13: 45055 | V13: 276 | W13: 1000 | X13: Team Harder Super Investments | Y13: MAGNUS BUSINESS ADVISERS AND ACCOUNTANTS, UNIT 10 , 39 OLD CLEVELAND ROAD , CAPALABA QLD 4157 | Z13: 160 ALPERTON ROAD , BURBANK QLD 4156 , Australia
K26: 9079 | L26: 7478 | O26: 7800
K27: 9060 | L27: 7641 | M27: =K26-L27 -> 1438 | O27: 340
K28: =K26-K27 -> 19 | L28: =L26-L27 -> -163 | O28: =O26-O27 -> 7460
L30: 163
L31: 70
L32: =L30+L31 -> 233

Sheet Insurance Cover
A1: Cover | B1: Insured | C1: Start Date | D1: Renewal Date | E1: Monthly/Annual Payment | F1: Broker / Insurer | G1: Broker Name | H1: email | I1: Contact Number | K1: Policy Number
A2: House & Contents including small Business | B2: Rachel Harder - Invoiced to Tekna Homes | C2: 14.11.2023 | D2: 14.11.2024 | E2: $15,196.46 / $1,405.98 | F2: Shielded Insurance | G2: Tim Cantwell | H2: tim@shieldedinsurance.com.au | I2: P: 07 3710 8289 | J2: CGU | K2: 06H0502850
A4: Construction Works & Public/Products Liability | B4: Tekna Homes | C4: 28.11.2023 | D4: 28.11.2024 | E4: $5483.41 pa | F4: HIA/AON | G4: Dianne Thompson | H4: dianne.a.thompson@aon.com | I4: W: 3012 0791 M: 0416 287 476 | K4: 323105456CAR
A6: Defigo Commercial Motor Vehicle - Excavator | B6: Rachel Harder | C6: 30.06.2023 | D6: 230.03.2024 | E6: $137.09 m / 1490.25 pa | F6: HIA/AON | G6: Dianne Thompson | H6: dianne.a.thompson@aon.com | I6: W: 3012 0791 M: 0416 287 477 | J6: need to separate personal entities that just for say the directors o | K6: 446360PAMI
A7: Bobcat | B7: Tekna Admin
A8: Isuzu Truck | B8: Tekna Admin
A9: Professional Indemnity & Liability | B9: Tekna, Tekna Drafting, Tekna Homes | C9: 21.12.2022 | D9: 21.12.2023 | E9: $2050 pa | F9: Austcover | G9: Becky Maddison / | H9: becky.maddison@austcover.com.au | I9: P: 07 3237 8619 M: 0455 941 601 | J9: Dual WebRater | K9: AU00010775000/AU00010776000
G10: Dean Brumby | H10: dean.brumby@austcover.com.au
A11: Directors Insurance

Sheet SVL
A1: 0.26 | E1: Average Price | H1: 0.165 | I1: 0.2 | J1: 0.25 | K1: 0.3 | L1: 0.4 | M1: 0.5 | N1: 0.75 | O1: 1 | P1: 1.5 | Q1: 3 | R1: 5 | S1: 10 | T1: 25 | U1: 50 | V1: 100
A2: . | B2: Team Harder Super Investments | D2: 2900000 | E2: 0.179 | F2: =D2*E2 -> 519100
B3: Team Harder Family Trust | D3: 9050000 | E3: 0.235 | F3: =D3*E3 -> 2126750
B4: W2G Assets | D4: 3500000 | E4: 0.2288 | F4: =D4*E4 -> 800800
B5: Team Harder Super Fund | D5: 4855000 | E5: 0.2476 | F5: =D5*E5 -> 1202098
D6: =SUM(D2:D5) -> 20305000 | E6: =F6/D6 -> 0.22894597 | F6: =SUM(F2:F5) -> 4648748 | H6: =$D$6*H1 -> 3350325 | I6: =$D$6*I1 -> 4061000 | J6: =$D$6*J1 -> 5076250 | K6: =$D$6*K1 -> 6091500 | L6: =$D$6*L1 -> 8122000 | M6: =$D$6*M1 -> 10152500 | N6: =$D$6*N1 -> 15228750 | O6: =$D$6*O1 -> 20305000 | ... V6: =$D$6*V1 -> 2030500000
D7: =D2+D3+D5 -> 16805000 | E7: =F7/D7 -> 0.22897638 | F7: =F2+F3+F5 -> 3847948
D8: =E8/F6 -> 0.1356391 | E8: =F8-F6 -> 630552 | F8: =D6*A1 -> 5279300
B9: Blessing Account
B10: Lisa Moore | D10: 5000 | H10: =$D$10*H1 -> 825 | I10: =$D$10*I1 -> 1000 | J10: =$D$10*J1 -> 1250 | K10: =$D$10*K1 -> 1500 | L10: =$D$10*L1 -> 2000 | M10: =$D$10*M1 -> 2500 | N10: =$D$10*N1 -> 3750 | O10: =$D$10*O1 -> 5000 | ... V10: =$D$10*V1 -> 500000
B11: Warners | D11: 5000 | H11: =$D$11*H1 -> 825 | I11: =$D$11*I1 -> 1000 | J11: =$D$11*J1 -> 1250 | K11: =$D$11*K1 -> 1500 | L11: =$D$11*L1 -> 2000 | M11: =$D$11*M1 -> 2500 | N11: =$D$11*N1 -> 3750 | O11: =$D$11*O1 -> 5000 | ... V11: =$D$11*V1 -> 500000
B12: John and Sue | D12: 5000 | H12: =$D$11*H1 -> 825 | I12: =$D$12*I1 -> 1000 | J12: =$D$12*J1 -> 1250 | K12: =$D$12*K1 -> 1500 | L12: =$D$12*L1 -> 2000 | M12: =$D$12*M1 -> 2500 | N12: =$D$12*N1 -> 3750 | O12: =$D$12*O1 -> 5000 | P12: =$D$12*P1 -> 7500 | ... V12: =$D$12*V1 -> 500000
B13: David and Jess Quack | D13: 5000 | H13: =$D$11*H1 -> 825 | I13: =$D$11*I1 -> 1000 | J13: =$D$11*J1 -> 1250 | K13: =$D$11*K1 -> 1500 | L13: =$D$11*L1 -> 2000 | M13: =$D$11*M1 -> 2500 | N13: =$D$11*N1 -> 3750 | O13: =$D$11*O1 -> 5000 | ... V13: =$D$11*V1 -> 500000
B15: Average Price Without W2G Assets | C15: 0.22891 | D15: =F7 -> 3847948 | E15: =F15-D15 -> 521352 | F15: =D7*A1 -> 4369300
B16: Average Price With W2G @ 13 cents | C16: 0.2118 | D16: 4278888 | E16: =F16-D16 -> 1000412 | F16: =D6*A1 -> 5279300
E18: =E16-E8 -> 369860
A21: Ounces Purchased | B21: Purchase Price | D21: Purchase Price in AUS per Oz | F21: Current Price in AUS per Ounce | H21: Current Value | J21: Current Profit | L21: % Increase
A22: 85.55 | B22: 203832.8 | D22: =B22/A22 -> 2382.616 | F22: 3015.46 | H22: =A22*F22 -> 257972.6 | J22: =H22-B22 -> 54139.803 | L22: =J22/B22 -> 0.26560889
A23: 16947 | B23: 517474 | D23: =B23/A23 -> 30.534844 | F23: 38.34 | H23: =A23*F23 -> 649747.98 | J23: =H23-B23 -> 132273.98 | L23: =J23/B23 -> 0.25561474

Sheet Tekna Models
B2: Team Harder Family Trust | C2: 0.6 | E2: Plug Family Trust | F2: 0.4
B5: Tekna Homes Master Franchise Agreement | F5: 0.33 | G5: Income received from all Franchise Fees Paid
B8: Tekna | K8: Tekna Share Holding
K9: Jonno | L9: 0.1
K10: THFT | L10: 0.55
K11: PFT | L11: 0.35
B13: Tekna Drafting | E13: Tekna Licence | G13: Tekna Homes | I13: Tekna JV
B14: Own Licence to use T3D with Drafting | E14: Sells Licensing to use T3D | G14: Sells Franchise Agreements
E15: Current Sales | G15: Sells Licensing Agreement | I15: Hybrid Model
E16: Tekna Drafting | I16: We sign clients here and receive income from bank
E17: AFG Group which lets Torsion Homes Use it | I17: We purchase all Supplier to build house of New Company
J19: Company A T/A Tekna Homes Share Strucutre 80/20 | K19: This is not a licenced Building Company, only a reseller of Goods
I21: Create special share for 100 paid up capital
I22: Hold 1 % of each build as a retention until 7 year structural warranty is up and then get paid out to Company A once all warranty work has been completed.
B26: Current Steps | I26: Discussion with Laywer
B28: Get Legal Advice | D28: Sign up for 5 years but if don’t sign more than 5 franchises we can exit deal. | I28: All marketing material is put in separate fund for 50/50 JV Local marketing initatives, if not used then gifted to local charity. ( If possible without to much overhead we will track rebate to specific areas
B29: Get Price to run trial Campaign to sell houses | D29: Max Spend is 50k | I29: 10% of all income from Licencing agreement goes to our development fund to keep developing software to make us competative.
B30: Find JV Builder to Run Hybrid Model | I30: .5% if build in outside your zone paid to franchise
B31: Get working version of Software | I31: Marketing Committee to decide if we require more than 1% fund and how we spend the marketing money ( cant market on things outside Christian Principles )
B33: House Size (M2) | C33: Cost per m2
B34: 250 | C34: 2000 | E34: =B34*C34 -> 500000
B36: Year 1
B37: 0.03 | C37: =B37*$E$34 -> 15000 | D37: 25 | F37: =C37*D37 -> 375000 | I37: Included if Franchise Fee
B38: 0.025 | C38: =B38*$E$34 -> 12500 | D38: 25 | E38: =D37+D38 -> 50 | F38: =C38*D38 -> 312500 | I38: T3D Costs (including Pure WEB) | J38: Fair use policy
B39: 0.02 | C39: =B39*$E$34 -> 10000 | D39: 25 | E39: =E38+D39 -> 75 | F39: =C39*D39 -> 250000 | I39: Easy- Build Costs | J39: Fair use policy
B40: 0.015 | C40: =B40*$E$34 -> 7500 | D40: 25 | E40: =E39+D40 -> 100 | F40: =C40*D40 -> 187500 | I40: Zoom Meetings
B41: 0.01 | C41: =B41*$E$34 -> 5000 | D41: 25 | E41: =E40+D41 -> 125 | F41: =C41*D41 -> 125000
B42: 0.005 | C42: =B42*$E$34 -> 2500 | D42: 125 | E42: =E41+D42 -> 250 | F42: =C42*D42 -> 312500
D43: =SUM(D37:D42) -> 250 | F43: =SUM(F37:F42) -> 1562500 | I43: Not Included
I44: Office 365
I45: Xero
B46: Bonus if you hit 50 for the Previous Full year | I46: Azure ot Host Easy-Build
B47: 0.025 | C47: =B47*$E$34 -> 12500 | D47: 25 | F47: =C47*D47 -> 312500 | I47: PDF stuff
B48: =B47-0.5% -> 0.02 | C48: =B48*$E$34 -> 10000 | D48: 25 | E48: =D47+D48 -> 50 | F48: =C48*D48 -> 250000 | I48: Drafting Costs | J48: 10m2 for Std Designs
B49: =B48-0.5% -> 0.015 | C49: =B49*$E$34 -> 7500 | D49: 25 | E49: =E48+D49 -> 75 | F49: =C49*D49 -> 187500 | J49: Customs as per quote
B50: =B49-0.5% -> 0.01 | C50: =B50*$E$34 -> 5000 | D50: 25 | E50: =E49+D50 -> 100 | F50: =C50*D50 -> 125000 | I50: Flights and Accomadation to Conferences
B51: =B50-0.5% -> 0.005 | C51: =B51*$E$34 -> 2500 | D51: 150 | E51: =E50+D51 -> 250 | F51: =C51*D51 -> 375000
D52: =SUM(D47:D51) -> 250 | F52: =SUM(F47:F51) -> 1250000
B55: Bonus if you hit 100 for the Previous Full year
B56: 0.02 | C56: =B56*$E$34 -> 10000 | D56: 25 | F56: =C56*D56 -> 250000
B57: =B56-0.5% -> 0.015 | C57: =B57*$E$34 -> 7500 | D57: 25 | E57: =D56+D57 -> 50 | F57: =C57*D57 -> 187500
B58: =B57-0.5% -> 0.01 | C58: =B58*$E$34 -> 5000 | D58: 25 | E58: =E57+D58 -> 75 | F58: =C58*D58 -> 125000
B59: =B58-0.5% -> 0.005 | C59: =B59*$E$34 -> 2500 | D59: 175 | E59: =E58+D59 -> 250 | F59: =C59*D59 -> 437500
D60: =SUM(D56:D59) -> 250 | F60: =SUM(F56:F59) -> 1000000
B63: Bonus if you hit 150 for the Previous Full year
B64: 0.015 | C64: =B64*$E$34 -> 7500 | D64: 25 | F64: =C64*D64 -> 187500
B65: =B64-0.5% -> 0.01 | C65: =B65*$E$34 -> 5000 | D65: 25 | E65: =D64+D65 -> 50 | F65: =C65*D65 -> 125000
B66: =B65-0.5% -> 0.005 | C66: =B66*$E$34 -> 2500 | D66: 200 | E66: =E65+D66 -> 250 | F66: =C66*D66 -> 500000
D67: =SUM(D64:D66) -> 250 | F67: =SUM(F64:F66) -> 812500
B70: Bonus if you hit 200 for the Previous Full year
B71: 0.01 | C71: =B71*$E$34 -> 5000 | D71: 25 | F71: =C71*D71 -> 125000
B72: =B71-0.5% -> 0.005 | C72: =B72*$E$34 -> 2500 | D72: 225 | E72: =D71+D72 -> 250 | F72: =C72*D72 -> 562500
D73: =SUM(D71:D72) -> 250 | F73: =SUM(F71:F72) -> 687500
B76: Bonus if you hit 250 for the Previous Full year
B77: 0.005 | C77: =B77*$E$34 -> 2500 | D77: 250 | F77: =C77*D77 -> 625000
D78: =SUM(D77:D77) -> 250 | F78: =SUM(F77:F77) -> 625000
B81: Cost to use T3D | D81: 2 | E81: T3D
D82: 3 | E82: Easy-Build
D83: =SUM(D81:D82) -> 5
B85: 100 | C85: =B85*$B$34 -> 25000 | D85: =$D$83 -> 5 | F85: =C85*D85 -> 125000
B86: 150 | C86: =B86*$B$34 -> 37500 | D86: =$D$83 -> 5 | F86: =C86*D86 -> 187500
B87: 200 | C87: =B87*$B$34 -> 50000 | D87: =$D$83 -> 5 | F87: =C87*D87 -> 250000
B88: 250 | C88: =B88*$B$34 -> 62500 | D88: =$D$83 -> 5 | F88: =C88*D88 -> 312500
B89: 300 | C89: =B89*$B$34 -> 75000 | D89: =$D$83 -> 5 | F89: =C89*D89 -> 375000

Sheet  Charity
A1: Group | D1: Company | E1: Corporate Key | F1: User Name | G1: Password | H1: What City was i born in? | I1: Answer | J1: Email | K1: 0438 765 935 | L1: abn | M1: TFN | N1: Established Date | O1: Director | P1: Review Date | Q1: Amount Owing | R1: Amount of Shares | S1: Shareholder | T1: Registered | U1: Principle Place of Business
A2: Charity | B2: XERO | D2: Homes of Hope Limited | E2: 99406654 | F2: homesofhopeltd | G2: Bl3ss3d. | H2: What City was I Born In? | I2: Adelaide | J2: hello@joii.org.au | K2: 643 194 156 | L2: 22 643 194 156 | M2: 639 296 766 | N2: 44047 | O2: David , David and Aaron | P2: 45024 | Q2: 0 | R2: Public | T2: OFFICE 6 / 2404 LOGAN ROAD EIGHT MILE PLAINS QLD 4113 | U2: 160 ALPERTON ROAD , BURBANK QLD 4156 , Australia
A3: Charity | B3: XERO | D3: Livin The Dream | E3: 72943215 | F3: livinthedream | G3: Bl3ss3d. | H3: What City was I Born In? | I3: Adelaide | J3: hello@joii.org.au | K3: 142 372 245 | L3: 95 142 372 245 | M3: 913 810 842 | N3: 40240 | O3: James Jonathan Harder | P3: 44988 | Q3: 688 | R3: 100 | S3: Homes Of Hope | T3: OFFICE 6 / 2404 LOGAN ROAD EIGHT MILE PLAINS QLD 4113 | U3: 160 ALPERTON ROAD , BURBANK QLD 4156 , Australia
A4: Charity | B4: XERO | D4: Love Your World | E4: ordered | K4: 158 841 180 | L4: 91 158 841 180 | M4: 942 944 937 | N4: 41066 | O4: David , David and Aaron | P4: 45083 | Q4: 0 | R4: Public | T4: OFFICE 6 / 2404 LOGAN ROAD EIGHT MILE PLAINS QLD 4114 | U4: 160 ALPERTON ROAD , BURBANK QLD 4156 , Australia
A5: Charity | B5: R and D | C5: Want to close | D5: Money Matters | K5: 605 103 615 | L5: 63 605 103 615 | M5: 635 209 293 | N5: 42095 | O5: Aaron Glowka | P5: 45017 | R5: 100 | S5: Love Your World | T5: OFFICE 6 / 2404 LOGAN ROAD EIGHT MILE PLAINS QLD 4114 | U5: 160 ALPERTON ROAD , BURBANK QLD 4156 , Australia
I9: 51106.24
I10: 50405.24
I11: =I9-I10 -> 701

Sheet Wages
B2: Tekna | C2: Tekna Drafting | D2: Tekna Licence
B3: 43 658 462 394 | C3: 96 159 565 849 | D3: 34 658 462 732
A4: Jonno | B4: 1
A5: Jared | B5: 1
A6: Sam | B6: 1
A7: Robert | C7: 0.5 | D7: 0.5
A8: Kate | C8: 1
A9: Grace | D9: 1
A10: Sophie | B10: 1
A11: Off Shore | C11: 1
